Workbook

Sheet Inputs
A1: Project Keystone - Model Inputs and Locked Deal Ledger v1.2
A2: Field | B2: Value | C2: Unit | D2: Status | E2: Source / Ledger ID | F2: Notes
A3: Enterprise value | B3: 108 | C3: $mm | D3: LOCKED | E3: KS-DL-1.2 | F3: Cash-free, debt-free
A4: Seller net debt and debt-like items | B4: 10.2 | C4: $mm | D4: LOCKED | E4: KS-DL-1.2 | F4: Closing estimate
A5: Seller equity value | B5: 97.8 | C5: $mm | D5: DERIVED | E5: EV less seller net debt
A6: Cash consideration | B6: 85.8 | C6: $mm | D6: DERIVED | E6: Seller equity less rollover
A7: Seller rollover | B7: 12 | C7: $mm | D7: LOCKED | E7: KS-DL-1.2 | F7: Founder $8.0m; management $4.0m
A8: Sponsor initial cash equity | B8: 62 | C8: $mm | D8: LOCKED | E8: KS-DL-1.2 | F8: Corrected capitalization
A9: First-lien opening debt | B9: 42.8 | C9: $mm | D9: LOCKED | E9: KS-DL-1.2
A10: Opening cash | B10: 3 | C10: $mm | D10: LOCKED | E10: KS-DL-1.2
A11: Opening firm EBITDA | B11: 11.4 | C11: $mm | D11: LOCKED | E11: KS-DL-1.2 | F11: Valuation and internal leverage
A12: Opening covenant EBITDA | B12: 12.2 | C12: $mm | D12: LOCKED | E12: KS-DL-1.2 | F12: Credit agreement only
A13: Largest ultimate-parent concentration | B13: 0.182 | C13: % | D13: LOCKED | E13: KS-DL-1.2 | F13: Riverton Industrial Group
A14: Normalized NWC target | B14: 8.4 | C14: $mm | D14: LOCKED | E14: KS-DL-1.2 | F14: Dollar-for-dollar true-up
A15: Tax rate | B15: 0.26 | C15: % | D15: MODEL ASSUMPTION | E15: KS-MA-001 | F15: Blended federal/state cash and book rate
A16: Cash interest deduction cap | B16: 0.3 | C16: % of EBITDA | D16: MODEL ASSUMPTION | E16: KS-MA-002 | F16: Simplified 163(j) treatment
A17: Depreciation as % revenue | B17: 0.015 | C17: % | D17: MODEL ASSUMPTION | E17: KS-MA-003 | F17: Consistent with historical run-rate
A18: Maintenance capex share | B18: 0.75 | C18: % of capex | D18: MODEL ASSUMPTION | E18: KS-MA-004 | F18: Growth capex is residual
A19: Eligible cash netting cap | B19: 5 | C19: $mm | D19: LOCKED | E19: KS-DL-1.2 | F19: Covenant only
A20: Revolver commitment | B20: 7.5 | C20: $mm | D20: LOCKED | E20: KS-DL-1.2
A21: DDTL commitment | B21: 10 | C21: $mm | D21: LOCKED | E21: KS-DL-1.2
A22: LC sublimit | B22: 2 | C22: $mm | D22: LOCKED | E22: KS-DL-1.2
A23: Term loan spread | B23: 0.055 | C23: % | D23: LOCKED | E23: KS-DL-1.2 | F23: Over adjusted Term SOFR
A24: Revolver spread | B24: 0.05 | C24: % | D24: LOCKED | E24: KS-DL-1.2
A25: DDTL spread | B25: 0.0575 | C25: % | D25: LOCKED | E25: KS-DL-1.2
A26: SOFR floor | B26: 0.01 | C26: % | D26: LOCKED | E26: KS-DL-1.2
A27: Annual term amortization | B27: 0.01 | C27: % original principal | D27: LOCKED | E27: KS-DL-1.2 | F27: Quarterly payments
A28: Annual DDTL amortization | B28: 0.01 | C28: % original principal | D28: LOCKED | E28: KS-DL-1.2 | F28: Quarterly after draw
A29: Unused revolver fee | B29: 0.005 | C29: % | D29: LOCKED | E29: KS-DL-1.2
A30: Unused DDTL fee | B30: 0.01 | C30: % | D30: LOCKED | E30: KS-DL-1.2 | F30: After first 90 days
A31: Financing fees and OID | B31: 1.4 | C31: $mm | D31: LOCKED | E31: KS-DL-1.2 | F31: Amortized over 24 quarters
A32: Buyer transaction expenses | B32: 4.4 | C32: $mm | D32: LOCKED | E32: KS-DL-1.2 | F32: Expensed at closing
A33: Opening equity after transaction expense | B33: 69.6 | C33: $mm | D33: DERIVED | E33: 74.0 less 4.4
A34: Exit date | B34: 47938 | C34: date | D34: LOCKED | E34: KS-DL-1.2 | F34: Exact LTM basis
A38: Annual Operating Assumptions
A39: Case / Driver | B39: Unit | C39: 2026 | D39: 2027 | E39: 2028 | F39: 2029 | G39: 2030 | H39: 2031
A40: Standalone Base - Platform growth | B40: % | C40: 0.07 | D40: 0.07 | E40: 0.07 | F40: 0.07 | G40: 0.07 | H40: 0.07
A41: Standalone Base - Gross margin | B41: % | C41: 0.362 | D41: 0.365 | E41: 0.368 | F41: 0.371 | G41: 0.374 | H41: 0.377
A42: Standalone Base - Firm EBITDA margin | B42: % | C42: 0.156 | D42: 0.161 | E42: 0.165 | F42: 0.169 | G42: 0.173 | H42: 0.177
A43: Standalone Base - DSO | B43: days | C43: 64 | D43: 63 | E43: 62 | F43: 61 | G43: 60 | H43: 60
A44: Standalone Base - WIP / revenue | B44: % | C44: 0.067 | D44: 0.065 | E44: 0.063 | F44: 0.061 | G44: 0.06 | H44: 0.06
A45: Standalone Base - Capex / revenue | B45: % | C45: 0.016 | D45: 0.016 | E45: 0.016 | F45: 0.016 | G45: 0.016 | H45: 0.016
A46: Standalone Base - Exit multiple | B46: x | C46: 9 | D46: 9 | E46: 9 | F46: 9 | G46: 9 | H46: 9
A47: Standalone Downside - Platform growth | B47: % | C47: 0.04 | D47: 0.02 | E47: 0.04 | F47: 0.05 | G47: 0.05 | H47: 0.05
A48: Standalone Downside - Gross margin | B48: % | C48: 0.355 | D48: 0.345 | E48: 0.35 | F48: 0.355 | G48: 0.36 | H48: 0.362
A49: Standalone Downside - Firm EBITDA margin | B49: % | C49: 0.145 | D49: 0.135 | E49: 0.145 | F49: 0.153 | G49: 0.158 | H49: 0.162
A50: Standalone Downside - DSO | B50: days | C50: 67 | D50: 75 | E50: 72 | F50: 69 | G50: 67 | H50: 66
... A74: Combined Risk - Exit multiple | B74: x | C74: 8.5 | D74: 8.5 | E74: 8.5 | F74: 8.5 | G74: 8.5 | H74: 8.5
A76: SOFR and Exit Assumptions
A77: Driver | B77: Unit | C77: 2026 | D77: 2027 | E77: 2028 | F77: 2029 | G77: 2030 | H77: 2031
A78: Adjusted Term SOFR | B78: % | C78: 0.0425 | D78: 0.0375 | E78: 0.035 | F78: 0.0325 | G78: 0.03 | H78: 0.03

Sheet Hist_3Stmt
A1: Historical Three-Statement Financials ($mm)
A3: Income Statement | B3: Unit | C3: FY2023A | D3: FY2024A | E3: FY2025A | G3: Historical data source map
A4: Revenue | B4: $mm | C4: 56.8 | D4: 65.4 | E4: 74 | G4: Revenue / GP / EBITDA | H4: KS-DL-1.2
A5: Growth | B5: % | D5: 0.151 | E5: 0.131 | G5: D&A / interest / tax | H5: KS-MA-HIST-001 | I5: Synthetic statement completion assumptions
A6: COGS | B6: $mm | C6: -37.4 | D6: -42.5 | E6: -47.4 | G6: Balance-sheet detail | H6: KS-MA-HIST-002 | I6: Constructed to tie to locked NWC, cash and debt
A7: Gross profit | B7: $mm | C7: 19.4 | D7: 22.9 | E7: 26.6 | G7: Cash-flow financing | H7: KS-MA-HIST-003 | I7: Owner activity reconciles equity and cash
A8: Gross margin | B8: % | C8: 0.342 | D8: 0.35 | E8: 0.359 | G8: All figures fictional | H8: Yes
A9: SG&A | B9: $mm | C9: -11.9 | D9: -14.1 | E9: -16.4
A10: Reported EBITDA | B10: $mm | C10: 7.5 | D10: 8.8 | E10: 10.2
A11: EBITDA margin | B11: % | C11: 0.132 | D11: 0.135 | E11: 0.138
A12: D&A | B12: $mm | C12: -1.1 | D12: -1.3 | E12: -1.5
A13: EBIT | B13: $mm | C13: 6.4 | D13: 7.5 | E13: 8.7
A14: Cash interest | B14: $mm | C14: -0.75 | D14: -0.85 | E14: -0.95
A15: Pre-tax income | B15: $mm | C15: 5.65 | D15: 6.65 | E15: 7.75
A16: Book tax expense | B16: $mm | C16: -1.47 | D16: -1.73 | E16: -2.02
A17: Net income | B17: $mm | C17: 4.18 | D17: 4.92 | E17: 5.73
A20: Balance Sheet
A21: Balance Sheet | B21: Unit | C21: FY2023A | D21: FY2024A | E21: FY2025A
A22: Cash | B22: $mm | C22: 2.5 | D22: 3.2 | E22: 4.2
A23: Accounts receivable | B23: $mm | C23: 9.8 | D23: 11.3 | E23: 13.2
A24: Unbilled WIP | B24: $mm | C24: 3.4 | D24: 4.2 | E24: 5.1
A25: Prepaids | B25: $mm | C25: 0.7 | D25: 0.8 | E25: 0.9
A26: PP&E, net | B26: $mm | C26: 4 | D26: 3.7 | E26: 3.4
A27: Goodwill | B27: $mm | C27: 18 | D27: 23 | E27: 28
A28: Other intangibles | B28: $mm | C28: 6 | D28: 8.5 | E28: 10
A29: Other assets | B29: $mm | C29: 1 | D29: 1.2 | E29: 1.3
A30: Total assets | B30: $mm | C30: 45.4 | D30: 55.9 | E30: 66.1
A31: Accounts payable | B31: $mm | C31: 2.9 | D31: 3.5 | E31: 4.1
A32: Accrued liabilities | B32: $mm | C32: 4.1 | D32: 4.8 | E32: 5.6
A33: Deferred revenue | B33: $mm | C33: 0.6 | D33: 0.8 | E33: 0.9
... A41: Balance check | B41: $mm | C41: 0 | D41: 0 | E41: 0
A44: Cash Flow Statement
A45: Cash Flow Statement | B45: Unit | C45: FY2023A | D45: FY2024A | E45: FY2025A
A46: Net income | B46: $mm | C46: 4.18 | D46: 4.92 | E46: 5.73
A47: D&A | B47: $mm | C47: 1.1 | D47: 1.3 | E47: 1.5
A48: Change in operating NWC | B48: $mm | C48: -0.5 | D48: -0.9 | E48: -1.4
A49: Cash from operations | B49: $mm | C49: 4.78 | D49: 5.32 | E49: 5.83
A50: Capital expenditure | B50: $mm | C50: -0.8 | D50: -1 | E50: -1.2
A51: Acquisitions, net | B51: $mm | C51: -5 | D51: -7 | E51: 0
A52: Cash from investing | B52: $mm | C52: -5.8 | D52: -8 | E52: -1.2
A53: Debt issuance / (repayment) | B53: $mm | C53: 1 | D53: 0.5 | E53: 0.6
A54: Owner equity activity | B54: $mm | C54: 0.52 | D54: 3.88 | E54: -4.23
A55: Cash from financing | B55: $mm | C55: 1.52 | D55: 4.38 | E55: -3.63
A56: Net change in cash | B56: $mm | C56: 0.5 | D56: 0.7 | E56: 1
A57: Beginning cash | B57: $mm | C57: 2 | D57: 2.5 | E57: 3.2
... A59: Cash flow check | B59: $mm | C59: 0 | D59: 0 | E59: 0

Sheet Hist_Monthly
A1: Monthly Management Accounts - FY2023A to FY2025A ($mm)
A3: Line Item | B3: Unit | C3: 44927 | D3: 44958 | E3: 44986 | F3: 45017 | G3: 45047 | H3: 45078 | I3: 45108 | J3: 45139 | K3: 45170 | L3: 45200 | M3: 45231 | N3: 45261 | O3: 45292 | P3: 45323 | Q3: 45352 | R3: 45383 | S3: 45413 | T3: 45444 | U3: 45474 | V3: 45505 | W3: 45536 | X3: 45566 | Y3: 45597 | Z3: 45627 | AA3: 45658 | AB3: 45689 | AC3: 45717 | AD3: 45748 | AE3: 45778 | AF3: 45809 | AG3: 45839 | AH3: 45870 | AI3: 45901 | AJ3: 45931 | AK3: 45962 | AL3: 45992
A4: Revenue | B4: $mm | C4: 4.26 | D4: 4.3736 | E4: 4.4304 | F4: 4.544 | G4: 4.6576 | H4: 4.7144 | I4: 4.7712 | J4: 4.828 | K4: 4.828 | L4: 4.9416 | M4: 5.1688 | N4: 5.2824 | O4: 4.905 | P4: 5.0358 | Q4: 5.1012 | R4: 5.232 | S4: 5.3628 | T4: 5.4282 | U4: 5.4936 | V4: 5.559 | W4: 5.559 | X4: 5.6898 | Y4: 5.9514 | Z4: 6.0822 | AA4: 5.55 | AB4: 5.698 | AC4: 5.772 | AD4: 5.92 | AE4: 6.068 | AF4: 6.142 | AG4: 6.216 | AH4: 6.29 | AI4: 6.29 | AJ4: 6.438 | AK4: 6.734 | AL4: 6.882
A5: Gross profit | B5: $mm | C5: 1.455 | D5: 1.4938 | E5: 1.5132 | F5: 1.552 | G5: 1.5908 | H5: 1.6102 | I5: 1.6296 | J5: 1.649 | K5: 1.649 | L5: 1.6878 | M5: 1.7654 | N5: 1.8042 | O5: 1.7175 | P5: 1.7633 | Q5: 1.7862 | R5: 1.832 | S5: 1.8778 | T5: 1.9007 | U5: 1.9236 | V5: 1.9465 | W5: 1.9465 | X5: 1.9923 | Y5: 2.0839 | Z5: 2.1297 | AA5: 1.995 | AB5: 2.0482 | AC5: 2.0748 | AD5: 2.128 | AE5: 2.1812 | AF5: 2.2078 | AG5: 2.2344 | AH5: 2.261 | AI5: 2.261 | AJ5: 2.3142 | AK5: 2.4206 | AL5: 2.4738
A6: Gross margin | B6: % | C6: 0.3415493 | D6: 0.3415493 | E6: 0.3415493 | F6: 0.3415493 | G6: 0.3415493 | H6: 0.3415493 | I6: 0.3415493 | J6: 0.3415493 | K6: 0.3415493 | L6: 0.3415493 | M6: 0.3415493 | N6: 0.3415493 | O6: 0.35015291 | P6: 0.35015291 | Q6: 0.35015291 | R6: 0.35015291 | S6: 0.35015291 | T6: 0.35015291 | U6: 0.35015291 | V6: 0.35015291 | W6: 0.35015291 | X6: 0.35015291 | Y6: 0.35015291 | Z6: 0.35015291 | AA6: 0.35945946 | AB6: 0.35945946 | AC6: 0.35945946 | AD6: 0.35945946 | AE6: 0.35945946 | AF6: 0.35945946 | AG6: 0.35945946 | AH6: 0.35945946 | AI6: 0.35945946 | AJ6: 0.35945946 | AK6: 0.35945946 | AL6: 0.35945946
A7: Reported EBITDA | B7: $mm | C7: 0.5625 | D7: 0.5775 | E7: 0.585 | F7: 0.6 | G7: 0.615 | H7: 0.6225 | I7: 0.63 | J7: 0.6375 | K7: 0.6375 | L7: 0.6525 | M7: 0.6825 | N7: 0.6975 | O7: 0.66 | P7: 0.6776 | Q7: 0.6864 | R7: 0.704 | S7: 0.7216 | T7: 0.7304 | U7: 0.7392 | V7: 0.748 | W7: 0.748 | X7: 0.7656 | Y7: 0.8008 | Z7: 0.8184 | AA7: 0.765 | AB7: 0.7854 | AC7: 0.7956 | AD7: 0.816 | AE7: 0.8364 | AF7: 0.8466 | AG7: 0.8568 | AH7: 0.867 | AI7: 0.867 | AJ7: 0.8874 | AK7: 0.9282 | AL7: 0.9486
A8: EBITDA margin | B8: % | C8: 0.13204225 | D8: 0.13204225 | E8: 0.13204225 | F8: 0.13204225 | G8: 0.13204225 | H8: 0.13204225 | I8: 0.13204225 | J8: 0.13204225 | K8: 0.13204225 | L8: 0.13204225 | M8: 0.13204225 | N8: 0.13204225 | O8: 0.13455657 | P8: 0.13455657 | Q8: 0.13455657 | R8: 0.13455657 | S8: 0.13455657 | T8: 0.13455657 | U8: 0.13455657 | V8: 0.13455657 | W8: 0.13455657 | X8: 0.13455657 | Y8: 0.13455657 | Z8: 0.13455657 | AA8: 0.13783784 | AB8: 0.13783784 | AC8: 0.13783784 | AD8: 0.13783784 | AE8: 0.13783784 | AF8: 0.13783784 | AG8: 0.13783784 | AH8: 0.13783784 | AI8: 0.13783784 | AJ8: 0.13783784 | AK8: 0.13783784 | AL8: 0.13783784
A9: Capex | B9: $mm | C9: 0.06 | D9: 0.0616 | E9: 0.0624 | F9: 0.064 | G9: 0.0656 | H9: 0.0664 | I9: 0.0672 | J9: 0.068 | K9: 0.068 | L9: 0.0696 | M9: 0.0728 | N9: 0.0744 | O9: 0.075 | P9: 0.077 | Q9: 0.078 | R9: 0.08 | S9: 0.082 | T9: 0.083 | U9: 0.084 | V9: 0.085 | W9: 0.085 | X9: 0.087 | Y9: 0.091 | Z9: 0.093 | AA9: 0.09 | AB9: 0.0924 | AC9: 0.0936 | AD9: 0.096 | AE9: 0.0984 | AF9: 0.0996 | AG9: 0.1008 | AH9: 0.102 | AI9: 0.102 | AJ9: 0.1044 | AK9: 0.1092 | AL9: 0.1116

Sheet Customer_Data
A1: Raw Customer Revenue Schedule - FY2025A
A3: Billing Account ID | B3: Billing Account | C3: Ultimate Parent | D3: Service Line | E3: End Market | F3: Region | G3: 2025 Revenue ($mm) | H3: % Revenue | I3: Recurring / Repeat / Project | J3: Contract Start | K3: Termination Notice (days) | L3: Minimum Volume | M3: Change of Control | N3: Relationship Tenure (yrs) | O3: Source
A4: RIV-DEC | B4: Riverton Advanced Materials - Decatur | C4: Riverton Industrial Group | D4: EHS Compliance | E4: Industrial manufacturing | F4: Midwest | G4: 5.624 | H4: 0.076 | I4: Repeat | J4: 42767 | K4: 60 | L4: No | M4: Notice | N4: 9 | O4: Customer ledger / KS-DL-1.2
A5: MET-N | B5: Metro Utility - North | C5: Metro Utility Holdings | D5: Field Inspection | E5: Infrastructure and utilities | F5: Midwest | G5: 3.2 | H5: 0.043243243 | I5: Recurring | J5: 43160 | K5: 90 | L5: No | M5: Consent | N5: 7 | O5: Customer ledger / KS-DL-1.2
A6: STA-01 | B6: State Infrastructure Department | C6: State Infrastructure Authority | D6: Permitting & Advisory | E6: Municipal and public sector | F6: Southeast | G6: 2.8 | H6: 0.037837838 | I6: Repeat | J6: 43556 | K6: 30 | L6: No | M6: Notice | N6: 11 | O6: Customer ledger / KS-DL-1.2
A7: MED-01 | B7: MedCore Hospital System | C7: MedCore Health | D7: Industrial Hygiene | E7: Healthcare and life sciences | F7: Midwest | G7: 2.3 | H7: 0.031081081 | I7: Recurring | J7: 43952 | K7: 60 | L7: No | M7: Notice | N7: 8 | O7: Customer ledger / KS-DL-1.2
A8: RIV-CORP | B8: Riverton Corporate EHS | C8: Riverton Industrial Group | D8: EHS Compliance | E8: Industrial manufacturing | F8: Midwest | G8: 1.912 | H8: 0.025837838 | I8: Recurring | J8: 44348 | K8: 60 | L8: No | M8: Notice | N8: 9 | O8: Customer ledger / KS-DL-1.2
A9: BIO-01 | B9: BioHealth Laboratories | C9: BioHealth Laboratories | D9: Industrial Hygiene | E9: Healthcare and life sciences | F9: Southeast | G9: 1.7 | H9: 0.022972973 | I9: Recurring | J9: 44743 | K9: 60 | L9: No | M9: Notice | N9: 6 | O9: Customer ledger / KS-DL-1.2
A10: APX-01 | B10: Apex Manufacturing - Main | C10: Apex Manufacturing | D10: EHS Compliance | E10: Industrial manufacturing | F10: Midwest | G10: 1.6 | H10: 0.021621622 | I10: Repeat | J10: 45139 | K10: 30 | L10: No | M10: None | N10: 5 | O10: Customer ledger / KS-DL-1.2
A11: RIV-GRN | B11: Riverton Components - Greenville | C11: Riverton Industrial Group | D11: Field Inspection | E11: Industrial manufacturing | F11: Southeast | G11: 1.5 | H11: 0.02027027 | I11: Repeat | J11: 42614 | K11: 60 | L11: No | M11: Notice | N11: 7 | O11: Customer ledger / KS-DL-1.2
A12: MET-S | B12: Metro Utility - South | C12: Metro Utility Holdings | D12: Field Inspection | E12: Infrastructure and utilities | F12: Southeast | G12: 1.4 | H12: 0.018918919 | I12: Recurring | J12: 43009 | K12: 90 | L12: No | M12: Consent | N12: 6 | O12: Customer ledger / KS-DL-1.2
A13: STA-02 | B13: State Infrastructure District 2 | C13: State Infrastructure Authority | D13: Permitting & Advisory | E13: Municipal and public sector | F13: Southeast | G13: 1.274 | H13: 0.017216216 | I13: Repeat | J13: 43405 | K13: 30 | L13: No | M13: Notice | N13: 10 | O13: Customer ledger / KS-DL-1.2
A14: RIV-MIL | B14: Riverton Metals - Milltown | C14: Riverton Industrial Group | D14: Industrial Hygiene | E14: Industrial manufacturing | F14: Midwest | G14: 1.3 | H14: 0.017567568 | I14: Recurring | J14: 43800 | K14: 60 | L14: No | M14: Notice | N14: 8 | O14: Customer ledger / KS-DL-1.2
A15: RIV-CHEM | B15: Riverton Chemicals - East | C15: Riverton Industrial Group | D15: EHS Compliance | E15: Industrial manufacturing | F15: Midwest | G15: 1.2 | H15: 0.016216216 | I15: Repeat | J15: 43831 | K15: 60 | L15: No | M15: Notice | N15: 6 | O15: Customer ledger / KS-DL-1.2
... A62: SM-035 | B62: Meridian Transit 2 Account 35 | C62: Meridian Transit 2 | D62: Field Inspection | E62: Infrastructure and utilities | F62: Midwest | G62: 0.84245998 | H62: 0.011384594 | I62: Project | J62: 43800 | K62: 60 | L62: No | M62: Notice | N62: 3 | O62: Customer ledger / KS-DL-1.2
A64: Concentration Summary
A65: Metric | B65: Billing-account view | C65: Ultimate-parent view | D65: Ledger target | E65: Check
A66: Largest customer | B66: 0.076 | C66: 0.182 | D66: 0.182
A67: Top five | B67: 0.214 | C67: 0.365 | D67: 0.365
A68: Top ten | B68: 0.315 | C68: 0.505 | D68: 0.505
A69: Total revenue | B69: 74 | C69: 74 | D69: 74

Sheet Project_Data
A1: Project-Level Revenue, Margin, Backlog and Contract Schedule - FY2025A
A3: Project ID | B3: Billing Account ID | C3: Ultimate Parent | D3: Service Line | E3: Project Type | F3: Start Date | G3: End / Renewal Date | H3: 2025 Revenue ($mm) | I3: Gross Margin % | J3: Unbilled WIP ($mm) | K3: WIP Age (days) | L3: Contracted Backlog ($mm) | M3: Expected Recurring Revenue ($mm) | N3: Termination Notice | O3: PO Required | P3: System | Q3: Branch | R3: Source
A4: RIV-DEC-P1 | B4: RIV-DEC | C4: Riverton Industrial Group | D4: EHS Compliance | E4: Repeat | F4: 45323 | G4: 46082 | H4: 1.6179894 | I4: 0.30724363 | J4: 0.10807215 | K4: 56 | L4: 0.74103742 | M4: 0.40449736 | N4: 30-60 days | O4: Yes | P4: Central PSA | Q4: Charlotte | R4: Project ledger / data room
A5: RIV-DEC-P2 | B5: RIV-DEC | C5: Riverton Industrial Group | D5: EHS Compliance | E5: Repeat | F5: 45352 | G5: 46143 | H5: 0.75369881 | I5: 0.35074357 | J5: 0.031560974 | K5: 63 | L5: 0.35412948 | M5: 0.1884247 | N5: 30-60 days | O5: No | P5: Legacy A | Q5: Indianapolis | R5: Project ledger / data room
A6: RIV-DEC-P3 | B6: RIV-DEC | C6: Riverton Industrial Group | D6: EHS Compliance | E6: Repeat | F6: 45383 | G6: 46204 | H6: 3.2523117 | I6: 0.3090713 | J6: 0.19912591 | K6: 102 | L6: 1.7035673 | M6: 0.81307794 | N6: 30-60 days | O6: Yes | P6: Legacy B | Q6: Chicago | R6: Project ledger / data room
A7: MET-N-P1 | B7: MET-N | C7: Metro Utility Holdings | D7: Field Inspection | E7: Recurring | F7: 45323 | G7: 46082 | H7: 0.39722653 | I7: 0.35771029 | J7: 0.023767661 | K7: 117 | L7: 0.17739449 | M7: 0.19861326 | N7: 30-60 days | O7: Yes | P7: Legacy B | Q7: Indianapolis | R7: Project ledger / data room
A8: MET-N-P2 | B8: MET-N | C8: Metro Utility Holdings | D8: Field Inspection | E8: Recurring | F8: 45352 | G8: 46143 | H8: 1.1164409 | I8: 0.38584685 | J8: 0.060824221 | K8: 34 | L8: 0.57808445 | M8: 0.55822047 | N8: 30-60 days | O8: No | P8: Central PSA | Q8: Chicago | R8: Project ledger / data room
A9: MET-N-P3 | B9: MET-N | C9: Metro Utility Holdings | D9: Field Inspection | E9: Recurring | F9: 45383 | G9: 46204 | H9: 1.6863325 | I9: 0.33084818 | J9: 0.13626632 | K9: 38 | L9: 1.6553043 | M9: 0.84316627 | N9: 30-60 days | O9: Yes | P9: Legacy A | Q9: Louisville | R9: Project ledger / data room
A10: STA-01-P1 | B10: STA-01 | C10: State Infrastructure Authority | D10: Permitting & Advisory | E10: Repeat | F10: 45323 | G10: 46082 | H10: 1.1474625 | I10: 0.3062789 | J10: 0.049318006 | K10: 40 | L10: 1.2397185 | M10: 0.28686563 | N10: 30-60 days | O10: Yes | P10: Legacy A | Q10: Nashville | R10: Project ledger / data room
A11: STA-01-P2 | B11: STA-01 | C11: State Infrastructure Authority | D11: Permitting & Advisory | E11: Repeat | F11: 45352 | G11: 46143 | H11: 0.66881079 | I11: 0.34275923 | J11: 0.037257682 | K11: 78 | L11: 0.57061891 | M11: 0.1672027 | N11: 30-60 days | O11: No | P11: Legacy B | Q11: Raleigh | R11: Project ledger / data room
A12: STA-01-P3 | B12: STA-01 | C12: State Infrastructure Authority | D12: Permitting & Advisory | E12: Repeat | F12: 45383 | G12: 46204 | H12: 0.9837267 | I12: 0.3299767 | J12: 0.078421684 | K12: 89 | L12: 0.63361494 | M12: 0.24593168 | N12: 30-60 days | O12: Yes | P12: Central PSA | Q12: Charlotte | R12: Project ledger / data room
A13: MED-01-P1 | B13: MED-01 | C13: MedCore Health | D13: Industrial Hygiene | E13: Recurring | F13: 45323 | G13: 46082 | H13: 0.66903121 | I13: 0.37294453 | J13: 0.036393216 | K13: 118 | L13: 0.34660217 | M13: 0.3345156 | N13: 30-60 days | O13: Yes | P13: Legacy B | Q13: Raleigh | R13: Project ledger / data room
A14: MED-01-P2 | B14: MED-01 | C14: MedCore Health | D14: Industrial Hygiene | E14: Recurring | F14: 45352 | G14: 46143 | H14: 0.61169629 | I14: 0.34181228 | J14: 0.047624866 | K14: 35 | L14: 0.54377543 | M14: 0.30584814 | N14: 30-60 days | O14: No | P14: Central PSA | Q14: Charlotte | R14: Project ledger / data room
A15: MED-01-P3 | B15: MED-01 | C15: MedCore Health | D15: Industrial Hygiene | E15: Recurring | F15: 45383 | G15: 46204 | H15: 1.0192725 | I15: 0.30392073 | J15: 0.074825603 | K15: 96 | L15: 0.99177859 | M15: 0.50963625 | N15: 30-60 days | O15: Yes | P15: Legacy A | Q15: Indianapolis | R15: Project ledger / data room
... A118: SM-035-P1 | B118: SM-035 | C118: Meridian Transit 2 | D118: Field Inspection | E118: Project | F118: 45323 | G118: 46082 | H118: 0.84245998 | I118: 0.3189849 | J118: 0.049424991 | K118: 115 | L118: 1.0819432 | M118: 0.042122999 | N118: 30-60 days | O118: Yes | P118: Central PSA | Q118: Indianapolis | R118: Project ledger / data room

Sheet Employees
A1: Employee and Utilization Schedule - December 31, 2025
A3: Employee ID | B3: Office | C3: Region | D3: Function | E3: Service Line | F3: Billable? | G3: Annual Base Salary ($000) | H3: Bonus Target % | I3: Recorded Utilization % | J3: Standardized Utilization % | K3: Hire Date | L3: Acquisition Origin | M3: Status | N3: Manager Level | O3: Retention Critical? | P3: Source
A4: E0001 | B4: Chicago | C4: Midwest | D4: Technical | E4: Industrial Hygiene | F4: Yes | G4: 77 | H4: 0.05 | I4: 0.62 | J4: 0.58 | K4: 42401 | L4: Northstar | M4: Active | N4: Staff | O4: No | P4: HRIS / KS-DL-1.2
A5: E0002 | B5: Detroit | C5: Midwest | D5: Technical | E5: Field Inspection | F5: Yes | G5: 94 | H5: 0.05 | I5: 0.69 | J5: 0.65 | K5: 42795 | L5: Delta | M5: Active | N5: Staff | O5: No | P5: HRIS / KS-DL-1.2
A6: E0003 | B6: Louisville | C6: Southeast | D6: Technical | E6: Permitting & Advisory | F6: Yes | G6: 111 | H6: 0.05 | I6: 0.76 | J6: 0.72 | K6: 43191 | L6: Meridian | M6: Active | N6: Staff | O6: No | P6: HRIS / KS-DL-1.2
A7: E0004 | B7: Nashville | C7: Midwest | D7: Project Management | E7: EHS Compliance | F7: Yes | G7: 128 | H7: 0.05 | I7: 0.83 | J7: 0.79 | K7: 43586 | L7: Summit | M7: Active | N7: Staff | O7: No | P7: HRIS / KS-DL-1.2
A8: E0005 | B8: Raleigh | C8: Midwest | D8: Corporate | E8: Industrial Hygiene | F8: No | G8: 135 | H8: 0.15 | I8: 0 | J8: 0 | K8: 43983 | L8: Legacy Alderstone | M8: Active | N8: Staff | O8: No | P8: HRIS / KS-DL-1.2
A9: E0006 | B9: Charlotte | C9: Southeast | D9: Sales | E9: Field Inspection | F9: No | G9: 148 | H9: 0.15 | I9: 0 | J9: 0 | K9: 44378 | L9: Northstar | M9: Active | N9: Staff | O9: No | P9: HRIS / KS-DL-1.2
A10: E0007 | B10: Cincinnati | C10: Midwest | D10: Finance | E10: Permitting & Advisory | F10: No | G10: 161 | H10: 0.15 | I10: 0 | J10: 0 | K10: 44774 | L10: Delta | M10: Active | N10: Staff | O10: No | P10: HRIS / KS-DL-1.2
A11: E0008 | B11: Columbus | C11: Midwest | D11: HR | E11: EHS Compliance | F11: No | G11: 174 | H11: 0.15 | I11: 0 | J11: 0 | K11: 45170 | L11: Meridian | M11: Active | N11: Staff | O11: No | P11: HRIS / KS-DL-1.2
A12: E0009 | B12: Knoxville | C12: Southeast | D12: IT | E12: Industrial Hygiene | F12: No | G12: 77 | H12: 0.15 | I12: 0 | J12: 0 | K12: 45566 | L12: Summit | M12: Active | N12: Staff | O12: No | P12: HRIS / KS-DL-1.2
A13: E0010 | B13: Greenville | C13: Midwest | D13: Technical | E13: Field Inspection | F13: Yes | G13: 140 | H13: 0.05 | I13: 0.65 | J13: 0.61 | K13: 45962 | L13: Legacy Alderstone | M13: Active | N13: Staff | O13: No | P13: HRIS / KS-DL-1.2
A14: E0011 | B14: Milwaukee | C14: Midwest | D14: Technical | E14: Permitting & Advisory | F14: Yes | G14: 67 | H14: 0.05 | I14: 0.72 | J14: 0.68 | K14: 42339 | L14: Northstar | M14: Active | N14: Staff | O14: No | P14: HRIS / KS-DL-1.2
A15: E0012 | B15: St. Louis | C15: Southeast | D15: Technical | E15: EHS Compliance | F15: Yes | G15: 84 | H15: 0.05 | I15: 0.79 | J15: 0.75 | K15: 42370 | L15: Delta | M15: Active | N15: Manager | O15: No | P15: HRIS / KS-DL-1.2
... A471: E0468 | B471: Charlotte | C471: Southeast | D471: HR | E471: EHS Compliance | F471: No | G471: 104 | H471: 0.15 | I471: 0 | J471: 0 | K471: 44197 | L471: Meridian | M471: Active | N471: Manager | O471: No | P471: HRIS / KS-DL-1.2

Sheet AR_WIP
A1: Accounts Receivable and Unbilled WIP Detail - December 31, 2025
A3: Accounts Receivable Detail
A4: Invoice ID | B4: Billing Account ID | C4: Ultimate Parent | D4: Invoice Date | E4: Due Date | F4: Amount ($mm) | G4: Age (days) | H4: Current | I4: 31-60 | J4: 61-90 | K4: 91-120 | L4: 120+ | M4: Disputed?
A5: INV-0001 | B5: MED-01 | C5: MedCore Health | D5: 46001 | E5: 46031 | F5: 0.089416841 | G5: 21 | H5: 0.089416841 | I5: 0 | J5: 0 | K5: 0 | L5: 0 | M5: No
A6: INV-0002 | B6: APX-01 | C6: Apex Manufacturing | D6: 45972 | E6: 46002 | F6: 0.20202858 | G6: 50 | H6: 0 | I6: 0.20202858 | J6: 0 | K6: 0 | L6: 0 | M6: No
A7: INV-0003 | B7: STA-02 | C7: State Infrastructure Authority | D7: 45896 | E7: 45926 | F7: 0.12536859 | G7: 126 | H7: 0 | I7: 0 | J7: 0 | K7: 0 | L7: 0.12536859 | M7: No
A8: INV-0004 | B8: RIV-LOG | C8: Riverton Industrial Group | D8: 45977 | E8: 46007 | F8: 0.093327516 | G8: 45 | H8: 0 | I8: 0.093327516 | J8: 0 | K8: 0 | L8: 0 | M8: No
A9: INV-0005 | B9: APX-02 | C9: Apex Manufacturing | D9: 46004 | E9: 46034 | F9: 0.16170985 | G9: 18 | H9: 0.16170985 | I9: 0 | J9: 0 | K9: 0 | L9: 0 | M9: No
A10: INV-0006 | B10: CTY-01 | C10: CityWorks Municipal Group | D10: 45873 | E10: 45903 | F10: 0.16276976 | G10: 149 | H10: 0 | I10: 0 | J10: 0 | K10: 0 | L10: 0.16276976 | M10: No
A11: INV-0007 | B11: CLN-02 | C11: Clinica Health | D11: 45941 | E11: 45971 | F11: 0.1594249 | G11: 81 | H11: 0 | I11: 0 | J11: 0.1594249 | K11: 0 | L11: 0 | M11: No
A12: INV-0008 | B12: SM-001 | C12: Northfield Foods | D12: 46020 | E12: 46050 | F12: 0.15439631 | G12: 2 | H12: 0.15439631 | I12: 0 | J12: 0 | K12: 0 | L12: 0 | M12: No
A13: INV-0009 | B13: SM-004 | C13: Granite Bio | D13: 45937 | E13: 45967 | F13: 0.10894482 | G13: 85 | H13: 0 | I13: 0 | J13: 0.10894482 | K13: 0 | L13: 0 | M13: No
A14: INV-0010 | B14: SM-007 | C14: Keystone Health | D14: 46001 | E14: 46031 | F14: 0.1064285 | G14: 21 | H14: 0.1064285 | I14: 0 | J14: 0 | K14: 0 | L14: 0 | M14: No
A15: INV-0011 | B15: SM-010 | C15: Pioneer Components | D15: 45998 | E15: 46028 | F15: 0.20916982 | G15: 24 | H15: 0.20916982 | I15: 0 | J15: 0 | K15: 0 | L15: 0 | M15: No
A16: INV-0012 | B16: SM-013 | C16: Silverline Medical | D16: 45912 | E16: 45942 | F16: 0.12299482 | G16: 110 | H16: 0 | I16: 0 | J16: 0 | K16: 0.12299482 | L16: 0 | M16: No
... A84: INV-0080 | B84: RIV-CORP | C84: Riverton Industrial Group | D84: 45891 | E84: 45921 | F84: 0.21151392 | G84: 131 | H84: 0 | I84: 0 | J84: 0 | K84: 0 | L84: 0.21151392 | M84: No
A86: Unbilled WIP Detail
A87: WIP ID | B87: Project ID | C87: Billing Account ID | D87: Ultimate Parent | E87: Service Line | F87: Amount ($mm) | G87: Age (days) | H87: Customer Approval Required? | I87: PO / Change Order Status | J87: Expected Bill Date | K87: Collectibility | L87: System | M87: Source
A88: WIP-0001 | B88: MET-N-P3 | C88: MET-N | D88: Metro Utility Holdings | E88: Field Inspection | F88: 0.11257358 | G88: 39 | H88: No | I88: Approved | J88: 46038 | K88: High | L88: Legacy A | M88: WIP ledger / data room
A89: WIP-0002 | B89: MED-01-P2 | C89: MED-01 | D89: MedCore Health | E89: Industrial Hygiene | F89: 0.12640718 | G89: 56 | H89: No | I89: Approved | J89: 46039 | K89: High | L89: Central PSA | M89: WIP ledger / data room
A90: WIP-0003 | B90: BIO-01-P2 | C90: BIO-01 | D90: BioHealth Laboratories | E90: Industrial Hygiene | F90: 0.092467299 | G90: 102 | H90: No | I90: Approved | J90: 46040 | K90: Review | L90: Central PSA | M90: WIP ledger / data room
A91: WIP-0004 | B91: MET-S-P1 | C91: MET-S | D91: Metro Utility Holdings | E91: Field Inspection | F91: 0.091315484 | G91: 64 | H91: Yes | I91: Approved | J91: 46041 | K91: High | L91: Central PSA | M91: WIP ledger / data room
A92: WIP-0005 | B92: RIV-MIL-P2 | C92: RIV-MIL | D92: Riverton Industrial Group | E92: Industrial Hygiene | F92: 0.07617644 | G92: 42 | H92: No | I92: Pending | J92: 46042 | K92: High | L92: Legacy B | M92: WIP ledger / data room
A93: WIP-0006 | B93: RIV-WST-P1 | C93: RIV-WST | D93: Riverton Industrial Group | E93: Permitting & Advisory | F93: 0.15360392 | G93: 94 | H93: No | I93: Approved | J93: 46043 | K93: Review | L93: Central PSA | M93: WIP ledger / data room
A94: WIP-0007 | B94: APX-02-P2 | C94: APX-02 | D94: Apex Manufacturing | E94: Field Inspection | F94: 0.062806912 | G94: 6 | H94: No | I94: Approved | J94: 46044 | K94: High | L94: Central PSA | M94: WIP ledger / data room
A95: WIP-0008 | B95: CTY-01-P1 | C95: CTY-01 | D95: CityWorks Municipal Group | E95: Permitting & Advisory | F95: 0.044696954 | G95: 29 | H95: Yes | I95: Approved | J95: 46045 | K95: High | L95: Central PSA | M95: WIP ledger / data room
A96: WIP-0009 | B96: CLN-01-P2 | C96: CLN-01 | D96: Clinica Health | E96: Industrial Hygiene | F96: 0.059176534 | G96: 96 | H96: No | I96: Approved | J96: 46046 | K96: Review | L96: Central PSA | M96: WIP ledger / data room
A97: WIP-0010 | B97: SM-001-P1 | C97: SM-001 | D97: Northfield Foods | E97: EHS Compliance | F97: 0.059094217 | G97: 105 | H97: No | I97: Pending | J97: 46047 | K97: Review | L97: Legacy A | M97: WIP ledger / data room
A98: WIP-0011 | B98: SM-003-P2 | C98: SM-003 | D98: Cedar Municipal | E98: Field Inspection | F98: 0.067684239 | G98: 14 | H98: No | I98: Approved | J98: 46048 | K98: High | L98: Central PSA | M98: WIP ledger / data room
A99: WIP-0012 | B99: SM-006-P1 | C99: SM-006 | D99: Summit Water | E99: Industrial Hygiene | F99: 0.060053413 | G99: 9 | H99: Yes | I99: Approved | J99: 46049 | K99: High | L99: Legacy A | M99: WIP ledger / data room
... A147: WIP-0060 | B147: SM-011-P1 | C147: SM-011 | D147: Evergreen Chemicals | E147: Field Inspection | F147: 0.042145927 | G147: 118 | H147: Yes | I147: Pending | J147: 46097 | K147: Review | L147: Legacy B | M147: WIP ledger / data room

Sheet QoE_Bridge
A1: EBITDA Basis Schedule ($mm)
A3: Adjustment | B3: Reported | C3: Seller View | D3: QoE View | E3: Firm View | F3: Covenant View | G3: Source / Treatment
A4: Reported EBITDA | B4: 10.2 | C4: 10.2 | D4: 10.2 | E4: 10.2 | F4: 10.2 | G4: Historical accounts
A5: Founder / executive compensation | B5: 0 | C5: 0.4 | D5: 0.35 | E5: 0.35 | F5: 0.35 | G5: QoE accepted at market replacement cost
A6: Transaction-readiness and professional fees | B6: 0 | C6: 0.3 | D6: 0.25 | E6: 0.25 | F6: 0.25 | G6: Recurring audit/compliance retained
A7: Integration and systems costs | B7: 0 | C7: 0.5 | D7: 0.3 | E7: 0.2 | F7: 0.3 | G7: Firm retains $0.10m recurring cost
A8: Legal and settlement expense | B8: 0 | C8: 0.2 | D8: 0.2 | E8: 0.2 | F8: 0.2 | G8: Supported non-recurring item
A9: Duplicate occupancy / facility move | B9: 0 | C9: 0.2 | D9: 0.15 | E9: 0.15 | F9: 0.15 | G9: Implemented closure
A10: Implemented headcount savings | B10: 0 | C10: 0.4 | D10: 0.25 | E10: 0.25 | F10: 0.5 | G10: Additional covenant-certified savings
A11: Pricing and utilization initiatives | B11: 0 | C11: 0.5 | D11: 0 | E11: 0 | F11: 0 | G11: Forecast only; no historical add-back
A12: Revenue cut-off | B12: 0 | C12: 0 | D12: -0.1 | E12: -0.1 | F12: -0.1 | G12: QoE correction
A13: Bonus accrual normalization | B13: 0 | C13: 0 | D13: 0.2 | E13: 0.2 | F13: 0.2 | G13: Approved plan support
A14: Related-party rent normalization | B14: 0 | C14: 0 | D14: 0.1 | E14: 0.1 | F14: 0 | G14: Not recognized in covenant definition
A15: Revenue / WIP quality reserve | B15: 0 | C15: 0 | D15: 0 | E15: -0.2 | F15: 0 | G15: Firm conservatism
... A19: Adjusted EBITDA | B19: 10.2 | C19: 12.7 | D19: 11.9 | E19: 11.4 | F19: 12.2 | G19: Model amounts

Sheet S&U_Opening
A1: Sources & Uses, Purchase Price Bridge and Opening Balance Sheet ($mm)
A3: Purchase Price Bridge | E3: Gross Sources and Uses
A4: Enterprise value | B4: 108 | E4: Sources | F4: Amount | G4: Uses | H4: Amount
A5: Less: seller net debt and debt-like items | B5: -10.2 | E5: First-lien term loan | F5: 42.8 | G5: Seller equity purchase price | H5: 97.8
A6: Seller equity value | B6: 97.8 | E6: Sponsor cash equity | F6: 62 | G6: Debt and debt-like settlement | H6: 14.4
A7: Less: seller rollover | B7: -12 | E7: Seller rollover equity | F7: 12 | G7: Buyer transaction expenses | H7: 4.4
A8: Cash consideration | B8: 85.8 | E8: Acquired cash | F8: 4.2 | G8: Financing fees and OID | H8: 1.4
E9: Total sources | F9: 121 | G9: Opening cash | H9: 3
G10: Total uses | H10: 121
E11: S&U check | F11: 0
A13: Opening Pro Forma Balance Sheet - March 31, 2026
A14: Assets | B14: Amount | D14: Liabilities and Equity | E14: Amount | G14: Source
A15: Cash | B15: 3 | D15: Accounts payable | E15: 4.1 | G15: KS-DL-1.2 / PPA
A16: Accounts receivable | B16: 13.2 | D16: Accrued liabilities | E16: 5.6 | G16: KS-DL-1.2 / PPA
A17: Unbilled WIP | B17: 4.9 | D17: Deferred revenue | E17: 0.9 | G17: KS-DL-1.2 / PPA
A18: Prepaids | B18: 0.9 | D18: Term loan | E18: 42.8 | G18: KS-DL-1.2 / PPA
A19: PP&E, net | B19: 3.4 | D19: Deferred tax liability | E19: 8.5 | G19: KS-DL-1.2 / PPA
A20: Goodwill | B20: 71 | D20: Other liabilities | E20: 1.6 | G20: KS-DL-1.2 / PPA
A21: Customer relationships | B21: 28 | D21: Equity | E21: 69.6 | G21: KS-DL-1.2 / PPA
A22: Trade name | B22: 5 | G22: KS-DL-1.2 / PPA
A23: Non-compete | B23: 1 | G23: KS-DL-1.2 / PPA
A24: Deferred financing fees | B24: 1.4 | G24: KS-DL-1.2 / PPA
A25: Other assets | B25: 1.3 | G25: KS-DL-1.2 / PPA
A26: Total assets | B26: 133.1 | D26: Total liabilities & equity | E26: 133.1
A27: Balance sheet check | B27: 0

Sheet Purchase_Accounting
A1: Purchase Accounting and Intangible Amortization ($mm)
A3: Allocation Item | B3: Fair Value | C3: Useful Life | D3: Annual Amortization | E3: Tax Basis | F3: Source / Assumption
A4: Normalized net working capital | B4: 8.4 | C4: N/A | D4: 0 | E4: Carryover | F4: KS-DL-1.2
A5: PP&E | B5: 3.4 | C5: 5 years | D5: 0.68 | E5: Carryover | F5: KS-DL-1.2 / model
A6: Other net operating assets | B6: -0.3 | C6: N/A | D6: 0 | E6: Carryover | F6: Model completion assumption
A7: Customer relationships | B7: 28 | C7: 10 years | D7: 2.8 | E7: No step-up | F7: KS-MA-PPA-001
A8: Trade name | B8: 5 | C8: Indefinite | D8: 0 | E8: No step-up | F8: KS-MA-PPA-002
A9: Non-compete | B9: 1 | C9: 5 years | D9: 0.2 | E9: No step-up | F9: KS-MA-PPA-003
A10: Deferred tax liability | B10: -8.5 | C10: N/A | D10: 0 | E10: N/A | F10: 26% of non-tax-deductible intangibles
A11: Goodwill | B11: 71 | C11: Indefinite | D11: 0 | E11: No step-up | F11: Residual
A12: Enterprise value | B12: 108 | D12: 3 | F12: Check

Sheet Seller_Model
A1: Seller Operating Model - Updated January 2026 Financial Supplement ($mm)
A3: Line Item | B3: FY2025A | C3: FY2026E | D3: FY2027E | E3: FY2028E | F3: FY2029E | G3: FY2030E | H3: Source
A4: Revenue | B4: 74 | C4: 82.1 | D4: 90.7 | E4: 100.1 | F4: 110 | G4: 120.4 | H4: CIM supplement
A5: Growth | B5: 0.131 | C5: 0.109 | D5: 0.105 | E5: 0.104 | F5: 0.099 | G5: 0.095 | H5: Management forecast
A6: Management-adjusted EBITDA | B6: 12.7 | C6: 15 | D6: 16.9 | E6: 18.9 | F6: 21.1 | G6: 23.5 | H6: Seller-defined EBITDA
A7: EBITDA margin | B7: 0.172 | C7: 0.183 | D7: 0.186 | E7: 0.189 | F7: 0.192 | G7: 0.195 | H7: Management forecast
A8: Capital expenditure | B8: 1.2 | C8: 1.3 | D8: 1.5 | E8: 1.6 | F8: 1.8 | G8: 1.9 | H8: Management forecast
A9: Capex / revenue | B9: 0.016 | C9: 0.016 | D9: 0.016 | E9: 0.016 | F9: 0.016 | G9: 0.016 | H9: Management forecast

Sheet Scenario_Drivers
A1: Quarterly Scenario Drivers and Transaction Events
A3: Driver | B3: Unit | C3: 46203 | D3: 46295 | E3: 46387 | F3: 46477 | G3: 46568 | H3: 46660 | I3: 46752 | J3: 46843 | K3: 46934 | L3: 47026 | M3: 47118 | N3: 47208 | O3: 47299 | P3: 47391 | Q3: 47483 | R3: 47573 | S3: 47664 | T3: 47756 | U3: 47848 | V3: 47938
A4: Standalone Base
A5: Revenue | B5: $mm | C5: 19.795 | D5: 20.5868 | E5: 20.5868 | F5: 19.486198 | G5: 21.18065 | H5: 22.027876 | I5: 22.027876 | J5: 20.850232 | K5: 22.663296 | L5: 23.569827 | M5: 23.569827 | N5: 22.309748 | O5: 24.249726 | P5: 25.219715 | Q5: 25.219715 | R5: 23.87143 | S5: 25.947207 | T5: 26.985095 | U5: 26.985095 | V5: 25.542431
A6: Gross margin | B6: % | C6: 0.362 | D6: 0.362 | E6: 0.362 | F6: 0.365 | G6: 0.365 | H6: 0.365 | I6: 0.365 | J6: 0.368 | K6: 0.368 | L6: 0.368 | M6: 0.368 | N6: 0.371 | O6: 0.371 | P6: 0.371 | Q6: 0.371 | R6: 0.374 | S6: 0.374 | T6: 0.374 | U6: 0.374 | V6: 0.377
A7: Firm EBITDA | B7: $mm | C7: 3.08802 | D7: 3.2115408 | E7: 3.2115408 | F7: 3.1372779 | G7: 3.4100847 | H7: 3.546488 | I7: 3.546488 | J7: 3.4402883 | K7: 3.7394438 | L7: 3.8890215 | M7: 3.8890215 | N7: 3.7703474 | O7: 4.0982037 | P7: 4.2621319 | Q7: 4.2621319 | R7: 4.1297575 | S7: 4.4888668 | T7: 4.6684215 | U7: 4.6684215 | V7: 4.5210102
A8: One-time charges | B8: $mm | C8: 0 | D8: 0 | E8: 0 | F8: 0 | G8: 0 | H8: 0 | I8: 0 | J8: 0 | K8: 0 | L8: 0 | M8: 0 | N8: 0 | O8: 0 | P8: 0 | Q8: 0 | R8: 0 | S8: 0 | T8: 0 | U8: 0 | V8: 0
A9: Covenant add-backs | B9: $mm | C9: 0 | D9: 0 | E9: 0 | F9: 0 | G9: 0 | H9: 0 | I9: 0 | J9: 0 | K9: 0 | L9: 0 | M9: 0 | N9: 0 | O9: 0 | P9: 0 | Q9: 0 | R9: 0 | S9: 0 | T9: 0 | U9: 0 | V9: 0
A10: DSO | B10: days | C10: 64 | D10: 64 | E10: 64 | F10: 63 | G10: 63 | H10: 63 | I10: 63 | J10: 62 | K10: 62 | L10: 62 | M10: 62 | N10: 61 | O10: 61 | P10: 61 | Q10: 61 | R10: 60 | S10: 60 | T10: 60 | U10: 60 | V10: 60
A11: WIP / annualized revenue | B11: % | C11: 0.067 | D11: 0.067 | E11: 0.067 | F11: 0.065 | G11: 0.065 | H11: 0.065 | I11: 0.065 | J11: 0.063 | K11: 0.063 | L11: 0.063 | M11: 0.063 | N11: 0.061 | O11: 0.061 | P11: 0.061 | Q11: 0.061 | R11: 0.06 | S11: 0.06 | T11: 0.06 | U11: 0.06 | V11: 0.06
A12: Prepaids / annualized revenue | B12: % | C12: 0.012 | D12: 0.012 | E12: 0.012 | F12: 0.012 | G12: 0.012 | H12: 0.012 | I12: 0.012 | J12: 0.012 | K12: 0.012 | L12: 0.012 | M12: 0.012 | N12: 0.012 | O12: 0.012 | P12: 0.012 | Q12: 0.012 | R12: 0.012 | S12: 0.012 | T12: 0.012 | U12: 0.012 | V12: 0.012
A13: AP / annualized revenue | B13: % | C13: 0.055 | D13: 0.055 | E13: 0.055 | F13: 0.055 | G13: 0.055 | H13: 0.055 | I13: 0.055 | J13: 0.055 | K13: 0.055 | L13: 0.055 | M13: 0.055 | N13: 0.055 | O13: 0.055 | P13: 0.055 | Q13: 0.055 | R13: 0.055 | S13: 0.055 | T13: 0.055 | U13: 0.055 | V13: 0.055
A14: Accruals / annualized revenue | B14: % | C14: 0.075 | D14: 0.075 | E14: 0.075 | F14: 0.075 | G14: 0.075 | H14: 0.075 | I14: 0.075 | J14: 0.075 | K14: 0.075 | L14: 0.075 | M14: 0.075 | N14: 0.075 | O14: 0.075 | P14: 0.075 | Q14: 0.075 | R14: 0.075 | S14: 0.075 | T14: 0.075 | U14: 0.075 | V14: 0.075
A15: Deferred revenue / annualized revenue | B15: % | C15: 0.012 | D15: 0.012 | E15: 0.012 | F15: 0.012 | G15: 0.012 | H15: 0.012 | I15: 0.012 | J15: 0.012 | K15: 0.012 | L15: 0.012 | M15: 0.012 | N15: 0.012 | O15: 0.012 | P15: 0.012 | Q15: 0.012 | R15: 0.012 | S15: 0.012 | T15: 0.012 | U15: 0.012 | V15: 0.012
A16: Capex / revenue | B16: % | C16: 0.016 | D16: 0.016 | E16: 0.016 | F16: 0.016 | G16: 0.016 | H16: 0.016 | I16: 0.016 | J16: 0.016 | K16: 0.016 | L16: 0.016 | M16: 0.016 | N16: 0.016 | O16: 0.016 | P16: 0.016 | Q16: 0.016 | R16: 0.016 | S16: 0.016 | T16: 0.016 | U16: 0.016 | V16: 0.016
... A36: Seasonality | B36: % | C36: 0.25 | D36: 0.26 | E36: 0.26 | F36: 0.23 | G36: 0.25 | H36: 0.26 | I36: 0.26 | J36: 0.23 | K36: 0.25 | L36: 0.26 | M36: 0.26 | N36: 0.23 | O36: 0.25 | P36: 0.26 | Q36: 0.26 | R36: 0.23 | S36: 0.25 | T36: 0.26 | U36: 0.26 | V36: 0.23
A38: Standalone Downside
A39: Revenue | B39: $mm | C39: 19.24 | D39: 20.0096 | E39: 20.0096 | F39: 18.054816 | G39: 19.6248 | H39: 20.409792 | I39: 20.409792 | J39: 18.777009 | K39: 20.409792 | L39: 21.226184 | M39: 21.226184 | N39: 19.715859 | O39: 21.430282 | P39: 22.287493 | Q39: 22.287493 | R39: 20.701652 | S39: 22.501796 | T39: 23.401868 | U39: 23.401868 | V39: 21.736735
A40: Gross margin | B40: % | C40: 0.355 | D40: 0.355 | E40: 0.355 | F40: 0.345 | G40: 0.345 | H40: 0.345 | I40: 0.345 | J40: 0.35 | K40: 0.35 | L40: 0.35 | M40: 0.35 | N40: 0.355 | O40: 0.355 | P40: 0.355 | Q40: 0.355 | R40: 0.36 | S40: 0.36 | T40: 0.36 | U40: 0.36 | V40: 0.362
A41: Firm EBITDA | B41: $mm | C41: 2.7898 | D41: 2.901392 | E41: 2.901392 | F41: 2.4374002 | G41: 2.649348 | H41: 2.7553219 | I41: 2.7553219 | J41: 2.7226663 | K41: 2.9594198 | L41: 3.0777966 | M41: 3.0777966 | N41: 3.0165264 | O41: 3.2788331 | P41: 3.4099864 | Q41: 3.4099864 | R41: 3.270861 | S41: 3.5552837 | T41: 3.6974951 | U41: 3.6974951 | V41: 3.521351
A42: One-time charges | B42: $mm | C42: 0 | D42: 0 | E42: 0 | F42: 0 | G42: 0 | H42: 0 | I42: 0 | J42: 0 | K42: 0 | L42: 0 | M42: 0 | N42: 0 | O42: 0 | P42: 0 | Q42: 0 | R42: 0 | S42: 0 | T42: 0 | U42: 0 | V42: 0
A43: Covenant add-backs | B43: $mm | C43: 0 | D43: 0 | E43: 0 | F43: 0 | G43: 0 | H43: 0 | I43: 0 | J43: 0 | K43: 0 | L43: 0 | M43: 0 | N43: 0 | O43: 0 | P43: 0 | Q43: 0 | R43: 0 | S43: 0 | T43: 0 | U43: 0 | V43: 0
A44: DSO | B44: days | C44: 67 | D44: 67 | E44: 67 | F44: 75 | G44: 75 | H44: 75 | I44: 75 | J44: 72 | K44: 72 | L44: 72 | M44: 72 | N44: 69 | O44: 69 | P44: 69 | Q44: 69 | R44: 67 | S44: 67 | T44: 67 | U44: 67 | V44: 66
A45: WIP / annualized revenue | B45: % | C45: 0.07 | D45: 0.07 | E45: 0.07 | F45: 0.08 | G45: 0.08 | H45: 0.08 | I45: 0.08 | J45: 0.075 | K45: 0.075 | L45: 0.075 | M45: 0.075 | N45: 0.07 | O45: 0.07 | P45: 0.07 | Q45: 0.07 | R45: 0.068 | S45: 0.068 | T45: 0.068 | U45: 0.068 | V45: 0.066
A46: Prepaids / annualized revenue | B46: % | C46: 0.012 | D46: 0.012 | E46: 0.012 | F46: 0.012 | G46: 0.012 | H46: 0.012 | I46: 0.012 | J46: 0.012 | K46: 0.012 | L46: 0.012 | M46: 0.012 | N46: 0.012 | O46: 0.012 | P46: 0.012 | Q46: 0.012 | R46: 0.012 | S46: 0.012 | T46: 0.012 | U46: 0.012 | V46: 0.012
A47: AP / annualized revenue | B47: % | C47: 0.055 | D47: 0.055 | E47: 0.055 | F47: 0.055 | G47: 0.055 | H47: 0.055 | I47: 0.055 | J47: 0.055 | K47: 0.055 | L47: 0.055 | M47: 0.055 | N47: 0.055 | O47: 0.055 | P47: 0.055 | Q47: 0.055 | R47: 0.055 | S47: 0.055 | T47: 0.055 | U47: 0.055 | V47: 0.055
A48: Accruals / annualized revenue | B48: % | C48: 0.075 | D48: 0.075 | E48: 0.075 | F48: 0.075 | G48: 0.075 | H48: 0.075 | I48: 0.075 | J48: 0.075 | K48: 0.075 | L48: 0.075 | M48: 0.075 | N48: 0.075 | O48: 0.075 | P48: 0.075 | Q48: 0.075 | R48: 0.075 | S48: 0.075 | T48: 0.075 | U48: 0.075 | V48: 0.075
A49: Deferred revenue / annualized revenue | B49: % | C49: 0.012 | D49: 0.012 | E49: 0.012 | F49: 0.012 | G49: 0.012 | H49: 0.012 | I49: 0.012 | J49: 0.012 | K49: 0.012 | L49: 0.012 | M49: 0.012 | N49: 0.012 | O49: 0.012 | P49: 0.012 | Q49: 0.012 | R49: 0.012 | S49: 0.012 | T49: 0.012 | U49: 0.012 | V49: 0.012
A50: Capex / revenue | B50: % | C50: 0.016 | D50: 0.016 | E50: 0.016 | F50: 0.016 | G50: 0.016 | H50: 0.016 | I50: 0.016 | J50: 0.016 | K50: 0.016 | L50: 0.016 | M50: 0.016 | N50: 0.016 | O50: 0.016 | P50: 0.016 | Q50: 0.016 | R50: 0.016 | S50: 0.016 | T50: 0.016 | U50: 0.016 | V50: 0.016
... A70: Seasonality | B70: % | C70: 0.25 | D70: 0.26 | E70: 0.26 | F70: 0.23 | G70: 0.25 | H70: 0.26 | I70: 0.26 | J70: 0.23 | K70: 0.25 | L70: 0.26 | M70: 0.26 | N70: 0.23 | O70: 0.25 | P70: 0.26 | Q70: 0.26 | R70: 0.23 | S70: 0.25 | T70: 0.26 | U70: 0.26 | V70: 0.23
A72: Standalone Upside
A73: Revenue | B73: $mm | C73: 20.0725 | D73: 20.8754 | E73: 20.8754 | F73: 20.036369 | G73: 21.778662 | H73: 22.649809 | I73: 22.649809 | J73: 21.739461 | K73: 23.629849 | L73: 24.575043 | M73: 24.575043 | N73: 23.587315 | O73: 25.638386 | P73: 26.663921 | Q73: 26.663921 | R73: 25.592237 | S73: 27.817649 | T73: 28.930355 | U73: 28.930355 | V73: 27.767577
A74: Gross margin | B74: % | C74: 0.365 | D74: 0.365 | E74: 0.365 | F74: 0.372 | G74: 0.372 | H74: 0.372 | I74: 0.372 | J74: 0.378 | K74: 0.378 | L74: 0.378 | M74: 0.378 | N74: 0.382 | O74: 0.382 | P74: 0.382 | Q74: 0.382 | R74: 0.384 | S74: 0.384 | T74: 0.384 | U74: 0.384 | V74: 0.385
A75: Firm EBITDA | B75: $mm | C75: 3.2116 | D75: 3.340064 | E75: 3.340064 | F75: 3.3661101 | G75: 3.6588153 | H75: 3.8051679 | I75: 3.8051679 | J75: 3.7826662 | K75: 4.1115937 | L75: 4.2760574 | M75: 4.2760574 | N75: 4.2457167 | O75: 4.6149095 | P75: 4.7995059 | Q75: 4.7995059 | R75: 4.6833793 | S75: 5.0906297 | T75: 5.2942549 | U75: 5.2942549 | V75: 5.1370017
A76: One-time charges | B76: $mm | C76: 0 | D76: 0 | E76: 0 | F76: 0 | G76: 0 | H76: 0 | I76: 0 | J76: 0 | K76: 0 | L76: 0 | M76: 0 | N76: 0 | O76: 0 | P76: 0 | Q76: 0 | R76: 0 | S76: 0 | T76: 0 | U76: 0 | V76: 0
A77: Covenant add-backs | B77: $mm | C77: 0 | D77: 0 | E77: 0 | F77: 0 | G77: 0 | H77: 0 | I77: 0 | J77: 0 | K77: 0 | L77: 0 | M77: 0 | N77: 0 | O77: 0 | P77: 0 | Q77: 0 | R77: 0 | S77: 0 | T77: 0 | U77: 0 | V77: 0
A78: DSO | B78: days | C78: 62 | D78: 62 | E78: 62 | F78: 60 | G78: 60 | H78: 60 | I78: 60 | J78: 59 | K78: 59 | L78: 59 | M78: 59 | N78: 58 | O78: 58 | P78: 58 | Q78: 58 | R78: 58 | S78: 58 | T78: 58 | U78: 58 | V78: 58
A79: WIP / annualized revenue | B79: % | C79: 0.065 | D79: 0.065 | E79: 0.065 | F79: 0.062 | G79: 0.062 | H79: 0.062 | I79: 0.062 | J79: 0.06 | K79: 0.06 | L79: 0.06 | M79: 0.06 | N79: 0.058 | O79: 0.058 | P79: 0.058 | Q79: 0.058 | R79: 0.057 | S79: 0.057 | T79: 0.057 | U79: 0.057 | V79: 0.056
A80: Prepaids / annualized revenue | B80: % | C80: 0.012 | D80: 0.012 | E80: 0.012 | F80: 0.012 | G80: 0.012 | H80: 0.012 | I80: 0.012 | J80: 0.012 | K80: 0.012 | L80: 0.012 | M80: 0.012 | N80: 0.012 | O80: 0.012 | P80: 0.012 | Q80: 0.012 | R80: 0.012 | S80: 0.012 | T80: 0.012 | U80: 0.012 | V80: 0.012
A81: AP / annualized revenue | B81: % | C81: 0.055 | D81: 0.055 | E81: 0.055 | F81: 0.055 | G81: 0.055 | H81: 0.055 | I81: 0.055 | J81: 0.055 | K81: 0.055 | L81: 0.055 | M81: 0.055 | N81: 0.055 | O81: 0.055 | P81: 0.055 | Q81: 0.055 | R81: 0.055 | S81: 0.055 | T81: 0.055 | U81: 0.055 | V81: 0.055
A82: Accruals / annualized revenue | B82: % | C82: 0.075 | D82: 0.075 | E82: 0.075 | F82: 0.075 | G82: 0.075 | H82: 0.075 | I82: 0.075 | J82: 0.075 | K82: 0.075 | L82: 0.075 | M82: 0.075 | N82: 0.075 | O82: 0.075 | P82: 0.075 | Q82: 0.075 | R82: 0.075 | S82: 0.075 | T82: 0.075 | U82: 0.075 | V82: 0.075
A83: Deferred revenue / annualized revenue | B83: % | C83: 0.012 | D83: 0.012 | E83: 0.012 | F83: 0.012 | G83: 0.012 | H83: 0.012 | I83: 0.012 | J83: 0.012 | K83: 0.012 | L83: 0.012 | M83: 0.012 | N83: 0.012 | O83: 0.012 | P83: 0.012 | Q83: 0.012 | R83: 0.012 | S83: 0.012 | T83: 0.012 | U83: 0.012 | V83: 0.012
A84: Capex / revenue | B84: % | C84: 0.016 | D84: 0.016 | E84: 0.016 | F84: 0.016 | G84: 0.016 | H84: 0.016 | I84: 0.016 | J84: 0.016 | K84: 0.016 | L84: 0.016 | M84: 0.016 | N84: 0.016 | O84: 0.016 | P84: 0.016 | Q84: 0.016 | R84: 0.016 | S84: 0.016 | T84: 0.016 | U84: 0.016 | V84: 0.016
... A104: Seasonality | B104: % | C104: 0.25 | D104: 0.26 | E104: 0.26 | F104: 0.23 | G104: 0.25 | H104: 0.26 | I104: 0.26 | J104: 0.23 | K104: 0.25 | L104: 0.26 | M104: 0.26 | N104: 0.23 | O104: 0.25 | P104: 0.26 | Q104: 0.26 | R104: 0.23 | S104: 0.25 | T104: 0.26 | U104: 0.26 | V104: 0.23
A106: Acquisition Base
A107: Revenue | B107: $mm | C107: 19.795 | D107: 20.5868 | E107: 22.82559 | F107: 21.469137 | G107: 23.338707 | H107: 27.239056 | I107: 27.24186 | J107: 25.465085 | K107: 27.682143 | L107: 28.792243 | M107: 28.795061 | N107: 26.934566 | O107: 29.279418 | P107: 30.453423 | Q107: 30.456255 | R107: 28.506262 | S107: 30.987797 | T107: 32.230152 | U107: 32.232998 | V107: 30.187327
A108: Gross margin | B108: % | C108: 0.362 | D108: 0.362 | E108: 0.36082301 | F108: 0.36361457 | G108: 0.363613 | H108: 0.36213031 | I108: 0.36212906 | J108: 0.36473799 | K108: 0.36473655 | L108: 0.36473511 | M108: 0.36473367 | N108: 0.36739418 | O108: 0.36739257 | P108: 0.36739095 | Q108: 0.36738933 | R108: 0.37009784 | S108: 0.37009607 | T108: 0.3700943 | U108: 0.37009252 | V108: 0.37284553
A109: Firm EBITDA | B109: $mm | C109: 3.08802 | D109: 3.2115408 | E109: 3.5393904 | F109: 3.4298254 | G109: 3.7808239 | H109: 4.4406419 | I109: 4.4962336 | J109: 4.3527078 | K109: 4.6692023 | L109: 4.8555821 | M109: 4.7112005 | N109: 4.5026356 | O109: 4.8995843 | P109: 5.1012062 | Q109: 5.1068515 | R109: 4.8820093 | S109: 5.311973 | T109: 5.5301174 | U109: 5.5357898 | V109: 5.2933214
A110: One-time charges | B110: $mm | C110: 0 | D110: 0.6 | E110: 0.2 | F110: 0.2 | G110: 1 | H110: 0.25 | I110: 0.15 | J110: 0.1 | K110: 0 | L110: 0 | M110: 0 | N110: 0 | O110: 0 | P110: 0 | Q110: 0 | R110: 0 | S110: 0 | T110: 0 | U110: 0 | V110: 0
A111: Covenant add-backs | B111: $mm | C111: 0 | D111: 0.48173112 | E111: 0.2 | F111: 0.2 | G111: 0.56712358 | H111: 0.25 | I111: 0.15 | J111: 0.1 | K111: 0 | L111: 0 | M111: 0 | N111: 0 | O111: 0 | P111: 0 | Q111: 0 | R111: 0 | S111: 0 | T111: 0 | U111: 0 | V111: 0
A112: DSO | B112: days | C112: 64 | D112: 64 | E112: 64 | F112: 63 | G112: 63 | H112: 63 | I112: 63 | J112: 62 | K112: 62 | L112: 62 | M112: 62 | N112: 61 | O112: 61 | P112: 61 | Q112: 61 | R112: 60 | S112: 60 | T112: 60 | U112: 60 | V112: 60
A113: WIP / annualized revenue | B113: % | C113: 0.067 | D113: 0.067 | E113: 0.067 | F113: 0.065 | G113: 0.065 | H113: 0.065 | I113: 0.065 | J113: 0.063 | K113: 0.063 | L113: 0.063 | M113: 0.063 | N113: 0.061 | O113: 0.061 | P113: 0.061 | Q113: 0.061 | R113: 0.06 | S113: 0.06 | T113: 0.06 | U113: 0.06 | V113: 0.06
A114: Prepaids / annualized revenue | B114: % | C114: 0.012 | D114: 0.012 | E114: 0.012 | F114: 0.012 | G114: 0.012 | H114: 0.012 | I114: 0.012 | J114: 0.012 | K114: 0.012 | L114: 0.012 | M114: 0.012 | N114: 0.012 | O114: 0.012 | P114: 0.012 | Q114: 0.012 | R114: 0.012 | S114: 0.012 | T114: 0.012 | U114: 0.012 | V114: 0.012
A115: AP / annualized revenue | B115: % | C115: 0.055 | D115: 0.055 | E115: 0.055 | F115: 0.055 | G115: 0.055 | H115: 0.055 | I115: 0.055 | J115: 0.055 | K115: 0.055 | L115: 0.055 | M115: 0.055 | N115: 0.055 | O115: 0.055 | P115: 0.055 | Q115: 0.055 | R115: 0.055 | S115: 0.055 | T115: 0.055 | U115: 0.055 | V115: 0.055
A116: Accruals / annualized revenue | B116: % | C116: 0.075 | D116: 0.075 | E116: 0.075 | F116: 0.075 | G116: 0.075 | H116: 0.075 | I116: 0.075 | J116: 0.075 | K116: 0.075 | L116: 0.075 | M116: 0.075 | N116: 0.075 | O116: 0.075 | P116: 0.075 | Q116: 0.075 | R116: 0.075 | S116: 0.075 | T116: 0.075 | U116: 0.075 | V116: 0.075
A117: Deferred revenue / annualized revenue | B117: % | C117: 0.012 | D117: 0.012 | E117: 0.012 | F117: 0.012 | G117: 0.012 | H117: 0.012 | I117: 0.012 | J117: 0.012 | K117: 0.012 | L117: 0.012 | M117: 0.012 | N117: 0.012 | O117: 0.012 | P117: 0.012 | Q117: 0.012 | R117: 0.012 | S117: 0.012 | T117: 0.012 | U117: 0.012 | V117: 0.012
A118: Capex / revenue | B118: % | C118: 0.016 | D118: 0.016 | E118: 0.016 | F118: 0.016 | G118: 0.016 | H118: 0.016 | I118: 0.016 | J118: 0.016 | K118: 0.016 | L118: 0.016 | M118: 0.016 | N118: 0.016 | O118: 0.016 | P118: 0.016 | Q118: 0.016 | R118: 0.016 | S118: 0.016 | T118: 0.016 | U118: 0.016 | V118: 0.016
... A138: Seasonality | B138: % | C138: 0.25 | D138: 0.26 | E138: 0.26 | F138: 0.23 | G138: 0.25 | H138: 0.26 | I138: 0.26 | J138: 0.23 | K138: 0.25 | L138: 0.26 | M138: 0.26 | N138: 0.23 | O138: 0.25 | P138: 0.26 | Q138: 0.26 | R138: 0.23 | S138: 0.25 | T138: 0.26 | U138: 0.26 | V138: 0.23
A140: Combined Risk
A141: Revenue | B141: $mm | C141: 19.795 | D141: 20.5 | E141: 22 | F141: 20 | G141: 19 | H141: 19.5 | I141: 20 | J141: 20.5 | K141: 21.5 | L141: 22.5 | M141: 23.5 | N141: 23.5 | O141: 24 | P141: 25 | Q141: 25.5 | R141: 26 | S141: 27 | T141: 27.5 | U141: 28 | V141: 29
A142: Gross margin | B142: % | C142: 0.355 | D142: 0.35650312 | E142: 0.3678132 | F142: 0.32317001 | G142: 0.36980927 | H142: 0.37479032 | I142: 0.36546963 | J142: 0.36626889 | K142: 0.37964522 | L142: 0.37732676 | M142: 0.36131227 | N142: 0.36086588 | O142: 0.38411335 | P142: 0.38353837 | Q142: 0.37605687 | R142: 0.36857019 | S142: 0.38581739 | T142: 0.3939908 | U142: 0.38699083 | V142: 0.35648156
A143: Firm EBITDA | B143: $mm | C143: 2.870275 | D143: 2.8 | E143: 3 | F143: 2.55 | G143: 2.45 | H143: 2.55 | I143: 2.75 | J143: 2.8 | K143: 2.95 | L143: 3.1 | M143: 3.25 | N143: 3.3 | O143: 3.45 | P143: 3.65 | Q143: 3.8 | R143: 3.95 | S143: 4.15 | T143: 4.35 | U143: 4.55 | V143: 4.8
A144: One-time charges | B144: $mm | C144: 0 | D144: 0.1 | E144: 0.2 | F144: 0.35 | G144: 0.75 | H144: 0.35 | I144: 0.25 | J144: 0.2 | K144: 0.15 | L144: 0.1 | M144: 0.05 | N144: 0 | O144: 0 | P144: 0 | Q144: 0 | R144: 0 | S144: 0 | T144: 0 | U144: 0 | V144: 0
A145: Covenant add-backs | B145: $mm | C145: 0 | D145: 0.1 | E145: 0.2 | F145: 0.5 | G145: 0.6 | H145: 0.35 | I145: 0.25 | J145: 0.2 | K145: 0.15 | L145: 0.1 | M145: 0.05 | N145: 0 | O145: 0 | P145: 0 | Q145: 0 | R145: 0 | S145: 0 | T145: 0 | U145: 0 | V145: 0
A146: DSO | B146: days | C146: 68 | D146: 68 | E146: 68 | F146: 82 | G146: 82 | H146: 82 | I146: 82 | J146: 74 | K146: 74 | L146: 74 | M146: 74 | N146: 68 | O146: 68 | P146: 68 | Q146: 68 | R146: 64 | S146: 64 | T146: 64 | U146: 64 | V146: 62
A147: WIP / annualized revenue | B147: % | C147: 0.078 | D147: 0.078 | E147: 0.078 | F147: 0.105 | G147: 0.105 | H147: 0.105 | I147: 0.105 | J147: 0.085 | K147: 0.085 | L147: 0.085 | M147: 0.085 | N147: 0.072 | O147: 0.072 | P147: 0.072 | Q147: 0.072 | R147: 0.065 | S147: 0.065 | T147: 0.065 | U147: 0.065 | V147: 0.062
A148: Prepaids / annualized revenue | B148: % | C148: 0.012 | D148: 0.012 | E148: 0.012 | F148: 0.012 | G148: 0.012 | H148: 0.012 | I148: 0.012 | J148: 0.012 | K148: 0.012 | L148: 0.012 | M148: 0.012 | N148: 0.012 | O148: 0.012 | P148: 0.012 | Q148: 0.012 | R148: 0.012 | S148: 0.012 | T148: 0.012 | U148: 0.012 | V148: 0.012
A149: AP / annualized revenue | B149: % | C149: 0.055 | D149: 0.055 | E149: 0.055 | F149: 0.055 | G149: 0.055 | H149: 0.055 | I149: 0.055 | J149: 0.055 | K149: 0.055 | L149: 0.055 | M149: 0.055 | N149: 0.055 | O149: 0.055 | P149: 0.055 | Q149: 0.055 | R149: 0.055 | S149: 0.055 | T149: 0.055 | U149: 0.055 | V149: 0.055
A150: Accruals / annualized revenue | B150: % | C150: 0.075 | D150: 0.075 | E150: 0.075 | F150: 0.075 | G150: 0.075 | H150: 0.075 | I150: 0.075 | J150: 0.075 | K150: 0.075 | L150: 0.075 | M150: 0.075 | N150: 0.075 | O150: 0.075 | P150: 0.075 | Q150: 0.075 | R150: 0.075 | S150: 0.075 | T150: 0.075 | U150: 0.075 | V150: 0.075
A151: Deferred revenue / annualized revenue | B151: % | C151: 0.012 | D151: 0.012 | E151: 0.012 | F151: 0.012 | G151: 0.012 | H151: 0.012 | I151: 0.012 | J151: 0.012 | K151: 0.012 | L151: 0.012 | M151: 0.012 | N151: 0.012 | O151: 0.012 | P151: 0.012 | Q151: 0.012 | R151: 0.012 | S151: 0.012 | T151: 0.012 | U151: 0.012 | V151: 0.012
A152: Capex / revenue | B152: % | C152: 0.016 | D152: 0.016 | E152: 0.016 | F152: 0.016 | G152: 0.016 | H152: 0.016 | I152: 0.016 | J152: 0.016 | K152: 0.016 | L152: 0.016 | M152: 0.016 | N152: 0.016 | O152: 0.016 | P152: 0.016 | Q152: 0.016 | R152: 0.016 | S152: 0.016 | T152: 0.016 | U152: 0.016 | V152: 0.016
... A172: Seasonality | B172: % | C172: 0.25 | D172: 0.26 | E172: 0.26 | F172: 0.23 | G172: 0.25 | H172: 0.26 | I172: 0.26 | J172: 0.23 | K172: 0.25 | L172: 0.26 | M172: 0.26 | N172: 0.23 | O172: 0.25 | P172: 0.26 | Q172: 0.26 | R172: 0.23 | S172: 0.25 | T172: 0.26 | U172: 0.26 | V172: 0.23

Sheet SB_Base
A1: Project Keystone - Standalone Base Quarterly LBO ($mm)
A3: Line Item | B3: Unit | C3: 46203 | D3: 46295 | E3: 46387 | F3: 46477 | G3: 46568 | H3: 46660 | I3: 46752 | J3: 46843 | K3: 46934 | L3: 47026 | M3: 47118 | N3: 47208 | O3: 47299 | P3: 47391 | Q3: 47483 | R3: 47573 | S3: 47664 | T3: 47756 | U3: 47848 | V3: 47938
A4: Operating Model
A5: Revenue | B5: $mm | C5: ='Scenario_Drivers'!C5 | D5: ='Scenario_Drivers'!D5 | E5: ='Scenario_Drivers'!E5 | F5: ='Scenario_Drivers'!F5 | G5: ='Scenario_Drivers'!G5 | H5: ='Scenario_Drivers'!H5 | I5: ='Scenario_Drivers'!I5 | J5: ='Scenario_Drivers'!J5 | ... V5: ='Scenario_Drivers'!V5
A6: Growth | B6: % | C6: =C5/(74.0*'Scenario_Drivers'!C36)-1 | D6: =D5/C5-1 | E6: =E5/D5-1 | F6: =F5/V5-1 | G6: =G5/F5-1 | H6: =H5/G5-1 | I6: =I5/H5-1 | J6: =J5/F5-1 | K6: =K5/J5-1 | L6: =L5/K5-1 | M6: =M5/L5-1 | N6: =N5/J5-1 | O6: =O5/N5-1 | P6: =P5/O5-1 | Q6: =Q5/P5-1 | R6: =R5/N5-1 | S6: =S5/R5-1 | T6: =T5/S5-1 | U6: =U5/T5-1 | V6: =V5/R5-1
A7: Gross margin | B7: % | C7: ='Scenario_Drivers'!C6 | D7: ='Scenario_Drivers'!D6 | E7: ='Scenario_Drivers'!E6 | F7: ='Scenario_Drivers'!F6 | G7: ='Scenario_Drivers'!G6 | H7: ='Scenario_Drivers'!H6 | I7: ='Scenario_Drivers'!I6 | J7: ='Scenario_Drivers'!J6 | ... V7: ='Scenario_Drivers'!V6
A8: Gross profit | B8: $mm | C8: =C5*C7 | D8: =D5*D7 | E8: =E5*E7 | F8: =F5*F7 | G8: =G5*G7 | H8: =H5*H7 | I8: =I5*I7 | J8: =J5*J7 | ... V8: =V5*V7
A9: COGS | B9: $mm | C9: =-(C5-C8) | D9: =-(D5-D8) | E9: =-(E5-E8) | F9: =-(F5-F8) | G9: =-(G5-G8) | H9: =-(H5-H8) | I9: =-(I5-I8) | J9: =-(J5-J8) | ... V9: =-(V5-V8)
A10: Firm EBITDA | B10: $mm | C10: ='Scenario_Drivers'!C7 | D10: ='Scenario_Drivers'!D7 | E10: ='Scenario_Drivers'!E7 | F10: ='Scenario_Drivers'!F7 | G10: ='Scenario_Drivers'!G7 | H10: ='Scenario_Drivers'!H7 | I10: ='Scenario_Drivers'!I7 | J10: ='Scenario_Drivers'!J7 | ... V10: ='Scenario_Drivers'!V7
A11: One-time charges | B11: $mm | C11: =-'Scenario_Drivers'!C8 | D11: =-'Scenario_Drivers'!D8 | E11: =-'Scenario_Drivers'!E8 | F11: =-'Scenario_Drivers'!F8 | G11: =-'Scenario_Drivers'!G8 | H11: =-'Scenario_Drivers'!H8 | I11: =-'Scenario_Drivers'!I8 | J11: =-'Scenario_Drivers'!J8 | ... V11: =-'Scenario_Drivers'!V8
A12: Reported EBITDA | B12: $mm | C12: =C10+C11 | D12: =D10+D11 | E12: =E10+E11 | F12: =F10+F11 | G12: =G10+G11 | H12: =H10+H11 | I12: =I10+I11 | J12: =J10+J11 | ... V12: =V10+V11
A13: Covenant add-backs | B13: $mm | C13: ='Scenario_Drivers'!C9 | D13: ='Scenario_Drivers'!D9 | E13: ='Scenario_Drivers'!E9 | F13: ='Scenario_Drivers'!F9 | G13: ='Scenario_Drivers'!G9 | H13: ='Scenario_Drivers'!H9 | I13: ='Scenario_Drivers'!I9 | J13: ='Scenario_Drivers'!J9 | ... V13: ='Scenario_Drivers'!V9
A14: Covenant EBITDA | B14: $mm | C14: =C12+C13 | D14: =D12+D13 | E14: =E12+E13 | F14: =F12+F13 | G14: =G12+G13 | H14: =H12+H13 | I14: =I12+I13 | J14: =J12+J13 | ... V14: =V12+V13
A15: Firm EBITDA margin | B15: % | C15: =C10/C5 | D15: =D10/D5 | E15: =E10/E5 | F15: =F10/F5 | G15: =G10/G5 | H15: =H10/H5 | I15: =I10/I5 | J15: =J10/J5 | ... V15: =V10/V5
A16: Income Statement
A17: Depreciation | B17: $mm | C17: =C5*Inputs!$B$17 | D17: =D5*Inputs!$B$17 | E17: =E5*Inputs!$B$17 | F17: =F5*Inputs!$B$17 | G17: =G5*Inputs!$B$17 | H17: =H5*Inputs!$B$17 | I17: =I5*Inputs!$B$17 | J17: =J5*Inputs!$B$17 | ... V17: =V5*Inputs!$B$17
A18: Core PPA amortization | B18: $mm | C18: ='Scenario_Drivers'!C35 | D18: ='Scenario_Drivers'!D35 | E18: ='Scenario_Drivers'!E35 | F18: ='Scenario_Drivers'!F35 | G18: ='Scenario_Drivers'!G35 | H18: ='Scenario_Drivers'!H35 | I18: ='Scenario_Drivers'!I35 | J18: ='Scenario_Drivers'!J35 | ... V18: ='Scenario_Drivers'!V35
A19: Integration asset amortization | B19: $mm | C19: =0 | D19: =0 | E19: =0 | F19: =0 | G19: =0 | H19: =0 | I19: =0 | J19: =0 | ... V19: =0
A20: Total D&A | B20: $mm | C20: =SUM(C17:C19) | D20: =SUM(D17:D19) | E20: =SUM(E17:E19) | F20: =SUM(F17:F19) | G20: =SUM(G17:G19) | H20: =SUM(H17:H19) | I20: =SUM(I17:I19) | J20: =SUM(J17:J19) | ... V20: =SUM(V17:V19)
A21: EBIT | B21: $mm | C21: =C12-C20 | D21: =D12-D20 | E21: =E12-E20 | F21: =F12-F20 | G21: =G12-G20 | H21: =H12-H20 | I21: =I12-I20 | J21: =J12-J20 | ... V21: =V12-V20
A22: Cash interest | B22: $mm | C22: =-((('S&U_Opening'!$E$18+MAX(0,'S&U_Opening'!$E$18-(MIN(0.107,'S&U_Opening'!$E$18))))/2)*(MAX('Scenario_Drivers'!C33,Inputs!$B$26)+Inputs!$B$23+'Scenario_Drivers'!C34)/4+((0+0+'Scenario_Drivers'!C25-(IF(0>0,MIN(0.015,0),0)))/2)*(MAX('Scenario_Drivers'!C33,Inputs!$B$26)+Inputs!$B$25+'Scenario_Drivers'!C34)/4+0*(MAX('Scenario_Drivers'!C33,Inputs!$B$26)+Inputs!$B$24+'Scenario_Drivers'!C34)/4+MAX(0,Inputs!$B$20-0-'Scenario_Drivers'!C28)*Inputs!$B$29/4+0) | D22: =-(((C76+MAX(0,C76-(MIN(0.107,C76))))/2)*(MAX('Scenario_Drivers'!D33,Inputs!$B$26)+Inputs!$B$23+'Scenario_Drivers'!D34)/4+((C77+C77+'Scenario_Drivers'!D25-(IF(C77>0,MIN(0.015,C77),0)))/2)*(MAX('Scenario_Drivers'!D33,Inputs!$B$26)+Inputs!$B$25+'Scenario_Drivers'!D34)/4+C78*(MAX('Scenario_Drivers'!D33,Inputs!$B$26)+Inputs!$B$24+'Scenario_Drivers'!D34)/4+MAX(0,Inputs!$B$20-C78-'Scenario_Drivers'!D28)*Inputs!$B$29/4+MAX(0,Inputs!$B$21-C77-'Scenario_Drivers'!D25)*Inputs!$B$30/4) | E22: =-(((D76+MAX(0,D76-(MIN(0.107,D76))))/2)*(MAX('Scenario_Drivers'!E33,Inputs!$B$26)+Inputs!$B$23+'Scenario_Drivers'!E34)/4+((D77+D77+'Scenario_Drivers'!E25-(IF(D77>0,MIN(0.015,D77),0)))/2)*(MAX('Scenario_Drivers'!E33,Inputs!$B$26)+Inputs!$B$25+'Scenario_Drivers'!E34)/4+D78*(MAX('Scenario_Drivers'!E33,Inputs!$B$26)+Inputs!$B$24+'Scenario_Drivers'!E34)/4+MAX(0,Inputs!$B$20-D78-'Scenario_Drivers'!E28)*Inputs!$B$29/4+MAX(0,Inputs!$B$21-D77-'Scenario_Drivers'!E25)*Inputs!$B$30/4) | F22: =-(((E76+MAX(0,E76-(MIN(0.107,E76))))/2)*(MAX('Scenario_Drivers'!F33,Inputs!$B$26)+Inputs!$B$23+'Scenario_Drivers'!F34)/4+((E77+E77+'Scenario_Drivers'!F25-(IF(E77>0,MIN(0.015,E77),0)))/2)*(MAX('Scenario_Drivers'!F33,Inputs!$B$26)+Inputs!$B$25+'Scenario_Drivers'!F34)/4+E78*(MAX('Scenario_Drivers'!F33,Inputs!$B$26)+Inputs!$B$24+'Scenario_Drivers'!F34)/4+MAX(0,Inputs!$B$20-E78-'Scenario_Drivers'!F28)*Inputs!$B$29/4+MAX(0,Inputs!$B$21-E77-'Scenario_Drivers'!F25)*Inputs!$B$30/4) | G22: =-(((F76+MAX(0,F76-(MIN(0.107,F76))))/2)*(MAX('Scenario_Drivers'!G33,Inputs!$B$26)+Inputs!$B$23+'Scenario_Drivers'!G34)/4+((F77+F77+'Scenario_Drivers'!G25-(IF(F77>0,MIN(0.015,F77),0)))/2)*(MAX('Scenario_Drivers'!G33,Inputs!$B$26)+Inputs!$B$25+'Scenario_Drivers'!G34)/4+F78*(MAX('Scenario_Drivers'!G33,Inputs!$B$26)+Inputs!$B$24+'Scenario_Drivers'!G34)/4+MAX(0,Inputs!$B$20-F78-'Scenario_Drivers'!G28)*Inputs!$B$29/4+MAX(0,Inputs!$B$21-F77-'Scenario_Drivers'!G25)*Inputs!$B$30/4) | H22: =-(((G76+MAX(0,G76-(MIN(0.107,G76))))/2)*(MAX('Scenario_Drivers'!H33,Inputs!$B$26)+Inputs!$B$23+'Scenario_Drivers'!H34)/4+((G77+G77+'Scenario_Drivers'!H25-(IF(G77>0,MIN(0.015,G77),0)))/2)*(MAX('Scenario_Drivers'!H33,Inputs!$B$26)+Inputs!$B$25+'Scenario_Drivers'!H34)/4+G78*(MAX('Scenario_Drivers'!H33,Inputs!$B$26)+Inputs!$B$24+'Scenario_Drivers'!H34)/4+MAX(0,Inputs!$B$20-G78-'Scenario_Drivers'!H28)*Inputs!$B$29/4+MAX(0,Inputs!$B$21-G77-'Scenario_Drivers'!H25)*Inputs!$B$30/4) | I22: =-(((H76+MAX(0,H76-(MIN(0.107,H76))))/2)*(MAX('Scenario_Drivers'!I33,Inputs!$B$26)+Inputs!$B$23+'Scenario_Drivers'!I34)/4+((H77+H77+'Scenario_Drivers'!I25-(IF(H77>0,MIN(0.015,H77),0)))/2)*(MAX('Scenario_Drivers'!I33,Inputs!$B$26)+Inputs!$B$25+'Scenario_Drivers'!I34)/4+H78*(MAX('Scenario_Drivers'!I33,Inputs!$B$26)+Inputs!$B$24+'Scenario_Drivers'!I34)/4+MAX(0,Inputs!$B$20-H78-'Scenario_Drivers'!I28)*Inputs!$B$29/4+0) | J22: =-(((I76+MAX(0,I76-(MIN(0.107,I76))))/2)*(MAX('Scenario_Drivers'!J33,Inputs!$B$26)+Inputs!$B$23+'Scenario_Drivers'!J34)/4+((I77+I77+'Scenario_Drivers'!J25-(IF(I77>0,MIN(0.015,I77),0)))/2)*(MAX('Scenario_Drivers'!J33,Inputs!$B$26)+Inputs!$B$25+'Scenario_Drivers'!J34)/4+I78*(MAX('Scenario_Drivers'!J33,Inputs!$B$26)+Inputs!$B$24+'Scenario_Drivers'!J34)/4+MAX(0,Inputs!$B$20-I78-'Scenario_Drivers'!J28)*Inputs!$B$29/4+0) | K22: =-(((J76+MAX(0,J76-(MIN(0.107,J76))))/2)*(MAX('Scenario_Drivers'!K33,Inputs!$B$26)+Inputs!$B$23+'Scenario_Drivers'!K34)/4+((J77+J77+'Scenario_Drivers'!K25-(IF(J77>0,MIN(0.015,J77),0)))/2)*(MAX('Scenario_Drivers'!K33,Inputs!$B$26)+Inputs!$B$25+'Scenario_Drivers'!K34)/4+J78*(MAX('Scenario_Drivers'!K33,Inputs!$B$26)+Inputs!$B$24+'Scenario_Drivers'!K34)/4+MAX(0,Inputs!$B$20-J78-'Scenario_Drivers'!K28)*Inputs!$B$29/4+0) | L22: =-(((K76+MAX(0,K76-(MIN(0.107,K76))))/2)*(MAX('Scenario_Drivers'!L33,Inputs!$B$26)+Inputs!$B$23+'Scenario_Drivers'!L34)/4+((K77+K77+'Scenario_Drivers'!L25-(IF(K77>0,MIN(0.015,K77),0)))/2)*(MAX('Scenario_Drivers'!L33,Inputs!$B$26)+Inputs!$B$25+'Scenario_Drivers'!L34)/4+K78*(MAX('Scenario_Drivers'!L33,Inputs!$B$26)+Inputs!$B$24+'Scenario_Drivers'!L34)/4+MAX(0,Inputs!$B$20-K78-'Scenario_Drivers'!L28)*Inputs!$B$29/4+0) | M22: =-(((L76+MAX(0,L76-(MIN(0.107,L76))))/2)*(MAX('Scenario_Drivers'!M33,Inputs!$B$26)+Inputs!$B$23+'Scenario_Drivers'!M34)/4+((L77+L77+'Scenario_Drivers'!M25-(IF(L77>0,MIN(0.015,L77),0)))/2)*(MAX('Scenario_Drivers'!M33,Inputs!$B$26)+Inputs!$B$25+'Scenario_Drivers'!M34)/4+L78*(MAX('Scenario_Drivers'!M33,Inputs!$B$26)+Inputs!$B$24+'Scenario_Drivers'!M34)/4+MAX(0,Inputs!$B$20-L78-'Scenario_Drivers'!M28)*Inputs!$B$29/4+0) | N22: =-(((M76+MAX(0,M76-(MIN(0.107,M76))))/2)*(MAX('Scenario_Drivers'!N33,Inputs!$B$26)+Inputs!$B$23+'Scenario_Drivers'!N34)/4+((M77+M77+'Scenario_Drivers'!N25-(IF(M77>0,MIN(0.015,M77),0)))/2)*(MAX('Scenario_Drivers'!N33,Inputs!$B$26)+Inputs!$B$25+'Scenario_Drivers'!N34)/4+M78*(MAX('Scenario_Drivers'!N33,Inputs!$B$26)+Inputs!$B$24+'Scenario_Drivers'!N34)/4+MAX(0,Inputs!$B$20-M78-'Scenario_Drivers'!N28)*Inputs!$B$29/4+0) | O22: =-(((N76+MAX(0,N76-(MIN(0.107,N76))))/2)*(MAX('Scenario_Drivers'!O33,Inputs!$B$26)+Inputs!$B$23+'Scenario_Drivers'!O34)/4+((N77+N77+'Scenario_Drivers'!O25-(IF(N77>0,MIN(0.015,N77),0)))/2)*(MAX('Scenario_Drivers'!O33,Inputs!$B$26)+Inputs!$B$25+'Scenario_Drivers'!O34)/4+N78*(MAX('Scenario_Drivers'!O33,Inputs!$B$26)+Inputs!$B$24+'Scenario_Drivers'!O34)/4+MAX(0,Inputs!$B$20-N78-'Scenario_Drivers'!O28)*Inputs!$B$29/4+0) | P22: =-(((O76+MAX(0,O76-(MIN(0.107,O76))))/2)*(MAX('Scenario_Drivers'!P33,Inputs!$B$26)+Inputs!$B$23+'Scenario_Drivers'!P34)/4+((O77+O77+'Scenario_Drivers'!P25-(IF(O77>0,MIN(0.015,O77),0)))/2)*(MAX('Scenario_Drivers'!P33,Inputs!$B$26)+Inputs!$B$25+'Scenario_Drivers'!P34)/4+O78*(MAX('Scenario_Drivers'!P33,Inputs!$B$26)+Inputs!$B$24+'Scenario_Drivers'!P34)/4+MAX(0,Inputs!$B$20-O78-'Scenario_Drivers'!P28)*Inputs!$B$29/4+0) | ... V22: =-(((U76+MAX(0,U76-(MIN(0.107,U76))))/2)*(MAX('Scenario_Drivers'!V33,Inputs!$B$26)+Inputs!$B$23+'Scenario_Drivers'!V34)/4+((U77+U77+'Scenario_Drivers'!V25-(IF(U77>0,MIN(0.015,U77),0)))/2)*(MAX('Scenario_Drivers'!V33,Inputs!$B$26)+Inputs!$B$25+'Scenario_Drivers'!V34)/4+U78*(MAX('Scenario_Drivers'!V33,Inputs!$B$26)+Inputs!$B$24+'Scenario_Drivers'!V34)/4+MAX(0,Inputs!$B$20-U78-'Scenario_Drivers'!V28)*Inputs!$B$29/4+0)
A23: Financing fee amortization | B23: $mm | C23: =MIN('S&U_Opening'!$B$24,1.4/24) | D23: =MIN(C73,1.4/24) | E23: =MIN(D73,1.4/24) | F23: =MIN(E73,1.4/24) | G23: =MIN(F73,1.4/24) | H23: =MIN(G73,1.4/24) | I23: =MIN(H73,1.4/24) | J23: =MIN(I73,1.4/24) | K23: =MIN(J73,1.4/24) | ... V23: =MIN(U73,1.4/24)
A24: Interest income | B24: $mm | C24: ='S&U_Opening'!$B$15*1.0%/4 | D24: =C67*1.0%/4 | E24: =D67*1.0%/4 | F24: =E67*1.0%/4 | G24: =F67*1.0%/4 | H24: =G67*1.0%/4 | I24: =H67*1.0%/4 | J24: =I67*1.0%/4 | K24: =J67*1.0%/4 | ... V24: =U67*1.0%/4
A25: Pre-tax income | B25: $mm | C25: =C21+C22-C23+C24 | D25: =D21+D22-D23+D24 | E25: =E21+E22-E23+E24 | F25: =F21+F22-F23+F24 | G25: =G21+G22-G23+G24 | H25: =H21+H22-H23+H24 | I25: =I21+I22-I23+I24 | J25: =J21+J22-J23+J24 | ... V25: =V21+V22-V23+V24
A26: Book tax expense | B26: $mm | C26: =-MAX(0,C25*Inputs!$B$15) | D26: =-MAX(0,D25*Inputs!$B$15) | E26: =-MAX(0,E25*Inputs!$B$15) | F26: =-MAX(0,F25*Inputs!$B$15) | G26: =-MAX(0,G25*Inputs!$B$15) | H26: =-MAX(0,H25*Inputs!$B$15) | I26: =-MAX(0,I25*Inputs!$B$15) | J26: =-MAX(0,J25*Inputs!$B$15) | ... V26: =-MAX(0,V25*Inputs!$B$15)
A27: Cash taxes | B27: $mm | C27: =-MAX(0,(C116-0)*Inputs!$B$15) | D27: =-MAX(0,(D116-C115)*Inputs!$B$15) | E27: =-MAX(0,(E116-D115)*Inputs!$B$15) | F27: =-MAX(0,(F116-E115)*Inputs!$B$15) | G27: =-MAX(0,(G116-F115)*Inputs!$B$15) | H27: =-MAX(0,(H116-G115)*Inputs!$B$15) | I27: =-MAX(0,(I116-H115)*Inputs!$B$15) | J27: =-MAX(0,(J116-I115)*Inputs!$B$15) | K27: =-MAX(0,(K116-J115)*Inputs!$B$15) | ... V27: =-MAX(0,(V116-U115)*Inputs!$B$15)
A28: Net income | B28: $mm | C28: =C25+C26 | D28: =D25+D26 | E28: =E25+E26 | F28: =F25+F26 | G28: =G25+G26 | H28: =H25+H26 | I28: =I25+I26 | J28: =J25+J26 | ... V28: =V25+V26
A29: Working Capital and Capital Expenditure
A30: Accounts receivable | B30: $mm | C30: =(C5/'Scenario_Drivers'!C36)*'Scenario_Drivers'!C10/365 | D30: =(D5/'Scenario_Drivers'!D36)*'Scenario_Drivers'!D10/365 | E30: =(E5/'Scenario_Drivers'!E36)*'Scenario_Drivers'!E10/365 | F30: =(F5/'Scenario_Drivers'!F36)*'Scenario_Drivers'!F10/365 | G30: =(G5/'Scenario_Drivers'!G36)*'Scenario_Drivers'!G10/365 | H30: =(H5/'Scenario_Drivers'!H36)*'Scenario_Drivers'!H10/365 | I30: =(I5/'Scenario_Drivers'!I36)*'Scenario_Drivers'!I10/365 | J30: =(J5/'Scenario_Drivers'!J36)*'Scenario_Drivers'!J10/365 | ... V30: =(V5/'Scenario_Drivers'!V36)*'Scenario_Drivers'!V10/365
A31: Unbilled WIP | B31: $mm | C31: =(C5/'Scenario_Drivers'!C36)*'Scenario_Drivers'!C11 | D31: =(D5/'Scenario_Drivers'!D36)*'Scenario_Drivers'!D11 | E31: =(E5/'Scenario_Drivers'!E36)*'Scenario_Drivers'!E11 | F31: =(F5/'Scenario_Drivers'!F36)*'Scenario_Drivers'!F11 | G31: =(G5/'Scenario_Drivers'!G36)*'Scenario_Drivers'!G11 | H31: =(H5/'Scenario_Drivers'!H36)*'Scenario_Drivers'!H11 | I31: =(I5/'Scenario_Drivers'!I36)*'Scenario_Drivers'!I11 | J31: =(J5/'Scenario_Drivers'!J36)*'Scenario_Drivers'!J11 | ... V31: =(V5/'Scenario_Drivers'!V36)*'Scenario_Drivers'!V11
A32: Prepaids | B32: $mm | C32: =(C5/'Scenario_Drivers'!C36)*'Scenario_Drivers'!C12 | D32: =(D5/'Scenario_Drivers'!D36)*'Scenario_Drivers'!D12 | E32: =(E5/'Scenario_Drivers'!E36)*'Scenario_Drivers'!E12 | F32: =(F5/'Scenario_Drivers'!F36)*'Scenario_Drivers'!F12 | G32: =(G5/'Scenario_Drivers'!G36)*'Scenario_Drivers'!G12 | H32: =(H5/'Scenario_Drivers'!H36)*'Scenario_Drivers'!H12 | I32: =(I5/'Scenario_Drivers'!I36)*'Scenario_Drivers'!I12 | J32: =(J5/'Scenario_Drivers'!J36)*'Scenario_Drivers'!J12 | ... V32: =(V5/'Scenario_Drivers'!V36)*'Scenario_Drivers'!V12
A33: Accounts payable | B33: $mm | C33: =(C5/'Scenario_Drivers'!C36)*'Scenario_Drivers'!C13 | D33: =(D5/'Scenario_Drivers'!D36)*'Scenario_Drivers'!D13 | E33: =(E5/'Scenario_Drivers'!E36)*'Scenario_Drivers'!E13 | F33: =(F5/'Scenario_Drivers'!F36)*'Scenario_Drivers'!F13 | G33: =(G5/'Scenario_Drivers'!G36)*'Scenario_Drivers'!G13 | H33: =(H5/'Scenario_Drivers'!H36)*'Scenario_Drivers'!H13 | I33: =(I5/'Scenario_Drivers'!I36)*'Scenario_Drivers'!I13 | J33: =(J5/'Scenario_Drivers'!J36)*'Scenario_Drivers'!J13 | ... V33: =(V5/'Scenario_Drivers'!V36)*'Scenario_Drivers'!V13
A34: Accrued liabilities | B34: $mm | C34: =(C5/'Scenario_Drivers'!C36)*'Scenario_Drivers'!C14 | D34: =(D5/'Scenario_Drivers'!D36)*'Scenario_Drivers'!D14 | E34: =(E5/'Scenario_Drivers'!E36)*'Scenario_Drivers'!E14 | F34: =(F5/'Scenario_Drivers'!F36)*'Scenario_Drivers'!F14 | G34: =(G5/'Scenario_Drivers'!G36)*'Scenario_Drivers'!G14 | H34: =(H5/'Scenario_Drivers'!H36)*'Scenario_Drivers'!H14 | I34: =(I5/'Scenario_Drivers'!I36)*'Scenario_Drivers'!I14 | J34: =(J5/'Scenario_Drivers'!J36)*'Scenario_Drivers'!J14 | ... V34: =(V5/'Scenario_Drivers'!V36)*'Scenario_Drivers'!V14
A35: Deferred revenue | B35: $mm | C35: =(C5/'Scenario_Drivers'!C36)*'Scenario_Drivers'!C15 | D35: =(D5/'Scenario_Drivers'!D36)*'Scenario_Drivers'!D15 | E35: =(E5/'Scenario_Drivers'!E36)*'Scenario_Drivers'!E15 | F35: =(F5/'Scenario_Drivers'!F36)*'Scenario_Drivers'!F15 | G35: =(G5/'Scenario_Drivers'!G36)*'Scenario_Drivers'!G15 | H35: =(H5/'Scenario_Drivers'!H36)*'Scenario_Drivers'!H15 | I35: =(I5/'Scenario_Drivers'!I36)*'Scenario_Drivers'!I15 | J35: =(J5/'Scenario_Drivers'!J36)*'Scenario_Drivers'!J15 | ... V35: =(V5/'Scenario_Drivers'!V36)*'Scenario_Drivers'!V15
A36: Operating NWC | B36: $mm | C36: =C30+C31+C32-C33-C34-C35 | D36: =D30+D31+D32-D33-D34-D35 | E36: =E30+E31+E32-E33-E34-E35 | F36: =F30+F31+F32-F33-F34-F35 | G36: =G30+G31+G32-G33-G34-G35 | H36: =H30+H31+H32-H33-H34-H35 | I36: =I30+I31+I32-I33-I34-I35 | J36: =J30+J31+J32-J33-J34-J35 | ... V36: =V30+V31+V32-V33-V34-V35
A37: Acquired NWC | B37: $mm | C37: ='Scenario_Drivers'!C17 | D37: ='Scenario_Drivers'!D17 | E37: ='Scenario_Drivers'!E17 | F37: ='Scenario_Drivers'!F17 | G37: ='Scenario_Drivers'!G17 | H37: ='Scenario_Drivers'!H17 | I37: ='Scenario_Drivers'!I17 | J37: ='Scenario_Drivers'!J17 | ... V37: ='Scenario_Drivers'!V17
A38: Organic change in NWC | B38: $mm | C38: =C36-('S&U_Opening'!$B$16+'S&U_Opening'!$B$17+'S&U_Opening'!$B$18-'S&U_Opening'!$E$15-'S&U_Opening'!$E$16-'S&U_Opening'!$E$17)-C37 | D38: =D36-(C36)-D37 | E38: =E36-(D36)-E37 | F38: =F36-(E36)-F37 | G38: =G36-(F36)-G37 | H38: =H36-(G36)-H37 | I38: =I36-(H36)-I37 | J38: =J36-(I36)-J37 | K38: =K36-(J36)-K37 | ... V38: =V36-(U36)-V37
A39: Maintenance capex | B39: $mm | C39: =C5*'Scenario_Drivers'!C16*Inputs!$B$18 | D39: =D5*'Scenario_Drivers'!D16*Inputs!$B$18 | E39: =E5*'Scenario_Drivers'!E16*Inputs!$B$18 | F39: =F5*'Scenario_Drivers'!F16*Inputs!$B$18 | G39: =G5*'Scenario_Drivers'!G16*Inputs!$B$18 | H39: =H5*'Scenario_Drivers'!H16*Inputs!$B$18 | I39: =I5*'Scenario_Drivers'!I16*Inputs!$B$18 | J39: =J5*'Scenario_Drivers'!J16*Inputs!$B$18 | ... V39: =V5*'Scenario_Drivers'!V16*Inputs!$B$18
A40: Growth capex | B40: $mm | C40: =C5*'Scenario_Drivers'!C16*(1-Inputs!$B$18) | D40: =D5*'Scenario_Drivers'!D16*(1-Inputs!$B$18) | E40: =E5*'Scenario_Drivers'!E16*(1-Inputs!$B$18) | F40: =F5*'Scenario_Drivers'!F16*(1-Inputs!$B$18) | G40: =G5*'Scenario_Drivers'!G16*(1-Inputs!$B$18) | H40: =H5*'Scenario_Drivers'!H16*(1-Inputs!$B$18) | I40: =I5*'Scenario_Drivers'!I16*(1-Inputs!$B$18) | J40: =J5*'Scenario_Drivers'!J16*(1-Inputs!$B$18) | ... V40: =V5*'Scenario_Drivers'!V16*(1-Inputs!$B$18)
A41: Total capex | B41: $mm | C41: =SUM(C39:C40) | D41: =SUM(D39:D40) | E41: =SUM(E39:E40) | F41: =SUM(F39:F40) | G41: =SUM(G39:G40) | H41: =SUM(H39:H40) | I41: =SUM(I39:I40) | J41: =SUM(J39:J40) | ... V41: =SUM(V39:V40)
A42: Acquired PP&E | B42: $mm | C42: ='Scenario_Drivers'!C18 | D42: ='Scenario_Drivers'!D18 | E42: ='Scenario_Drivers'!E18 | F42: ='Scenario_Drivers'!F18 | G42: ='Scenario_Drivers'!G18 | H42: ='Scenario_Drivers'!H18 | I42: ='Scenario_Drivers'!I18 | J42: ='Scenario_Drivers'!J18 | ... V42: ='Scenario_Drivers'!V18
A43: Acquisition EV | B43: $mm | C43: ='Scenario_Drivers'!C19 | D43: ='Scenario_Drivers'!D19 | E43: ='Scenario_Drivers'!E19 | F43: ='Scenario_Drivers'!F19 | G43: ='Scenario_Drivers'!G19 | H43: ='Scenario_Drivers'!H19 | I43: ='Scenario_Drivers'!I19 | J43: ='Scenario_Drivers'!J19 | ... V43: ='Scenario_Drivers'!V19
A44: Acquisition fees | B44: $mm | C44: ='Scenario_Drivers'!C20 | D44: ='Scenario_Drivers'!D20 | E44: ='Scenario_Drivers'!E20 | F44: ='Scenario_Drivers'!F20 | G44: ='Scenario_Drivers'!G20 | H44: ='Scenario_Drivers'!H20 | I44: ='Scenario_Drivers'!I20 | J44: ='Scenario_Drivers'!J20 | ... V44: ='Scenario_Drivers'!V20
A45: Capitalized integration spend | B45: $mm | C45: ='Scenario_Drivers'!C27 | D45: ='Scenario_Drivers'!D27 | E45: ='Scenario_Drivers'!E27 | F45: ='Scenario_Drivers'!F27 | G45: ='Scenario_Drivers'!G27 | H45: ='Scenario_Drivers'!H27 | I45: ='Scenario_Drivers'!I27 | J45: ='Scenario_Drivers'!J27 | ... V45: ='Scenario_Drivers'!V27
A46: Cash Flow Statement
A47: Net income - CF | B47: $mm | C47: =C28 | D47: =D28 | E47: =E28 | F47: =F28 | G47: =G28 | H47: =H28 | I47: =I28 | J47: =J28 | ... V47: =V28
A48: Total D&A - CF | B48: $mm | C48: =C20 | D48: =D20 | E48: =E20 | F48: =F20 | G48: =G20 | H48: =H20 | I48: =I20 | J48: =J20 | ... V48: =V20
A49: Financing fee amortization - CF | B49: $mm | C49: =C23 | D49: =D23 | E49: =E23 | F49: =F23 | G49: =G23 | H49: =H23 | I49: =I23 | J49: =J23 | ... V49: =V23
A50: Deferred tax / non-cash tax | B50: $mm | C50: =-C26+C27 | D50: =-D26+D27 | E50: =-E26+E27 | F50: =-F26+F27 | G50: =-G26+G27 | H50: =-H26+H27 | I50: =-I26+I27 | J50: =-J26+J27 | ... V50: =-V26+V27
A51: Change in NWC - CF | B51: $mm | C51: =-C38 | D51: =-D38 | E51: =-E38 | F51: =-F38 | G51: =-G38 | H51: =-H38 | I51: =-I38 | J51: =-J38 | ... V51: =-V38
A52: Cash from operations | B52: $mm | C52: =SUM(C47:C51) | D52: =SUM(D47:D51) | E52: =SUM(E47:E51) | F52: =SUM(F47:F51) | G52: =SUM(G47:G51) | H52: =SUM(H47:H51) | I52: =SUM(I47:I51) | J52: =SUM(J47:J51) | ... V52: =SUM(V47:V51)
A53: Capital expenditure - CF | B53: $mm | C53: =-C41 | D53: =-D41 | E53: =-E41 | F53: =-F41 | G53: =-G41 | H53: =-H41 | I53: =-I41 | J53: =-J41 | ... V53: =-V41
A54: Acquisition EV - CF | B54: $mm | C54: =-C43 | D54: =-D43 | E54: =-E43 | F54: =-F43 | G54: =-G43 | H54: =-H43 | I54: =-I43 | J54: =-J43 | ... V54: =-V43
A55: Capitalized integration spend - CF | B55: $mm | C55: =-C45 | D55: =-D45 | E55: =-E45 | F55: =-F45 | G55: =-G45 | H55: =-H45 | I55: =-I45 | J55: =-J45 | ... V55: =-V45
A56: Cash from investing | B56: $mm | C56: =SUM(C53:C55) | D56: =SUM(D53:D55) | E56: =SUM(E53:E55) | F56: =SUM(F53:F55) | G56: =SUM(G53:G55) | H56: =SUM(H53:H55) | I56: =SUM(I53:I55) | J56: =SUM(J53:J55) | ... V56: =SUM(V53:V55)
A57: Sponsor equity contribution | B57: $mm | C57: ='Scenario_Drivers'!C26 | D57: ='Scenario_Drivers'!D26 | E57: ='Scenario_Drivers'!E26 | F57: ='Scenario_Drivers'!F26 | G57: ='Scenario_Drivers'!G26 | H57: ='Scenario_Drivers'!H26 | I57: ='Scenario_Drivers'!I26 | J57: ='Scenario_Drivers'!J26 | ... V57: ='Scenario_Drivers'!V26
A58: DDTL draw | B58: $mm | C58: ='Scenario_Drivers'!C25 | D58: ='Scenario_Drivers'!D25 | E58: ='Scenario_Drivers'!E25 | F58: ='Scenario_Drivers'!F25 | G58: ='Scenario_Drivers'!G25 | H58: ='Scenario_Drivers'!H25 | I58: ='Scenario_Drivers'!I25 | J58: ='Scenario_Drivers'!J25 | ... V58: ='Scenario_Drivers'!V25
A59: Revolver draw | B59: $mm | C59: =IF('Scenario_Drivers'!C30>=0,MAX(0,'Scenario_Drivers'!C30-0),IF('S&U_Opening'!$B$15+C52+C56+C57+C58+C61+C62<'Scenario_Drivers'!C29,MIN((MAX(0,Inputs!$B$20-'Scenario_Drivers'!C28))-0,'Scenario_Drivers'!C29-('S&U_Opening'!$B$15+C52+C56+C57+C58+C61+C62)),0)) | D59: =IF('Scenario_Drivers'!D30>=0,MAX(0,'Scenario_Drivers'!D30-C78),IF(C67+D52+D56+D57+D58+D61+D62<'Scenario_Drivers'!D29,MIN((MAX(0,Inputs!$B$20-'Scenario_Drivers'!D28))-C78,'Scenario_Drivers'!D29-(C67+D52+D56+D57+D58+D61+D62)),0)) | E59: =IF('Scenario_Drivers'!E30>=0,MAX(0,'Scenario_Drivers'!E30-D78),IF(D67+E52+E56+E57+E58+E61+E62<'Scenario_Drivers'!E29,MIN((MAX(0,Inputs!$B$20-'Scenario_Drivers'!E28))-D78,'Scenario_Drivers'!E29-(D67+E52+E56+E57+E58+E61+E62)),0)) | F59: =IF('Scenario_Drivers'!F30>=0,MAX(0,'Scenario_Drivers'!F30-E78),IF(E67+F52+F56+F57+F58+F61+F62<'Scenario_Drivers'!F29,MIN((MAX(0,Inputs!$B$20-'Scenario_Drivers'!F28))-E78,'Scenario_Drivers'!F29-(E67+F52+F56+F57+F58+F61+F62)),0)) | G59: =IF('Scenario_Drivers'!G30>=0,MAX(0,'Scenario_Drivers'!G30-F78),IF(F67+G52+G56+G57+G58+G61+G62<'Scenario_Drivers'!G29,MIN((MAX(0,Inputs!$B$20-'Scenario_Drivers'!G28))-F78,'Scenario_Drivers'!G29-(F67+G52+G56+G57+G58+G61+G62)),0)) | H59: =IF('Scenario_Drivers'!H30>=0,MAX(0,'Scenario_Drivers'!H30-G78),IF(G67+H52+H56+H57+H58+H61+H62<'Scenario_Drivers'!H29,MIN((MAX(0,Inputs!$B$20-'Scenario_Drivers'!H28))-G78,'Scenario_Drivers'!H29-(G67+H52+H56+H57+H58+H61+H62)),0)) | I59: =IF('Scenario_Drivers'!I30>=0,MAX(0,'Scenario_Drivers'!I30-H78),IF(H67+I52+I56+I57+I58+I61+I62<'Scenario_Drivers'!I29,MIN((MAX(0,Inputs!$B$20-'Scenario_Drivers'!I28))-H78,'Scenario_Drivers'!I29-(H67+I52+I56+I57+I58+I61+I62)),0)) | J59: =IF('Scenario_Drivers'!J30>=0,MAX(0,'Scenario_Drivers'!J30-I78),IF(I67+J52+J56+J57+J58+J61+J62<'Scenario_Drivers'!J29,MIN((MAX(0,Inputs!$B$20-'Scenario_Drivers'!J28))-I78,'Scenario_Drivers'!J29-(I67+J52+J56+J57+J58+J61+J62)),0)) | K59: =IF('Scenario_Drivers'!K30>=0,MAX(0,'Scenario_Drivers'!K30-J78),IF(J67+K52+K56+K57+K58+K61+K62<'Scenario_Drivers'!K29,MIN((MAX(0,Inputs!$B$20-'Scenario_Drivers'!K28))-J78,'Scenario_Drivers'!K29-(J67+K52+K56+K57+K58+K61+K62)),0)) | ... V59: =IF('Scenario_Drivers'!V30>=0,MAX(0,'Scenario_Drivers'!V30-U78),IF(U67+V52+V56+V57+V58+V61+V62<'Scenario_Drivers'!V29,MIN((MAX(0,Inputs!$B$20-'Scenario_Drivers'!V28))-U78,'Scenario_Drivers'!V29-(U67+V52+V56+V57+V58+V61+V62)),0))
A60: Revolver repayment | B60: $mm | C60: =-(IF('Scenario_Drivers'!C31=1,0,IF('Scenario_Drivers'!C30>=0,MAX(0,0-'Scenario_Drivers'!C30),IF('S&U_Opening'!$B$15+C52+C56+C57+C58+C61+C62>'Scenario_Drivers'!C29,MIN(0,('S&U_Opening'!$B$15+C52+C56+C57+C58+C61+C62)-'Scenario_Drivers'!C29),0)))) | D60: =-(IF('Scenario_Drivers'!D31=1,C78,IF('Scenario_Drivers'!D30>=0,MAX(0,C78-'Scenario_Drivers'!D30),IF(C67+D52+D56+D57+D58+D61+D62>'Scenario_Drivers'!D29,MIN(C78,(C67+D52+D56+D57+D58+D61+D62)-'Scenario_Drivers'!D29),0)))) | E60: =-(IF('Scenario_Drivers'!E31=1,D78,IF('Scenario_Drivers'!E30>=0,MAX(0,D78-'Scenario_Drivers'!E30),IF(D67+E52+E56+E57+E58+E61+E62>'Scenario_Drivers'!E29,MIN(D78,(D67+E52+E56+E57+E58+E61+E62)-'Scenario_Drivers'!E29),0)))) | F60: =-(IF('Scenario_Drivers'!F31=1,E78,IF('Scenario_Drivers'!F30>=0,MAX(0,E78-'Scenario_Drivers'!F30),IF(E67+F52+F56+F57+F58+F61+F62>'Scenario_Drivers'!F29,MIN(E78,(E67+F52+F56+F57+F58+F61+F62)-'Scenario_Drivers'!F29),0)))) | G60: =-(IF('Scenario_Drivers'!G31=1,F78,IF('Scenario_Drivers'!G30>=0,MAX(0,F78-'Scenario_Drivers'!G30),IF(F67+G52+G56+G57+G58+G61+G62>'Scenario_Drivers'!G29,MIN(F78,(F67+G52+G56+G57+G58+G61+G62)-'Scenario_Drivers'!G29),0)))) | H60: =-(IF('Scenario_Drivers'!H31=1,G78,IF('Scenario_Drivers'!H30>=0,MAX(0,G78-'Scenario_Drivers'!H30),IF(G67+H52+H56+H57+H58+H61+H62>'Scenario_Drivers'!H29,MIN(G78,(G67+H52+H56+H57+H58+H61+H62)-'Scenario_Drivers'!H29),0)))) | I60: =-(IF('Scenario_Drivers'!I31=1,H78,IF('Scenario_Drivers'!I30>=0,MAX(0,H78-'Scenario_Drivers'!I30),IF(H67+I52+I56+I57+I58+I61+I62>'Scenario_Drivers'!I29,MIN(H78,(H67+I52+I56+I57+I58+I61+I62)-'Scenario_Drivers'!I29),0)))) | J60: =-(IF('Scenario_Drivers'!J31=1,I78,IF('Scenario_Drivers'!J30>=0,MAX(0,I78-'Scenario_Drivers'!J30),IF(I67+J52+J56+J57+J58+J61+J62>'Scenario_Drivers'!J29,MIN(I78,(I67+J52+J56+J57+J58+J61+J62)-'Scenario_Drivers'!J29),0)))) | K60: =-(IF('Scenario_Drivers'!K31=1,J78,IF('Scenario_Drivers'!K30>=0,MAX(0,J78-'Scenario_Drivers'!K30),IF(J67+K52+K56+K57+K58+K61+K62>'Scenario_Drivers'!K29,MIN(J78,(J67+K52+K56+K57+K58+K61+K62)-'Scenario_Drivers'!K29),0)))) | ... V60: =-(IF('Scenario_Drivers'!V31=1,U78,IF('Scenario_Drivers'!V30>=0,MAX(0,U78-'Scenario_Drivers'!V30),IF(U67+V52+V56+V57+V58+V61+V62>'Scenario_Drivers'!V29,MIN(U78,(U67+V52+V56+V57+V58+V61+V62)-'Scenario_Drivers'!V29),0))))
A61: Scheduled term amortization | B61: $mm | C61: =-(MIN(0.107,'S&U_Opening'!$E$18)) | D61: =-(MIN(0.107,C76)) | E61: =-(MIN(0.107,D76)) | F61: =-(MIN(0.107,E76)) | G61: =-(MIN(0.107,F76)) | H61: =-(MIN(0.107,G76)) | I61: =-(MIN(0.107,H76)) | J61: =-(MIN(0.107,I76)) | K61: =-(MIN(0.107,J76)) | ... V61: =-(MIN(0.107,U76))
A62: Scheduled DDTL amortization | B62: $mm | C62: =-(IF(0>0,MIN(0.015,0),0)) | D62: =-(IF(C77>0,MIN(0.015,C77),0)) | E62: =-(IF(D77>0,MIN(0.015,D77),0)) | F62: =-(IF(E77>0,MIN(0.015,E77),0)) | G62: =-(IF(F77>0,MIN(0.015,F77),0)) | H62: =-(IF(G77>0,MIN(0.015,G77),0)) | I62: =-(IF(H77>0,MIN(0.015,H77),0)) | J62: =-(IF(I77>0,MIN(0.015,I77),0)) | K62: =-(IF(J77>0,MIN(0.015,J77),0)) | ... V62: =-(IF(U77>0,MIN(0.015,U77),0))
A63: ECF sweep | B63: $mm | C63: =-(0) | D63: =-(0) | E63: =-(MIN((MAX(0,D76+E61)),MAX(0,((D67+E52+E56+E57+E58+E61+E62)+E59+E60)-'Scenario_Drivers'!E29))*(IF((((MAX(0,D76+E61))+(MAX(0,D77+E58+E62))+(D78+E59+E60)-MIN(((D67+E52+E56+E57+E58+E61+E62)+E59+E60),Inputs!$B$19))/MAX(0.001,(SUM(C14:E14))))>3.0,50%,IF((((MAX(0,D76+E61))+(MAX(0,D77+E58+E62))+(D78+E59+E60)-MIN(((D67+E52+E56+E57+E58+E61+E62)+E59+E60),Inputs!$B$19))/MAX(0.001,(SUM(C14:E14))))>2.5,25%,0%)))) | F63: =-(0) | G63: =-(0) | H63: =-(0) | I63: =-(MIN((MAX(0,H76+I61)),MAX(0,((H67+I52+I56+I57+I58+I61+I62)+I59+I60)-'Scenario_Drivers'!I29))*(IF((((MAX(0,H76+I61))+(MAX(0,H77+I58+I62))+(H78+I59+I60)-MIN(((H67+I52+I56+I57+I58+I61+I62)+I59+I60),Inputs!$B$19))/MAX(0.001,(SUM(F14:I14))))>3.0,50%,IF((((MAX(0,H76+I61))+(MAX(0,H77+I58+I62))+(H78+I59+I60)-MIN(((H67+I52+I56+I57+I58+I61+I62)+I59+I60),Inputs!$B$19))/MAX(0.001,(SUM(F14:I14))))>2.5,25%,0%)))) | J63: =-(0) | K63: =-(0) | L63: =-(0) | M63: =-(MIN((MAX(0,L76+M61)),MAX(0,((L67+M52+M56+M57+M58+M61+M62)+M59+M60)-'Scenario_Drivers'!M29))*(IF((((MAX(0,L76+M61))+(MAX(0,L77+M58+M62))+(L78+M59+M60)-MIN(((L67+M52+M56+M57+M58+M61+M62)+M59+M60),Inputs!$B$19))/MAX(0.001,(SUM(J14:M14))))>3.0,50%,IF((((MAX(0,L76+M61))+(MAX(0,L77+M58+M62))+(L78+M59+M60)-MIN(((L67+M52+M56+M57+M58+M61+M62)+M59+M60),Inputs!$B$19))/MAX(0.001,(SUM(J14:M14))))>2.5,25%,0%)))) | N63: =-(0) | O63: =-(0) | P63: =-(0) | Q63: =-(MIN((MAX(0,P76+Q61)),MAX(0,((P67+Q52+Q56+Q57+Q58+Q61+Q62)+Q59+Q60)-'Scenario_Drivers'!Q29))*(IF((((MAX(0,P76+Q61))+(MAX(0,P77+Q58+Q62))+(P78+Q59+Q60)-MIN(((P67+Q52+Q56+Q57+Q58+Q61+Q62)+Q59+Q60),Inputs!$B$19))/MAX(0.001,(SUM(N14:Q14))))>3.0,50%,IF((((MAX(0,P76+Q61))+(MAX(0,P77+Q58+Q62))+(P78+Q59+Q60)-MIN(((P67+Q52+Q56+Q57+Q58+Q61+Q62)+Q59+Q60),Inputs!$B$19))/MAX(0.001,(SUM(N14:Q14))))>2.5,25%,0%)))) | R63: =-(0) | S63: =-(0) | T63: =-(0) | U63: =-(MIN((MAX(0,T76+U61)),MAX(0,((T67+U52+U56+U57+U58+U61+U62)+U59+U60)-'Scenario_Drivers'!U29))*(IF((((MAX(0,T76+U61))+(MAX(0,T77+U58+U62))+(T78+U59+U60)-MIN(((T67+U52+U56+U57+U58+U61+U62)+U59+U60),Inputs!$B$19))/MAX(0.001,(SUM(R14:U14))))>3.0,50%,IF((((MAX(0,T76+U61))+(MAX(0,T77+U58+U62))+(T78+U59+U60)-MIN(((T67+U52+U56+U57+U58+U61+U62)+U59+U60),Inputs!$B$19))/MAX(0.001,(SUM(R14:U14))))>2.5,25%,0%)))) | V63: =-(0)
A64: Cash from financing | B64: $mm | C64: =SUM(C57:C63) | D64: =SUM(D57:D63) | E64: =SUM(E57:E63) | F64: =SUM(F57:F63) | G64: =SUM(G57:G63) | H64: =SUM(H57:H63) | I64: =SUM(I57:I63) | J64: =SUM(J57:J63) | ... V64: =SUM(V57:V63)
A65: Net change in cash | B65: $mm | C65: =C52+C56+C64 | D65: =D52+D56+D64 | E65: =E52+E56+E64 | F65: =F52+F56+F64 | G65: =G52+G56+G64 | H65: =H52+H56+H64 | I65: =I52+I56+I64 | J65: =J52+J56+J64 | ... V65: =V52+V56+V64
A66: Beginning cash | B66: $mm | C66: ='S&U_Opening'!$B$15 | D66: =C67 | E66: =D67 | F66: =E67 | G66: =F67 | H66: =G67 | I66: =H67 | J66: =I67 | K66: =J67 | ... V66: =U67
A67: Ending cash | B67: $mm | C67: =C66+C65 | D67: =D66+D65 | E67: =E66+E65 | F67: =F66+F65 | G67: =G66+G65 | H67: =H66+H65 | I67: =I66+I65 | J67: =J66+J65 | ... V67: =V66+V65
A68: Balance Sheet
A69: PP&E, net | B69: $mm | C69: ='S&U_Opening'!$B$19+C41+C42-C17 | D69: =C69+D41+D42-D17 | E69: =D69+E41+E42-E17 | F69: =E69+F41+F42-F17 | G69: =F69+G41+G42-G17 | H69: =G69+H41+H42-H17 | I69: =H69+I41+I42-I17 | J69: =I69+J41+J42-J17 | K69: =J69+K41+K42-K17 | ... V69: =U69+V41+V42-V17
A70: Goodwill | B70: $mm | C70: ='S&U_Opening'!$B$20+'Scenario_Drivers'!C22 | D70: =C70+'Scenario_Drivers'!D22 | E70: =D70+'Scenario_Drivers'!E22 | F70: =E70+'Scenario_Drivers'!F22 | G70: =F70+'Scenario_Drivers'!G22 | H70: =G70+'Scenario_Drivers'!H22 | I70: =H70+'Scenario_Drivers'!I22 | J70: =I70+'Scenario_Drivers'!J22 | K70: =J70+'Scenario_Drivers'!K22 | ... V70: =U70+'Scenario_Drivers'!V22
A71: Intangibles, net | B71: $mm | C71: =MAX(0,SUM('S&U_Opening'!$B$21:$B$23)+'Scenario_Drivers'!C21-C18) | D71: =MAX(0,C71+'Scenario_Drivers'!D21-D18) | E71: =MAX(0,D71+'Scenario_Drivers'!E21-E18) | F71: =MAX(0,E71+'Scenario_Drivers'!F21-F18) | G71: =MAX(0,F71+'Scenario_Drivers'!G21-G18) | H71: =MAX(0,G71+'Scenario_Drivers'!H21-H18) | I71: =MAX(0,H71+'Scenario_Drivers'!I21-I18) | J71: =MAX(0,I71+'Scenario_Drivers'!J21-J18) | K71: =MAX(0,J71+'Scenario_Drivers'!K21-K18) | ... V71: =MAX(0,U71+'Scenario_Drivers'!V21-V18)
A72: Integration asset | B72: $mm | C72: =MAX(0,0+C45-C19) | D72: =MAX(0,C72+D45-D19) | E72: =MAX(0,D72+E45-E19) | F72: =MAX(0,E72+F45-F19) | G72: =MAX(0,F72+G45-G19) | H72: =MAX(0,G72+H45-H19) | I72: =MAX(0,H72+I45-I19) | J72: =MAX(0,I72+J45-J19) | K72: =MAX(0,J72+K45-K19) | ... V72: =MAX(0,U72+V45-V19)
A73: Deferred financing fees | B73: $mm | C73: =MAX(0,'S&U_Opening'!$B$24-C23) | D73: =MAX(0,C73-D23) | E73: =MAX(0,D73-E23) | F73: =MAX(0,E73-F23) | G73: =MAX(0,F73-G23) | H73: =MAX(0,G73-H23) | I73: =MAX(0,H73-I23) | J73: =MAX(0,I73-J23) | K73: =MAX(0,J73-K23) | ... V73: =MAX(0,U73-V23)
A74: Other assets | B74: $mm | C74: =1.3 | D74: =1.3 | E74: =1.3 | F74: =1.3 | G74: =1.3 | H74: =1.3 | I74: =1.3 | J74: =1.3 | ... V74: =1.3
A75: Total assets | B75: $mm | C75: =SUM(C67,C30,C31,C32,C69,C70,C71,C72,C73,C74) | D75: =SUM(D67,D30,D31,D32,D69,D70,D71,D72,D73,D74) | E75: =SUM(E67,E30,E31,E32,E69,E70,E71,E72,E73,E74) | F75: =SUM(F67,F30,F31,F32,F69,F70,F71,F72,F73,F74) | G75: =SUM(G67,G30,G31,G32,G69,G70,G71,G72,G73,G74) | H75: =SUM(H67,H30,H31,H32,H69,H70,H71,H72,H73,H74) | I75: =SUM(I67,I30,I31,I32,I69,I70,I71,I72,I73,I74) | J75: =SUM(J67,J30,J31,J32,J69,J70,J71,J72,J73,J74) | ... V75: =SUM(V67,V30,V31,V32,V69,V70,V71,V72,V73,V74)
A76: Term loan | B76: $mm | C76: =MAX(0,MAX(0,'S&U_Opening'!$E$18+C61)+C63) | D76: =MAX(0,MAX(0,C76+D61)+D63) | E76: =MAX(0,MAX(0,D76+E61)+E63) | F76: =MAX(0,MAX(0,E76+F61)+F63) | G76: =MAX(0,MAX(0,F76+G61)+G63) | H76: =MAX(0,MAX(0,G76+H61)+H63) | I76: =MAX(0,MAX(0,H76+I61)+I63) | J76: =MAX(0,MAX(0,I76+J61)+J63) | K76: =MAX(0,MAX(0,J76+K61)+K63) | ... V76: =MAX(0,MAX(0,U76+V61)+V63)
A77: DDTL | B77: $mm | C77: =MAX(0,0+C58+C62) | D77: =MAX(0,C77+D58+D62) | E77: =MAX(0,D77+E58+E62) | F77: =MAX(0,E77+F58+F62) | G77: =MAX(0,F77+G58+G62) | H77: =MAX(0,G77+H58+H62) | I77: =MAX(0,H77+I58+I62) | J77: =MAX(0,I77+J58+J62) | K77: =MAX(0,J77+K58+K62) | ... V77: =MAX(0,U77+V58+V62)
A78: Revolver | B78: $mm | C78: =0+C59+C60 | D78: =C78+D59+D60 | E78: =D78+E59+E60 | F78: =E78+F59+F60 | G78: =F78+G59+G60 | H78: =G78+H59+H60 | I78: =H78+I59+I60 | J78: =I78+J59+J60 | K78: =J78+K59+K60 | ... V78: =U78+V59+V60
A79: Accounts payable - BS | B79: $mm | C79: =C33 | D79: =D33 | E79: =E33 | F79: =F33 | G79: =G33 | H79: =H33 | I79: =I33 | J79: =J33 | ... V79: =V33
A80: Accrued liabilities - BS | B80: $mm | C80: =C34 | D80: =D34 | E80: =E34 | F80: =F34 | G80: =G34 | H80: =H34 | I80: =I34 | J80: =J34 | ... V80: =V34
A81: Deferred revenue - BS | B81: $mm | C81: =C35 | D81: =D35 | E81: =E35 | F81: =F35 | G81: =G35 | H81: =H35 | I81: =I35 | J81: =J35 | ... V81: =V35
A82: Deferred tax liability | B82: $mm | C82: =MAX(0,'S&U_Opening'!$E$19+'Scenario_Drivers'!C23-C26+C27) | D82: =MAX(0,C82+'Scenario_Drivers'!D23-D26+D27) | E82: =MAX(0,D82+'Scenario_Drivers'!E23-E26+E27) | F82: =MAX(0,E82+'Scenario_Drivers'!F23-F26+F27) | G82: =MAX(0,F82+'Scenario_Drivers'!G23-G26+G27) | H82: =MAX(0,G82+'Scenario_Drivers'!H23-H26+H27) | I82: =MAX(0,H82+'Scenario_Drivers'!I23-I26+I27) | J82: =MAX(0,I82+'Scenario_Drivers'!J23-J26+J27) | K82: =MAX(0,J82+'Scenario_Drivers'!K23-K26+K27) | ... V82: =MAX(0,U82+'Scenario_Drivers'!V23-V26+V27)
A83: Other liabilities | B83: $mm | C83: ='S&U_Opening'!$E$20+'Scenario_Drivers'!C24 | D83: =C83+'Scenario_Drivers'!D24 | E83: =D83+'Scenario_Drivers'!E24 | F83: =E83+'Scenario_Drivers'!F24 | G83: =F83+'Scenario_Drivers'!G24 | H83: =G83+'Scenario_Drivers'!H24 | I83: =H83+'Scenario_Drivers'!I24 | J83: =I83+'Scenario_Drivers'!J24 | K83: =J83+'Scenario_Drivers'!K24 | ... V83: =U83+'Scenario_Drivers'!V24
A84: Total liabilities | B84: $mm | C84: =SUM(C76:C83) | D84: =SUM(D76:D83) | E84: =SUM(E76:E83) | F84: =SUM(F76:F83) | G84: =SUM(G76:G83) | H84: =SUM(H76:H83) | I84: =SUM(I76:I83) | J84: =SUM(J76:J83) | ... V84: =SUM(V76:V83)
A85: Equity | B85: $mm | C85: ='S&U_Opening'!$E$21+C28+C57 | D85: =C85+D28+D57 | E85: =D85+E28+E57 | F85: =E85+F28+F57 | G85: =F85+G28+G57 | H85: =G85+H28+H57 | I85: =H85+I28+I57 | J85: =I85+J28+J57 | K85: =J85+K28+K57 | ... V85: =U85+V28+V57
A86: Total liabilities & equity | B86: $mm | C86: =C84+C85 | D86: =D84+D85 | E86: =E84+E85 | F86: =F84+F85 | G86: =G84+G85 | H86: =H84+H85 | I86: =I84+I85 | J86: =J84+J85 | ... V86: =V84+V85
A87: Balance sheet check | B87: $mm | C87: =C75-C86 | D87: =D75-D86 | E87: =E75-E86 | F87: =F75-F86 | G87: =G75-G86 | H87: =H75-H86 | I87: =I75-I86 | J87: =J75-J86 | ... V87: =V75-V86
A88: Debt and Covenant Metrics
A89: Gross debt | B89: $mm | C89: =SUM(C76:C78) | D89: =SUM(D76:D78) | E89: =SUM(E76:E78) | F89: =SUM(F76:F78) | G89: =SUM(G76:G78) | H89: =SUM(H76:H78) | I89: =SUM(I76:I78) | J89: =SUM(J76:J78) | ... V89: =SUM(V76:V78)
A90: Eligible cash | B90: $mm | C90: =MIN(C67,Inputs!$B$19) | D90: =MIN(D67,Inputs!$B$19) | E90: =MIN(E67,Inputs!$B$19) | F90: =MIN(F67,Inputs!$B$19) | G90: =MIN(G67,Inputs!$B$19) | H90: =MIN(H67,Inputs!$B$19) | I90: =MIN(I67,Inputs!$B$19) | J90: =MIN(J67,Inputs!$B$19) | ... V90: =MIN(V67,Inputs!$B$19)
A91: Covenant net debt | B91: $mm | C91: =C89-C90 | D91: =D89-D90 | E91: =E89-E90 | F91: =F89-F90 | G91: =G89-G90 | H91: =H89-H90 | I91: =I89-I90 | J91: =J89-J90 | ... V91: =V89-V90
A92: Economic net debt | B92: $mm | C92: =C89-C67 | D92: =D89-D67 | E92: =E89-E67 | F92: =F89-F67 | G92: =G89-G67 | H92: =H89-H67 | I92: =I89-I67 | J92: =J89-J67 | ... V92: =V89-V67
A93: LTM revenue | B93: $mm | C93: =SUM(C5:C5) | D93: =SUM(C5:D5) | E93: =SUM(C5:E5) | F93: =SUM(C5:F5) | G93: =SUM(D5:G5) | H93: =SUM(E5:H5) | I93: =SUM(F5:I5) | J93: =SUM(G5:J5) | K93: =SUM(H5:K5) | L93: =SUM(I5:L5) | M93: =SUM(J5:M5) | ... V93: =SUM(S5:V5)
A94: LTM reported EBITDA | B94: $mm | C94: =SUM(C12:C12) | D94: =SUM(C12:D12) | E94: =SUM(C12:E12) | F94: =SUM(C12:F12) | G94: =SUM(D12:G12) | H94: =SUM(E12:H12) | I94: =SUM(F12:I12) | J94: =SUM(G12:J12) | K94: =SUM(H12:K12) | L94: =SUM(I12:L12) | M94: =SUM(J12:M12) | ... V94: =SUM(S12:V12)
A95: LTM firm EBITDA | B95: $mm | C95: =SUM(C10:C10) | D95: =SUM(C10:D10) | E95: =SUM(C10:E10) | F95: =SUM(C10:F10) | G95: =SUM(D10:G10) | H95: =SUM(E10:H10) | I95: =SUM(F10:I10) | J95: =SUM(G10:J10) | K95: =SUM(H10:K10) | L95: =SUM(I10:L10) | M95: =SUM(J10:M10) | ... V95: =SUM(S10:V10)
A96: LTM add-backs | B96: $mm | C96: =SUM(C13:C13) | D96: =SUM(C13:D13) | E96: =SUM(C13:E13) | F96: =SUM(C13:F13) | G96: =SUM(D13:G13) | H96: =SUM(E13:H13) | I96: =SUM(F13:I13) | J96: =SUM(G13:J13) | K96: =SUM(H13:K13) | L96: =SUM(I13:L13) | M96: =SUM(J13:M13) | ... V96: =SUM(S13:V13)
A97: LTM covenant EBITDA | B97: $mm | C97: =SUM(C14:C14) | D97: =SUM(C14:D14) | E97: =SUM(C14:E14) | F97: =SUM(C14:F14) | G97: =SUM(D14:G14) | H97: =SUM(E14:H14) | I97: =SUM(F14:I14) | J97: =SUM(G14:J14) | K97: =SUM(H14:K14) | L97: =SUM(I14:L14) | M97: =SUM(J14:M14) | ... V97: =SUM(S14:V14)
A98: Total net leverage | B98: x | C98: =C91/MAX(0.001,C97) | D98: =D91/MAX(0.001,D97) | E98: =E91/MAX(0.001,E97) | F98: =F91/MAX(0.001,F97) | G98: =G91/MAX(0.001,G97) | H98: =H91/MAX(0.001,H97) | I98: =I91/MAX(0.001,I97) | J98: =J91/MAX(0.001,J97) | ... V98: =V91/MAX(0.001,V97)
A99: Gross leverage | B99: x | C99: =C89/MAX(0.001,C95) | D99: =D89/MAX(0.001,D95) | E99: =E89/MAX(0.001,E95) | F99: =F89/MAX(0.001,F95) | G99: =G89/MAX(0.001,G95) | H99: =H89/MAX(0.001,H95) | I99: =I89/MAX(0.001,I95) | J99: =J89/MAX(0.001,J95) | ... V99: =V89/MAX(0.001,V95)
A100: Fixed charge coverage | B100: x | C100: =(C94-SUM(C27:C27)-SUM(C41:C41))/MAX(0.001,(-SUM(C22:C22)-SUM(C61:C61)-SUM(C62:C62))) | D100: =(D94-SUM(C27:D27)-SUM(C41:D41))/MAX(0.001,(-SUM(C22:D22)-SUM(C61:D61)-SUM(C62:D62))) | E100: =(E94-SUM(C27:E27)-SUM(C41:E41))/MAX(0.001,(-SUM(C22:E22)-SUM(C61:E61)-SUM(C62:E62))) | F100: =(F94-SUM(C27:F27)-SUM(C41:F41))/MAX(0.001,(-SUM(C22:F22)-SUM(C61:F61)-SUM(C62:F62))) | G100: =(G94-SUM(D27:G27)-SUM(D41:G41))/MAX(0.001,(-SUM(D22:G22)-SUM(D61:G61)-SUM(D62:G62))) | H100: =(H94-SUM(E27:H27)-SUM(E41:H41))/MAX(0.001,(-SUM(E22:H22)-SUM(E61:H61)-SUM(E62:H62))) | I100: =(I94-SUM(F27:I27)-SUM(F41:I41))/MAX(0.001,(-SUM(F22:I22)-SUM(F61:I61)-SUM(F62:I62))) | J100: =(J94-SUM(G27:J27)-SUM(G41:J41))/MAX(0.001,(-SUM(G22:J22)-SUM(G61:J61)-SUM(G62:J62))) | K100: =(K94-SUM(H27:K27)-SUM(H41:K41))/MAX(0.001,(-SUM(H22:K22)-SUM(H61:K61)-SUM(H62:K62))) | L100: =(L94-SUM(I27:L27)-SUM(I41:L41))/MAX(0.001,(-SUM(I22:L22)-SUM(I61:L61)-SUM(I62:L62))) | M100: =(M94-SUM(J27:M27)-SUM(J41:M41))/MAX(0.001,(-SUM(J22:M22)-SUM(J61:M61)-SUM(J62:M62))) | ... V100: =(V94-SUM(S27:V27)-SUM(S41:V41))/MAX(0.001,(-SUM(S22:V22)-SUM(S61:V61)-SUM(S62:V62)))
A101: Revolver availability | B101: $mm | C101: =MAX(0,Inputs!$B$20-C78-'Scenario_Drivers'!C28) | D101: =MAX(0,Inputs!$B$20-D78-'Scenario_Drivers'!D28) | E101: =MAX(0,Inputs!$B$20-E78-'Scenario_Drivers'!E28) | F101: =MAX(0,Inputs!$B$20-F78-'Scenario_Drivers'!F28) | G101: =MAX(0,Inputs!$B$20-G78-'Scenario_Drivers'!G28) | H101: =MAX(0,Inputs!$B$20-H78-'Scenario_Drivers'!H28) | I101: =MAX(0,Inputs!$B$20-I78-'Scenario_Drivers'!I28) | J101: =MAX(0,Inputs!$B$20-J78-'Scenario_Drivers'!J28) | ... V101: =MAX(0,Inputs!$B$20-V78-'Scenario_Drivers'!V28)
...

Sheet SB_Down
A1: Project Keystone - Standalone Downside Quarterly LBO ($mm)
A3: Line Item | B3: Unit | C3: 46203 | D3: 46295 | E3: 46387 | F3: 46477 | G3: 46568 | H3: 46660 | I3: 46752 | J3: 46843 | K3: 46934 | L3: 47026 | M3: 47118 | N3: 47208 | O3: 47299 | P3: 47391 | Q3: 47483 | R3: 47573 | S3: 47664 | T3: 47756 | U3: 47848 | V3: 47938
A4: Operating Model
A5: Revenue | B5: $mm | C5: ='Scenario_Drivers'!C39 | D5: ='Scenario_Drivers'!D39 | E5: ='Scenario_Drivers'!E39 | F5: ='Scenario_Drivers'!F39 | G5: ='Scenario_Drivers'!G39 | H5: ='Scenario_Drivers'!H39 | I5: ='Scenario_Drivers'!I39 | J5: ='Scenario_Drivers'!J39 | ... V5: ='Scenario_Drivers'!V39
A6: Growth | B6: % | C6: =C5/(74.0*'Scenario_Drivers'!C70)-1 | D6: =D5/C5-1 | E6: =E5/D5-1 | F6: =F5/V5-1 | G6: =G5/F5-1 | H6: =H5/G5-1 | I6: =I5/H5-1 | J6: =J5/F5-1 | K6: =K5/J5-1 | L6: =L5/K5-1 | M6: =M5/L5-1 | N6: =N5/J5-1 | O6: =O5/N5-1 | P6: =P5/O5-1 | Q6: =Q5/P5-1 | R6: =R5/N5-1 | S6: =S5/R5-1 | T6: =T5/S5-1 | U6: =U5/T5-1 | V6: =V5/R5-1
A7: Gross margin | B7: % | C7: ='Scenario_Drivers'!C40 | D7: ='Scenario_Drivers'!D40 | E7: ='Scenario_Drivers'!E40 | F7: ='Scenario_Drivers'!F40 | G7: ='Scenario_Drivers'!G40 | H7: ='Scenario_Drivers'!H40 | I7: ='Scenario_Drivers'!I40 | J7: ='Scenario_Drivers'!J40 | ... V7: ='Scenario_Drivers'!V40
A8: Gross profit | B8: $mm | C8: =C5*C7 | D8: =D5*D7 | E8: =E5*E7 | F8: =F5*F7 | G8: =G5*G7 | H8: =H5*H7 | I8: =I5*I7 | J8: =J5*J7 | ... V8: =V5*V7
A9: COGS | B9: $mm | C9: =-(C5-C8) | D9: =-(D5-D8) | E9: =-(E5-E8) | F9: =-(F5-F8) | G9: =-(G5-G8) | H9: =-(H5-H8) | I9: =-(I5-I8) | J9: =-(J5-J8) | ... V9: =-(V5-V8)
A10: Firm EBITDA | B10: $mm | C10: ='Scenario_Drivers'!C41 | D10: ='Scenario_Drivers'!D41 | E10: ='Scenario_Drivers'!E41 | F10: ='Scenario_Drivers'!F41 | G10: ='Scenario_Drivers'!G41 | H10: ='Scenario_Drivers'!H41 | I10: ='Scenario_Drivers'!I41 | J10: ='Scenario_Drivers'!J41 | ... V10: ='Scenario_Drivers'!V41
A11: One-time charges | B11: $mm | C11: =-'Scenario_Drivers'!C42 | D11: =-'Scenario_Drivers'!D42 | E11: =-'Scenario_Drivers'!E42 | F11: =-'Scenario_Drivers'!F42 | G11: =-'Scenario_Drivers'!G42 | H11: =-'Scenario_Drivers'!H42 | I11: =-'Scenario_Drivers'!I42 | J11: =-'Scenario_Drivers'!J42 | ... V11: =-'Scenario_Drivers'!V42
A12: Reported EBITDA | B12: $mm | C12: =C10+C11 | D12: =D10+D11 | E12: =E10+E11 | F12: =F10+F11 | G12: =G10+G11 | H12: =H10+H11 | I12: =I10+I11 | J12: =J10+J11 | ... V12: =V10+V11
A13: Covenant add-backs | B13: $mm | C13: ='Scenario_Drivers'!C43 | D13: ='Scenario_Drivers'!D43 | E13: ='Scenario_Drivers'!E43 | F13: ='Scenario_Drivers'!F43 | G13: ='Scenario_Drivers'!G43 | H13: ='Scenario_Drivers'!H43 | I13: ='Scenario_Drivers'!I43 | J13: ='Scenario_Drivers'!J43 | ... V13: ='Scenario_Drivers'!V43
A14: Covenant EBITDA | B14: $mm | C14: =C12+C13 | D14: =D12+D13 | E14: =E12+E13 | F14: =F12+F13 | G14: =G12+G13 | H14: =H12+H13 | I14: =I12+I13 | J14: =J12+J13 | ... V14: =V12+V13
A15: Firm EBITDA margin | B15: % | C15: =C10/C5 | D15: =D10/D5 | E15: =E10/E5 | F15: =F10/F5 | G15: =G10/G5 | H15: =H10/H5 | I15: =I10/I5 | J15: =J10/J5 | ... V15: =V10/V5
A16: Income Statement
A17: Depreciation | B17: $mm | C17: =C5*Inputs!$B$17 | D17: =D5*Inputs!$B$17 | E17: =E5*Inputs!$B$17 | F17: =F5*Inputs!$B$17 | G17: =G5*Inputs!$B$17 | H17: =H5*Inputs!$B$17 | I17: =I5*Inputs!$B$17 | J17: =J5*Inputs!$B$17 | ... V17: =V5*Inputs!$B$17
A18: Core PPA amortization | B18: $mm | C18: ='Scenario_Drivers'!C69 | D18: ='Scenario_Drivers'!D69 | E18: ='Scenario_Drivers'!E69 | F18: ='Scenario_Drivers'!F69 | G18: ='Scenario_Drivers'!G69 | H18: ='Scenario_Drivers'!H69 | I18: ='Scenario_Drivers'!I69 | J18: ='Scenario_Drivers'!J69 | ... V18: ='Scenario_Drivers'!V69
A19: Integration asset amortization | B19: $mm | C19: =0 | D19: =0 | E19: =0 | F19: =0 | G19: =0 | H19: =0 | I19: =0 | J19: =0 | ... V19: =0
A20: Total D&A | B20: $mm | C20: =SUM(C17:C19) | D20: =SUM(D17:D19) | E20: =SUM(E17:E19) | F20: =SUM(F17:F19) | G20: =SUM(G17:G19) | H20: =SUM(H17:H19) | I20: =SUM(I17:I19) | J20: =SUM(J17:J19) | ... V20: =SUM(V17:V19)
A21: EBIT | B21: $mm | C21: =C12-C20 | D21: =D12-D20 | E21: =E12-E20 | F21: =F12-F20 | G21: =G12-G20 | H21: =H12-H20 | I21: =I12-I20 | J21: =J12-J20 | ... V21: =V12-V20
A22: Cash interest | B22: $mm | C22: =-((('S&U_Opening'!$E$18+MAX(0,'S&U_Opening'!$E$18-(MIN(0.107,'S&U_Opening'!$E$18))))/2)*(MAX('Scenario_Drivers'!C67,Inputs!$B$26)+Inputs!$B$23+'Scenario_Drivers'!C68)/4+((0+0+'Scenario_Drivers'!C59-(IF(0>0,MIN(0.015,0),0)))/2)*(MAX('Scenario_Drivers'!C67,Inputs!$B$26)+Inputs!$B$25+'Scenario_Drivers'!C68)/4+0*(MAX('Scenario_Drivers'!C67,Inputs!$B$26)+Inputs!$B$24+'Scenario_Drivers'!C68)/4+MAX(0,Inputs!$B$20-0-'Scenario_Drivers'!C62)*Inputs!$B$29/4+0) | D22: =-(((C76+MAX(0,C76-(MIN(0.107,C76))))/2)*(MAX('Scenario_Drivers'!D67,Inputs!$B$26)+Inputs!$B$23+'Scenario_Drivers'!D68)/4+((C77+C77+'Scenario_Drivers'!D59-(IF(C77>0,MIN(0.015,C77),0)))/2)*(MAX('Scenario_Drivers'!D67,Inputs!$B$26)+Inputs!$B$25+'Scenario_Drivers'!D68)/4+C78*(MAX('Scenario_Drivers'!D67,Inputs!$B$26)+Inputs!$B$24+'Scenario_Drivers'!D68)/4+MAX(0,Inputs!$B$20-C78-'Scenario_Drivers'!D62)*Inputs!$B$29/4+MAX(0,Inputs!$B$21-C77-'Scenario_Drivers'!D59)*Inputs!$B$30/4) | E22: =-(((D76+MAX(0,D76-(MIN(0.107,D76))))/2)*(MAX('Scenario_Drivers'!E67,Inputs!$B$26)+Inputs!$B$23+'Scenario_Drivers'!E68)/4+((D77+D77+'Scenario_Drivers'!E59-(IF(D77>0,MIN(0.015,D77),0)))/2)*(MAX('Scenario_Drivers'!E67,Inputs!$B$26)+Inputs!$B$25+'Scenario_Drivers'!E68)/4+D78*(MAX('Scenario_Drivers'!E67,Inputs!$B$26)+Inputs!$B$24+'Scenario_Drivers'!E68)/4+MAX(0,Inputs!$B$20-D78-'Scenario_Drivers'!E62)*Inputs!$B$29/4+MAX(0,Inputs!$B$21-D77-'Scenario_Drivers'!E59)*Inputs!$B$30/4) | F22: =-(((E76+MAX(0,E76-(MIN(0.107,E76))))/2)*(MAX('Scenario_Drivers'!F67,Inputs!$B$26)+Inputs!$B$23+'Scenario_Drivers'!F68)/4+((E77+E77+'Scenario_Drivers'!F59-(IF(E77>0,MIN(0.015,E77),0)))/2)*(MAX('Scenario_Drivers'!F67,Inputs!$B$26)+Inputs!$B$25+'Scenario_Drivers'!F68)/4+E78*(MAX('Scenario_Drivers'!F67,Inputs!$B$26)+Inputs!$B$24+'Scenario_Drivers'!F68)/4+MAX(0,Inputs!$B$20-E78-'Scenario_Drivers'!F62)*Inputs!$B$29/4+MAX(0,Inputs!$B$21-E77-'Scenario_Drivers'!F59)*Inputs!$B$30/4) | G22: =-(((F76+MAX(0,F76-(MIN(0.107,F76))))/2)*(MAX('Scenario_Drivers'!G67,Inputs!$B$26)+Inputs!$B$23+'Scenario_Drivers'!G68)/4+((F77+F77+'Scenario_Drivers'!G59-(IF(F77>0,MIN(0.015,F77),0)))/2)*(MAX('Scenario_Drivers'!G67,Inputs!$B$26)+Inputs!$B$25+'Scenario_Drivers'!G68)/4+F78*(MAX('Scenario_Drivers'!G67,Inputs!$B$26)+Inputs!$B$24+'Scenario_Drivers'!G68)/4+MAX(0,Inputs!$B$20-F78-'Scenario_Drivers'!G62)*Inputs!$B$29/4+MAX(0,Inputs!$B$21-F77-'Scenario_Drivers'!G59)*Inputs!$B$30/4) | H22: =-(((G76+MAX(0,G76-(MIN(0.107,G76))))/2)*(MAX('Scenario_Drivers'!H67,Inputs!$B$26)+Inputs!$B$23+'Scenario_Drivers'!H68)/4+((G77+G77+'Scenario_Drivers'!H59-(IF(G77>0,MIN(0.015,G77),0)))/2)*(MAX('Scenario_Drivers'!H67,Inputs!$B$26)+Inputs!$B$25+'Scenario_Drivers'!H68)/4+G78*(MAX('Scenario_Drivers'!H67,Inputs!$B$26)+Inputs!$B$24+'Scenario_Drivers'!H68)/4+MAX(0,Inputs!$B$20-G78-'Scenario_Drivers'!H62)*Inputs!$B$29/4+MAX(0,Inputs!$B$21-G77-'Scenario_Drivers'!H59)*Inputs!$B$30/4) | I22: =-(((H76+MAX(0,H76-(MIN(0.107,H76))))/2)*(MAX('Scenario_Drivers'!I67,Inputs!$B$26)+Inputs!$B$23+'Scenario_Drivers'!I68)/4+((H77+H77+'Scenario_Drivers'!I59-(IF(H77>0,MIN(0.015,H77),0)))/2)*(MAX('Scenario_Drivers'!I67,Inputs!$B$26)+Inputs!$B$25+'Scenario_Drivers'!I68)/4+H78*(MAX('Scenario_Drivers'!I67,Inputs!$B$26)+Inputs!$B$24+'Scenario_Drivers'!I68)/4+MAX(0,Inputs!$B$20-H78-'Scenario_Drivers'!I62)*Inputs!$B$29/4+0) | J22: =-(((I76+MAX(0,I76-(MIN(0.107,I76))))/2)*(MAX('Scenario_Drivers'!J67,Inputs!$B$26)+Inputs!$B$23+'Scenario_Drivers'!J68)/4+((I77+I77+'Scenario_Drivers'!J59-(IF(I77>0,MIN(0.015,I77),0)))/2)*(MAX('Scenario_Drivers'!J67,Inputs!$B$26)+Inputs!$B$25+'Scenario_Drivers'!J68)/4+I78*(MAX('Scenario_Drivers'!J67,Inputs!$B$26)+Inputs!$B$24+'Scenario_Drivers'!J68)/4+MAX(0,Inputs!$B$20-I78-'Scenario_Drivers'!J62)*Inputs!$B$29/4+0) | K22: =-(((J76+MAX(0,J76-(MIN(0.107,J76))))/2)*(MAX('Scenario_Drivers'!K67,Inputs!$B$26)+Inputs!$B$23+'Scenario_Drivers'!K68)/4+((J77+J77+'Scenario_Drivers'!K59-(IF(J77>0,MIN(0.015,J77),0)))/2)*(MAX('Scenario_Drivers'!K67,Inputs!$B$26)+Inputs!$B$25+'Scenario_Drivers'!K68)/4+J78*(MAX('Scenario_Drivers'!K67,Inputs!$B$26)+Inputs!$B$24+'Scenario_Drivers'!K68)/4+MAX(0,Inputs!$B$20-J78-'Scenario_Drivers'!K62)*Inputs!$B$29/4+0) | L22: =-(((K76+MAX(0,K76-(MIN(0.107,K76))))/2)*(MAX('Scenario_Drivers'!L67,Inputs!$B$26)+Inputs!$B$23+'Scenario_Drivers'!L68)/4+((K77+K77+'Scenario_Drivers'!L59-(IF(K77>0,MIN(0.015,K77),0)))/2)*(MAX('Scenario_Drivers'!L67,Inputs!$B$26)+Inputs!$B$25+'Scenario_Drivers'!L68)/4+K78*(MAX('Scenario_Drivers'!L67,Inputs!$B$26)+Inputs!$B$24+'Scenario_Drivers'!L68)/4+MAX(0,Inputs!$B$20-K78-'Scenario_Drivers'!L62)*Inputs!$B$29/4+0) | M22: =-(((L76+MAX(0,L76-(MIN(0.107,L76))))/2)*(MAX('Scenario_Drivers'!M67,Inputs!$B$26)+Inputs!$B$23+'Scenario_Drivers'!M68)/4+((L77+L77+'Scenario_Drivers'!M59-(IF(L77>0,MIN(0.015,L77),0)))/2)*(MAX('Scenario_Drivers'!M67,Inputs!$B$26)+Inputs!$B$25+'Scenario_Drivers'!M68)/4+L78*(MAX('Scenario_Drivers'!M67,Inputs!$B$26)+Inputs!$B$24+'Scenario_Drivers'!M68)/4+MAX(0,Inputs!$B$20-L78-'Scenario_Drivers'!M62)*Inputs!$B$29/4+0) | N22: =-(((M76+MAX(0,M76-(MIN(0.107,M76))))/2)*(MAX('Scenario_Drivers'!N67,Inputs!$B$26)+Inputs!$B$23+'Scenario_Drivers'!N68)/4+((M77+M77+'Scenario_Drivers'!N59-(IF(M77>0,MIN(0.015,M77),0)))/2)*(MAX('Scenario_Drivers'!N67,Inputs!$B$26)+Inputs!$B$25+'Scenario_Drivers'!N68)/4+M78*(MAX('Scenario_Drivers'!N67,Inputs!$B$26)+Inputs!$B$24+'Scenario_Drivers'!N68)/4+MAX(0,Inputs!$B$20-M78-'Scenario_Drivers'!N62)*Inputs!$B$29/4+0) | O22: =-(((N76+MAX(0,N76-(MIN(0.107,N76))))/2)*(MAX('Scenario_Drivers'!O67,Inputs!$B$26)+Inputs!$B$23+'Scenario_Drivers'!O68)/4+((N77+N77+'Scenario_Drivers'!O59-(IF(N77>0,MIN(0.015,N77),0)))/2)*(MAX('Scenario_Drivers'!O67,Inputs!$B$26)+Inputs!$B$25+'Scenario_Drivers'!O68)/4+N78*(MAX('Scenario_Drivers'!O67,Inputs!$B$26)+Inputs!$B$24+'Scenario_Drivers'!O68)/4+MAX(0,Inputs!$B$20-N78-'Scenario_Drivers'!O62)*Inputs!$B$29/4+0) | P22: =-(((O76+MAX(0,O76-(MIN(0.107,O76))))/2)*(MAX('Scenario_Drivers'!P67,Inputs!$B$26)+Inputs!$B$23+'Scenario_Drivers'!P68)/4+((O77+O77+'Scenario_Drivers'!P59-(IF(O77>0,MIN(0.015,O77),0)))/2)*(MAX('Scenario_Drivers'!P67,Inputs!$B$26)+Inputs!$B$25+'Scenario_Drivers'!P68)/4+O78*(MAX('Scenario_Drivers'!P67,Inputs!$B$26)+Inputs!$B$24+'Scenario_Drivers'!P68)/4+MAX(0,Inputs!$B$20-O78-'Scenario_Drivers'!P62)*Inputs!$B$29/4+0) | ... V22: =-(((U76+MAX(0,U76-(MIN(0.107,U76))))/2)*(MAX('Scenario_Drivers'!V67,Inputs!$B$26)+Inputs!$B$23+'Scenario_Drivers'!V68)/4+((U77+U77+'Scenario_Drivers'!V59-(IF(U77>0,MIN(0.015,U77),0)))/2)*(MAX('Scenario_Drivers'!V67,Inputs!$B$26)+Inputs!$B$25+'Scenario_Drivers'!V68)/4+U78*(MAX('Scenario_Drivers'!V67,Inputs!$B$26)+Inputs!$B$24+'Scenario_Drivers'!V68)/4+MAX(0,Inputs!$B$20-U78-'Scenario_Drivers'!V62)*Inputs!$B$29/4+0)
A23: Financing fee amortization | B23: $mm | C23: =MIN('S&U_Opening'!$B$24,1.4/24) | D23: =MIN(C73,1.4/24) | E23: =MIN(D73,1.4/24) | F23: =MIN(E73,1.4/24) | G23: =MIN(F73,1.4/24) | H23: =MIN(G73,1.4/24) | I23: =MIN(H73,1.4/24) | J23: =MIN(I73,1.4/24) | K23: =MIN(J73,1.4/24) | ... V23: =MIN(U73,1.4/24)
A24: Interest income | B24: $mm | C24: ='S&U_Opening'!$B$15*1.0%/4 | D24: =C67*1.0%/4 | E24: =D67*1.0%/4 | F24: =E67*1.0%/4 | G24: =F67*1.0%/4 | H24: =G67*1.0%/4 | I24: =H67*1.0%/4 | J24: =I67*1.0%/4 | K24: =J67*1.0%/4 | ... V24: =U67*1.0%/4
A25: Pre-tax income | B25: $mm | C25: =C21+C22-C23+C24 | D25: =D21+D22-D23+D24 | E25: =E21+E22-E23+E24 | F25: =F21+F22-F23+F24 | G25: =G21+G22-G23+G24 | H25: =H21+H22-H23+H24 | I25: =I21+I22-I23+I24 | J25: =J21+J22-J23+J24 | ... V25: =V21+V22-V23+V24
A26: Book tax expense | B26: $mm | C26: =-MAX(0,C25*Inputs!$B$15) | D26: =-MAX(0,D25*Inputs!$B$15) | E26: =-MAX(0,E25*Inputs!$B$15) | F26: =-MAX(0,F25*Inputs!$B$15) | G26: =-MAX(0,G25*Inputs!$B$15) | H26: =-MAX(0,H25*Inputs!$B$15) | I26: =-MAX(0,I25*Inputs!$B$15) | J26: =-MAX(0,J25*Inputs!$B$15) | ... V26: =-MAX(0,V25*Inputs!$B$15)
A27: Cash taxes | B27: $mm | C27: =-MAX(0,(C116-0)*Inputs!$B$15) | D27: =-MAX(0,(D116-C115)*Inputs!$B$15) | E27: =-MAX(0,(E116-D115)*Inputs!$B$15) | F27: =-MAX(0,(F116-E115)*Inputs!$B$15) | G27: =-MAX(0,(G116-F115)*Inputs!$B$15) | H27: =-MAX(0,(H116-G115)*Inputs!$B$15) | I27: =-MAX(0,(I116-H115)*Inputs!$B$15) | J27: =-MAX(0,(J116-I115)*Inputs!$B$15) | K27: =-MAX(0,(K116-J115)*Inputs!$B$15) | ... V27: =-MAX(0,(V116-U115)*Inputs!$B$15)
A28: Net income | B28: $mm | C28: =C25+C26 | D28: =D25+D26 | E28: =E25+E26 | F28: =F25+F26 | G28: =G25+G26 | H28: =H25+H26 | I28: =I25+I26 | J28: =J25+J26 | ... V28: =V25+V26
A29: Working Capital and Capital Expenditure
A30: Accounts receivable | B30: $mm | C30: =(C5/'Scenario_Drivers'!C70)*'Scenario_Drivers'!C44/365 | D30: =(D5/'Scenario_Drivers'!D70)*'Scenario_Drivers'!D44/365 | E30: =(E5/'Scenario_Drivers'!E70)*'Scenario_Drivers'!E44/365 | F30: =(F5/'Scenario_Drivers'!F70)*'Scenario_Drivers'!F44/365 | G30: =(G5/'Scenario_Drivers'!G70)*'Scenario_Drivers'!G44/365 | H30: =(H5/'Scenario_Drivers'!H70)*'Scenario_Drivers'!H44/365 | I30: =(I5/'Scenario_Drivers'!I70)*'Scenario_Drivers'!I44/365 | J30: =(J5/'Scenario_Drivers'!J70)*'Scenario_Drivers'!J44/365 | ... V30: =(V5/'Scenario_Drivers'!V70)*'Scenario_Drivers'!V44/365
A31: Unbilled WIP | B31: $mm | C31: =(C5/'Scenario_Drivers'!C70)*'Scenario_Drivers'!C45 | D31: =(D5/'Scenario_Drivers'!D70)*'Scenario_Drivers'!D45 | E31: =(E5/'Scenario_Drivers'!E70)*'Scenario_Drivers'!E45 | F31: =(F5/'Scenario_Drivers'!F70)*'Scenario_Drivers'!F45 | G31: =(G5/'Scenario_Drivers'!G70)*'Scenario_Drivers'!G45 | H31: =(H5/'Scenario_Drivers'!H70)*'Scenario_Drivers'!H45 | I31: =(I5/'Scenario_Drivers'!I70)*'Scenario_Drivers'!I45 | J31: =(J5/'Scenario_Drivers'!J70)*'Scenario_Drivers'!J45 | ... V31: =(V5/'Scenario_Drivers'!V70)*'Scenario_Drivers'!V45
A32: Prepaids | B32: $mm | C32: =(C5/'Scenario_Drivers'!C70)*'Scenario_Drivers'!C46 | D32: =(D5/'Scenario_Drivers'!D70)*'Scenario_Drivers'!D46 | E32: =(E5/'Scenario_Drivers'!E70)*'Scenario_Drivers'!E46 | F32: =(F5/'Scenario_Drivers'!F70)*'Scenario_Drivers'!F46 | G32: =(G5/'Scenario_Drivers'!G70)*'Scenario_Drivers'!G46 | H32: =(H5/'Scenario_Drivers'!H70)*'Scenario_Drivers'!H46 | I32: =(I5/'Scenario_Drivers'!I70)*'Scenario_Drivers'!I46 | J32: =(J5/'Scenario_Drivers'!J70)*'Scenario_Drivers'!J46 | ... V32: =(V5/'Scenario_Drivers'!V70)*'Scenario_Drivers'!V46
A33: Accounts payable | B33: $mm | C33: =(C5/'Scenario_Drivers'!C70)*'Scenario_Drivers'!C47 | D33: =(D5/'Scenario_Drivers'!D70)*'Scenario_Drivers'!D47 | E33: =(E5/'Scenario_Drivers'!E70)*'Scenario_Drivers'!E47 | F33: =(F5/'Scenario_Drivers'!F70)*'Scenario_Drivers'!F47 | G33: =(G5/'Scenario_Drivers'!G70)*'Scenario_Drivers'!G47 | H33: =(H5/'Scenario_Drivers'!H70)*'Scenario_Drivers'!H47 | I33: =(I5/'Scenario_Drivers'!I70)*'Scenario_Drivers'!I47 | J33: =(J5/'Scenario_Drivers'!J70)*'Scenario_Drivers'!J47 | ... V33: =(V5/'Scenario_Drivers'!V70)*'Scenario_Drivers'!V47
A34: Accrued liabilities | B34: $mm | C34: =(C5/'Scenario_Drivers'!C70)*'Scenario_Drivers'!C48 | D34: =(D5/'Scenario_Drivers'!D70)*'Scenario_Drivers'!D48 | E34: =(E5/'Scenario_Drivers'!E70)*'Scenario_Drivers'!E48 | F34: =(F5/'Scenario_Drivers'!F70)*'Scenario_Drivers'!F48 | G34: =(G5/'Scenario_Drivers'!G70)*'Scenario_Drivers'!G48 | H34: =(H5/'Scenario_Drivers'!H70)*'Scenario_Drivers'!H48 | I34: =(I5/'Scenario_Drivers'!I70)*'Scenario_Drivers'!I48 | J34: =(J5/'Scenario_Drivers'!J70)*'Scenario_Drivers'!J48 | ... V34: =(V5/'Scenario_Drivers'!V70)*'Scenario_Drivers'!V48
A35: Deferred revenue | B35: $mm | C35: =(C5/'Scenario_Drivers'!C70)*'Scenario_Drivers'!C49 | D35: =(D5/'Scenario_Drivers'!D70)*'Scenario_Drivers'!D49 | E35: =(E5/'Scenario_Drivers'!E70)*'Scenario_Drivers'!E49 | F35: =(F5/'Scenario_Drivers'!F70)*'Scenario_Drivers'!F49 | G35: =(G5/'Scenario_Drivers'!G70)*'Scenario_Drivers'!G49 | H35: =(H5/'Scenario_Drivers'!H70)*'Scenario_Drivers'!H49 | I35: =(I5/'Scenario_Drivers'!I70)*'Scenario_Drivers'!I49 | J35: =(J5/'Scenario_Drivers'!J70)*'Scenario_Drivers'!J49 | ... V35: =(V5/'Scenario_Drivers'!V70)*'Scenario_Drivers'!V49
A36: Operating NWC | B36: $mm | C36: =C30+C31+C32-C33-C34-C35 | D36: =D30+D31+D32-D33-D34-D35 | E36: =E30+E31+E32-E33-E34-E35 | F36: =F30+F31+F32-F33-F34-F35 | G36: =G30+G31+G32-G33-G34-G35 | H36: =H30+H31+H32-H33-H34-H35 | I36: =I30+I31+I32-I33-I34-I35 | J36: =J30+J31+J32-J33-J34-J35 | ... V36: =V30+V31+V32-V33-V34-V35
A37: Acquired NWC | B37: $mm | C37: ='Scenario_Drivers'!C51 | D37: ='Scenario_Drivers'!D51 | E37: ='Scenario_Drivers'!E51 | F37: ='Scenario_Drivers'!F51 | G37: ='Scenario_Drivers'!G51 | H37: ='Scenario_Drivers'!H51 | I37: ='Scenario_Drivers'!I51 | J37: ='Scenario_Drivers'!J51 | ... V37: ='Scenario_Drivers'!V51
A38: Organic change in NWC | B38: $mm | C38: =C36-('S&U_Opening'!$B$16+'S&U_Opening'!$B$17+'S&U_Opening'!$B$18-'S&U_Opening'!$E$15-'S&U_Opening'!$E$16-'S&U_Opening'!$E$17)-C37 | D38: =D36-(C36)-D37 | E38: =E36-(D36)-E37 | F38: =F36-(E36)-F37 | G38: =G36-(F36)-G37 | H38: =H36-(G36)-H37 | I38: =I36-(H36)-I37 | J38: =J36-(I36)-J37 | K38: =K36-(J36)-K37 | ... V38: =V36-(U36)-V37
A39: Maintenance capex | B39: $mm | C39: =C5*'Scenario_Drivers'!C50*Inputs!$B$18 | D39: =D5*'Scenario_Drivers'!D50*Inputs!$B$18 | E39: =E5*'Scenario_Drivers'!E50*Inputs!$B$18 | F39: =F5*'Scenario_Drivers'!F50*Inputs!$B$18 | G39: =G5*'Scenario_Drivers'!G50*Inputs!$B$18 | H39: =H5*'Scenario_Drivers'!H50*Inputs!$B$18 | I39: =I5*'Scenario_Drivers'!I50*Inputs!$B$18 | J39: =J5*'Scenario_Drivers'!J50*Inputs!$B$18 | ... V39: =V5*'Scenario_Drivers'!V50*Inputs!$B$18
A40: Growth capex | B40: $mm | C40: =C5*'Scenario_Drivers'!C50*(1-Inputs!$B$18) | D40: =D5*'Scenario_Drivers'!D50*(1-Inputs!$B$18) | E40: =E5*'Scenario_Drivers'!E50*(1-Inputs!$B$18) | F40: =F5*'Scenario_Drivers'!F50*(1-Inputs!$B$18) | G40: =G5*'Scenario_Drivers'!G50*(1-Inputs!$B$18) | H40: =H5*'Scenario_Drivers'!H50*(1-Inputs!$B$18) | I40: =I5*'Scenario_Drivers'!I50*(1-Inputs!$B$18) | J40: =J5*'Scenario_Drivers'!J50*(1-Inputs!$B$18) | ... V40: =V5*'Scenario_Drivers'!V50*(1-Inputs!$B$18)
A41: Total capex | B41: $mm | C41: =SUM(C39:C40) | D41: =SUM(D39:D40) | E41: =SUM(E39:E40) | F41: =SUM(F39:F40) | G41: =SUM(G39:G40) | H41: =SUM(H39:H40) | I41: =SUM(I39:I40) | J41: =SUM(J39:J40) | ... V41: =SUM(V39:V40)
A42: Acquired PP&E | B42: $mm | C42: ='Scenario_Drivers'!C52 | D42: ='Scenario_Drivers'!D52 | E42: ='Scenario_Drivers'!E52 | F42: ='Scenario_Drivers'!F52 | G42: ='Scenario_Drivers'!G52 | H42: ='Scenario_Drivers'!H52 | I42: ='Scenario_Drivers'!I52 | J42: ='Scenario_Drivers'!J52 | ... V42: ='Scenario_Drivers'!V52
A43: Acquisition EV | B43: $mm | C43: ='Scenario_Drivers'!C53 | D43: ='Scenario_Drivers'!D53 | E43: ='Scenario_Drivers'!E53 | F43: ='Scenario_Drivers'!F53 | G43: ='Scenario_Drivers'!G53 | H43: ='Scenario_Drivers'!H53 | I43: ='Scenario_Drivers'!I53 | J43: ='Scenario_Drivers'!J53 | ... V43: ='Scenario_Drivers'!V53
A44: Acquisition fees | B44: $mm | C44: ='Scenario_Drivers'!C54 | D44: ='Scenario_Drivers'!D54 | E44: ='Scenario_Drivers'!E54 | F44: ='Scenario_Drivers'!F54 | G44: ='Scenario_Drivers'!G54 | H44: ='Scenario_Drivers'!H54 | I44: ='Scenario_Drivers'!I54 | J44: ='Scenario_Drivers'!J54 | ... V44: ='Scenario_Drivers'!V54
A45: Capitalized integration spend | B45: $mm | C45: ='Scenario_Drivers'!C61 | D45: ='Scenario_Drivers'!D61 | E45: ='Scenario_Drivers'!E61 | F45: ='Scenario_Drivers'!F61 | G45: ='Scenario_Drivers'!G61 | H45: ='Scenario_Drivers'!H61 | I45: ='Scenario_Drivers'!I61 | J45: ='Scenario_Drivers'!J61 | ... V45: ='Scenario_Drivers'!V61
A46: Cash Flow Statement
A47: Net income - CF | B47: $mm | C47: =C28 | D47: =D28 | E47: =E28 | F47: =F28 | G47: =G28 | H47: =H28 | I47: =I28 | J47: =J28 | ... V47: =V28
A48: Total D&A - CF | B48: $mm | C48: =C20 | D48: =D20 | E48: =E20 | F48: =F20 | G48: =G20 | H48: =H20 | I48: =I20 | J48: =J20 | ... V48: =V20
A49: Financing fee amortization - CF | B49: $mm | C49: =C23 | D49: =D23 | E49: =E23 | F49: =F23 | G49: =G23 | H49: =H23 | I49: =I23 | J49: =J23 | ... V49: =V23
A50: Deferred tax / non-cash tax | B50: $mm | C50: =-C26+C27 | D50: =-D26+D27 | E50: =-E26+E27 | F50: =-F26+F27 | G50: =-G26+G27 | H50: =-H26+H27 | I50: =-I26+I27 | J50: =-J26+J27 | ... V50: =-V26+V27
A51: Change in NWC - CF | B51: $mm | C51: =-C38 | D51: =-D38 | E51: =-E38 | F51: =-F38 | G51: =-G38 | H51: =-H38 | I51: =-I38 | J51: =-J38 | ... V51: =-V38
A52: Cash from operations | B52: $mm | C52: =SUM(C47:C51) | D52: =SUM(D47:D51) | E52: =SUM(E47:E51) | F52: =SUM(F47:F51) | G52: =SUM(G47:G51) | H52: =SUM(H47:H51) | I52: =SUM(I47:I51) | J52: =SUM(J47:J51) | ... V52: =SUM(V47:V51)
A53: Capital expenditure - CF | B53: $mm | C53: =-C41 | D53: =-D41 | E53: =-E41 | F53: =-F41 | G53: =-G41 | H53: =-H41 | I53: =-I41 | J53: =-J41 | ... V53: =-V41
A54: Acquisition EV - CF | B54: $mm | C54: =-C43 | D54: =-D43 | E54: =-E43 | F54: =-F43 | G54: =-G43 | H54: =-H43 | I54: =-I43 | J54: =-J43 | ... V54: =-V43
A55: Capitalized integration spend - CF | B55: $mm | C55: =-C45 | D55: =-D45 | E55: =-E45 | F55: =-F45 | G55: =-G45 | H55: =-H45 | I55: =-I45 | J55: =-J45 | ... V55: =-V45
A56: Cash from investing | B56: $mm | C56: =SUM(C53:C55) | D56: =SUM(D53:D55) | E56: =SUM(E53:E55) | F56: =SUM(F53:F55) | G56: =SUM(G53:G55) | H56: =SUM(H53:H55) | I56: =SUM(I53:I55) | J56: =SUM(J53:J55) | ... V56: =SUM(V53:V55)
A57: Sponsor equity contribution | B57: $mm | C57: ='Scenario_Drivers'!C60 | D57: ='Scenario_Drivers'!D60 | E57: ='Scenario_Drivers'!E60 | F57: ='Scenario_Drivers'!F60 | G57: ='Scenario_Drivers'!G60 | H57: ='Scenario_Drivers'!H60 | I57: ='Scenario_Drivers'!I60 | J57: ='Scenario_Drivers'!J60 | ... V57: ='Scenario_Drivers'!V60
A58: DDTL draw | B58: $mm | C58: ='Scenario_Drivers'!C59 | D58: ='Scenario_Drivers'!D59 | E58: ='Scenario_Drivers'!E59 | F58: ='Scenario_Drivers'!F59 | G58: ='Scenario_Drivers'!G59 | H58: ='Scenario_Drivers'!H59 | I58: ='Scenario_Drivers'!I59 | J58: ='Scenario_Drivers'!J59 | ... V58: ='Scenario_Drivers'!V59
A59: Revolver draw | B59: $mm | C59: =IF('Scenario_Drivers'!C64>=0,MAX(0,'Scenario_Drivers'!C64-0),IF('S&U_Opening'!$B$15+C52+C56+C57+C58+C61+C62<'Scenario_Drivers'!C63,MIN((MAX(0,Inputs!$B$20-'Scenario_Drivers'!C62))-0,'Scenario_Drivers'!C63-('S&U_Opening'!$B$15+C52+C56+C57+C58+C61+C62)),0)) | D59: =IF('Scenario_Drivers'!D64>=0,MAX(0,'Scenario_Drivers'!D64-C78),IF(C67+D52+D56+D57+D58+D61+D62<'Scenario_Drivers'!D63,MIN((MAX(0,Inputs!$B$20-'Scenario_Drivers'!D62))-C78,'Scenario_Drivers'!D63-(C67+D52+D56+D57+D58+D61+D62)),0)) | E59: =IF('Scenario_Drivers'!E64>=0,MAX(0,'Scenario_Drivers'!E64-D78),IF(D67+E52+E56+E57+E58+E61+E62<'Scenario_Drivers'!E63,MIN((MAX(0,Inputs!$B$20-'Scenario_Drivers'!E62))-D78,'Scenario_Drivers'!E63-(D67+E52+E56+E57+E58+E61+E62)),0)) | F59: =IF('Scenario_Drivers'!F64>=0,MAX(0,'Scenario_Drivers'!F64-E78),IF(E67+F52+F56+F57+F58+F61+F62<'Scenario_Drivers'!F63,MIN((MAX(0,Inputs!$B$20-'Scenario_Drivers'!F62))-E78,'Scenario_Drivers'!F63-(E67+F52+F56+F57+F58+F61+F62)),0)) | G59: =IF('Scenario_Drivers'!G64>=0,MAX(0,'Scenario_Drivers'!G64-F78),IF(F67+G52+G56+G57+G58+G61+G62<'Scenario_Drivers'!G63,MIN((MAX(0,Inputs!$B$20-'Scenario_Drivers'!G62))-F78,'Scenario_Drivers'!G63-(F67+G52+G56+G57+G58+G61+G62)),0)) | H59: =IF('Scenario_Drivers'!H64>=0,MAX(0,'Scenario_Drivers'!H64-G78),IF(G67+H52+H56+H57+H58+H61+H62<'Scenario_Drivers'!H63,MIN((MAX(0,Inputs!$B$20-'Scenario_Drivers'!H62))-G78,'Scenario_Drivers'!H63-(G67+H52+H56+H57+H58+H61+H62)),0)) | I59: =IF('Scenario_Drivers'!I64>=0,MAX(0,'Scenario_Drivers'!I64-H78),IF(H67+I52+I56+I57+I58+I61+I62<'Scenario_Drivers'!I63,MIN((MAX(0,Inputs!$B$20-'Scenario_Drivers'!I62))-H78,'Scenario_Drivers'!I63-(H67+I52+I56+I57+I58+I61+I62)),0)) | J59: =IF('Scenario_Drivers'!J64>=0,MAX(0,'Scenario_Drivers'!J64-I78),IF(I67+J52+J56+J57+J58+J61+J62<'Scenario_Drivers'!J63,MIN((MAX(0,Inputs!$B$20-'Scenario_Drivers'!J62))-I78,'Scenario_Drivers'!J63-(I67+J52+J56+J57+J58+J61+J62)),0)) | K59: =IF('Scenario_Drivers'!K64>=0,MAX(0,'Scenario_Drivers'!K64-J78),IF(J67+K52+K56+K57+K58+K61+K62<'Scenario_Drivers'!K63,MIN((MAX(0,Inputs!$B$20-'Scenario_Drivers'!K62))-J78,'Scenario_Drivers'!K63-(J67+K52+K56+K57+K58+K61+K62)),0)) | ... V59: =IF('Scenario_Drivers'!V64>=0,MAX(0,'Scenario_Drivers'!V64-U78),IF(U67+V52+V56+V57+V58+V61+V62<'Scenario_Drivers'!V63,MIN((MAX(0,Inputs!$B$20-'Scenario_Drivers'!V62))-U78,'Scenario_Drivers'!V63-(U67+V52+V56+V57+V58+V61+V62)),0))
A60: Revolver repayment | B60: $mm | C60: =-(IF('Scenario_Drivers'!C65=1,0,IF('Scenario_Drivers'!C64>=0,MAX(0,0-'Scenario_Drivers'!C64),IF('S&U_Opening'!$B$15+C52+C56+C57+C58+C61+C62>'Scenario_Drivers'!C63,MIN(0,('S&U_Opening'!$B$15+C52+C56+C57+C58+C61+C62)-'Scenario_Drivers'!C63),0)))) | D60: =-(IF('Scenario_Drivers'!D65=1,C78,IF('Scenario_Drivers'!D64>=0,MAX(0,C78-'Scenario_Drivers'!D64),IF(C67+D52+D56+D57+D58+D61+D62>'Scenario_Drivers'!D63,MIN(C78,(C67+D52+D56+D57+D58+D61+D62)-'Scenario_Drivers'!D63),0)))) | E60: =-(IF('Scenario_Drivers'!E65=1,D78,IF('Scenario_Drivers'!E64>=0,MAX(0,D78-'Scenario_Drivers'!E64),IF(D67+E52+E56+E57+E58+E61+E62>'Scenario_Drivers'!E63,MIN(D78,(D67+E52+E56+E57+E58+E61+E62)-'Scenario_Drivers'!E63),0)))) | F60: =-(IF('Scenario_Drivers'!F65=1,E78,IF('Scenario_Drivers'!F64>=0,MAX(0,E78-'Scenario_Drivers'!F64),IF(E67+F52+F56+F57+F58+F61+F62>'Scenario_Drivers'!F63,MIN(E78,(E67+F52+F56+F57+F58+F61+F62)-'Scenario_Drivers'!F63),0)))) | G60: =-(IF('Scenario_Drivers'!G65=1,F78,IF('Scenario_Drivers'!G64>=0,MAX(0,F78-'Scenario_Drivers'!G64),IF(F67+G52+G56+G57+G58+G61+G62>'Scenario_Drivers'!G63,MIN(F78,(F67+G52+G56+G57+G58+G61+G62)-'Scenario_Drivers'!G63),0)))) | H60: =-(IF('Scenario_Drivers'!H65=1,G78,IF('Scenario_Drivers'!H64>=0,MAX(0,G78-'Scenario_Drivers'!H64),IF(G67+H52+H56+H57+H58+H61+H62>'Scenario_Drivers'!H63,MIN(G78,(G67+H52+H56+H57+H58+H61+H62)-'Scenario_Drivers'!H63),0)))) | I60: =-(IF('Scenario_Drivers'!I65=1,H78,IF('Scenario_Drivers'!I64>=0,MAX(0,H78-'Scenario_Drivers'!I64),IF(H67+I52+I56+I57+I58+I61+I62>'Scenario_Drivers'!I63,MIN(H78,(H67+I52+I56+I57+I58+I61+I62)-'Scenario_Drivers'!I63),0)))) | J60: =-(IF('Scenario_Drivers'!J65=1,I78,IF('Scenario_Drivers'!J64>=0,MAX(0,I78-'Scenario_Drivers'!J64),IF(I67+J52+J56+J57+J58+J61+J62>'Scenario_Drivers'!J63,MIN(I78,(I67+J52+J56+J57+J58+J61+J62)-'Scenario_Drivers'!J63),0)))) | K60: =-(IF('Scenario_Drivers'!K65=1,J78,IF('Scenario_Drivers'!K64>=0,MAX(0,J78-'Scenario_Drivers'!K64),IF(J67+K52+K56+K57+K58+K61+K62>'Scenario_Drivers'!K63,MIN(J78,(J67+K52+K56+K57+K58+K61+K62)-'Scenario_Drivers'!K63),0)))) | ... V60: =-(IF('Scenario_Drivers'!V65=1,U78,IF('Scenario_Drivers'!V64>=0,MAX(0,U78-'Scenario_Drivers'!V64),IF(U67+V52+V56+V57+V58+V61+V62>'Scenario_Drivers'!V63,MIN(U78,(U67+V52+V56+V57+V58+V61+V62)-'Scenario_Drivers'!V63),0))))
A61: Scheduled term amortization | B61: $mm | C61: =-(MIN(0.107,'S&U_Opening'!$E$18)) | D61: =-(MIN(0.107,C76)) | E61: =-(MIN(0.107,D76)) | F61: =-(MIN(0.107,E76)) | G61: =-(MIN(0.107,F76)) | H61: =-(MIN(0.107,G76)) | I61: =-(MIN(0.107,H76)) | J61: =-(MIN(0.107,I76)) | K61: =-(MIN(0.107,J76)) | ... V61: =-(MIN(0.107,U76))
A62: Scheduled DDTL amortization | B62: $mm | C62: =-(IF(0>0,MIN(0.015,0),0)) | D62: =-(IF(C77>0,MIN(0.015,C77),0)) | E62: =-(IF(D77>0,MIN(0.015,D77),0)) | F62: =-(IF(E77>0,MIN(0.015,E77),0)) | G62: =-(IF(F77>0,MIN(0.015,F77),0)) | H62: =-(IF(G77>0,MIN(0.015,G77),0)) | I62: =-(IF(H77>0,MIN(0.015,H77),0)) | J62: =-(IF(I77>0,MIN(0.015,I77),0)) | K62: =-(IF(J77>0,MIN(0.015,J77),0)) | ... V62: =-(IF(U77>0,MIN(0.015,U77),0))
A63: ECF sweep | B63: $mm | C63: =-(0) | D63: =-(0) | E63: =-(MIN((MAX(0,D76+E61)),MAX(0,((D67+E52+E56+E57+E58+E61+E62)+E59+E60)-'Scenario_Drivers'!E63))*(IF((((MAX(0,D76+E61))+(MAX(0,D77+E58+E62))+(D78+E59+E60)-MIN(((D67+E52+E56+E57+E58+E61+E62)+E59+E60),Inputs!$B$19))/MAX(0.001,(SUM(C14:E14))))>3.0,50%,IF((((MAX(0,D76+E61))+(MAX(0,D77+E58+E62))+(D78+E59+E60)-MIN(((D67+E52+E56+E57+E58+E61+E62)+E59+E60),Inputs!$B$19))/MAX(0.001,(SUM(C14:E14))))>2.5,25%,0%)))) | F63: =-(0) | G63: =-(0) | H63: =-(0) | I63: =-(MIN((MAX(0,H76+I61)),MAX(0,((H67+I52+I56+I57+I58+I61+I62)+I59+I60)-'Scenario_Drivers'!I63))*(IF((((MAX(0,H76+I61))+(MAX(0,H77+I58+I62))+(H78+I59+I60)-MIN(((H67+I52+I56+I57+I58+I61+I62)+I59+I60),Inputs!$B$19))/MAX(0.001,(SUM(F14:I14))))>3.0,50%,IF((((MAX(0,H76+I61))+(MAX(0,H77+I58+I62))+(H78+I59+I60)-MIN(((H67+I52+I56+I57+I58+I61+I62)+I59+I60),Inputs!$B$19))/MAX(0.001,(SUM(F14:I14))))>2.5,25%,0%)))) | J63: =-(0) | K63: =-(0) | L63: =-(0) | M63: =-(MIN((MAX(0,L76+M61)),MAX(0,((L67+M52+M56+M57+M58+M61+M62)+M59+M60)-'Scenario_Drivers'!M63))*(IF((((MAX(0,L76+M61))+(MAX(0,L77+M58+M62))+(L78+M59+M60)-MIN(((L67+M52+M56+M57+M58+M61+M62)+M59+M60),Inputs!$B$19))/MAX(0.001,(SUM(J14:M14))))>3.0,50%,IF((((MAX(0,L76+M61))+(MAX(0,L77+M58+M62))+(L78+M59+M60)-MIN(((L67+M52+M56+M57+M58+M61+M62)+M59+M60),Inputs!$B$19))/MAX(0.001,(SUM(J14:M14))))>2.5,25%,0%)))) | N63: =-(0) | O63: =-(0) | P63: =-(0) | Q63: =-(MIN((MAX(0,P76+Q61)),MAX(0,((P67+Q52+Q56+Q57+Q58+Q61+Q62)+Q59+Q60)-'Scenario_Drivers'!Q63))*(IF((((MAX(0,P76+Q61))+(MAX(0,P77+Q58+Q62))+(P78+Q59+Q60)-MIN(((P67+Q52+Q56+Q57+Q58+Q61+Q62)+Q59+Q60),Inputs!$B$19))/MAX(0.001,(SUM(N14:Q14))))>3.0,50%,IF((((MAX(0,P76+Q61))+(MAX(0,P77+Q58+Q62))+(P78+Q59+Q60)-MIN(((P67+Q52+Q56+Q57+Q58+Q61+Q62)+Q59+Q60),Inputs!$B$19))/MAX(0.001,(SUM(N14:Q14))))>2.5,25%,0%)))) | R63: =-(0) | S63: =-(0) | T63: =-(0) | U63: =-(MIN((MAX(0,T76+U61)),MAX(0,((T67+U52+U56+U57+U58+U61+U62)+U59+U60)-'Scenario_Drivers'!U63))*(IF((((MAX(0,T76+U61))+(MAX(0,T77+U58+U62))+(T78+U59+U60)-MIN(((T67+U52+U56+U57+U58+U61+U62)+U59+U60),Inputs!$B$19))/MAX(0.001,(SUM(R14:U14))))>3.0,50%,IF((((MAX(0,T76+U61))+(MAX(0,T77+U58+U62))+(T78+U59+U60)-MIN(((T67+U52+U56+U57+U58+U61+U62)+U59+U60),Inputs!$B$19))/MAX(0.001,(SUM(R14:U14))))>2.5,25%,0%)))) | V63: =-(0)
A64: Cash from financing | B64: $mm | C64: =SUM(C57:C63) | D64: =SUM(D57:D63) | E64: =SUM(E57:E63) | F64: =SUM(F57:F63) | G64: =SUM(G57:G63) | H64: =SUM(H57:H63) | I64: =SUM(I57:I63) | J64: =SUM(J57:J63) | ... V64: =SUM(V57:V63)
A65: Net change in cash | B65: $mm | C65: =C52+C56+C64 | D65: =D52+D56+D64 | E65: =E52+E56+E64 | F65: =F52+F56+F64 | G65: =G52+G56+G64 | H65: =H52+H56+H64 | I65: =I52+I56+I64 | J65: =J52+J56+J64 | ... V65: =V52+V56+V64
A66: Beginning cash | B66: $mm | C66: ='S&U_Opening'!$B$15 | D66: =C67 | E66: =D67 | F66: =E67 | G66: =F67 | H66: =G67 | I66: =H67 | J66: =I67 | K66: =J67 | ... V66: =U67
A67: Ending cash | B67: $mm | C67: =C66+C65 | D67: =D66+D65 | E67: =E66+E65 | F67: =F66+F65 | G67: =G66+G65 | H67: =H66+H65 | I67: =I66+I65 | J67: =J66+J65 | ... V67: =V66+V65
A68: Balance Sheet
A69: PP&E, net | B69: $mm | C69: ='S&U_Opening'!$B$19+C41+C42-C17 | D69: =C69+D41+D42-D17 | E69: =D69+E41+E42-E17 | F69: =E69+F41+F42-F17 | G69: =F69+G41+G42-G17 | H69: =G69+H41+H42-H17 | I69: =H69+I41+I42-I17 | J69: =I69+J41+J42-J17 | K69: =J69+K41+K42-K17 | ... V69: =U69+V41+V42-V17
A70: Goodwill | B70: $mm | C70: ='S&U_Opening'!$B$20+'Scenario_Drivers'!C56 | D70: =C70+'Scenario_Drivers'!D56 | E70: =D70+'Scenario_Drivers'!E56 | F70: =E70+'Scenario_Drivers'!F56 | G70: =F70+'Scenario_Drivers'!G56 | H70: =G70+'Scenario_Drivers'!H56 | I70: =H70+'Scenario_Drivers'!I56 | J70: =I70+'Scenario_Drivers'!J56 | K70: =J70+'Scenario_Drivers'!K56 | ... V70: =U70+'Scenario_Drivers'!V56
A71: Intangibles, net | B71: $mm | C71: =MAX(0,SUM('S&U_Opening'!$B$21:$B$23)+'Scenario_Drivers'!C55-C18) | D71: =MAX(0,C71+'Scenario_Drivers'!D55-D18) | E71: =MAX(0,D71+'Scenario_Drivers'!E55-E18) | F71: =MAX(0,E71+'Scenario_Drivers'!F55-F18) | G71: =MAX(0,F71+'Scenario_Drivers'!G55-G18) | H71: =MAX(0,G71+'Scenario_Drivers'!H55-H18) | I71: =MAX(0,H71+'Scenario_Drivers'!I55-I18) | J71: =MAX(0,I71+'Scenario_Drivers'!J55-J18) | K71: =MAX(0,J71+'Scenario_Drivers'!K55-K18) | ... V71: =MAX(0,U71+'Scenario_Drivers'!V55-V18)
A72: Integration asset | B72: $mm | C72: =MAX(0,0+C45-C19) | D72: =MAX(0,C72+D45-D19) | E72: =MAX(0,D72+E45-E19) | F72: =MAX(0,E72+F45-F19) | G72: =MAX(0,F72+G45-G19) | H72: =MAX(0,G72+H45-H19) | I72: =MAX(0,H72+I45-I19) | J72: =MAX(0,I72+J45-J19) | K72: =MAX(0,J72+K45-K19) | ... V72: =MAX(0,U72+V45-V19)
A73: Deferred financing fees | B73: $mm | C73: =MAX(0,'S&U_Opening'!$B$24-C23) | D73: =MAX(0,C73-D23) | E73: =MAX(0,D73-E23) | F73: =MAX(0,E73-F23) | G73: =MAX(0,F73-G23) | H73: =MAX(0,G73-H23) | I73: =MAX(0,H73-I23) | J73: =MAX(0,I73-J23) | K73: =MAX(0,J73-K23) | ... V73: =MAX(0,U73-V23)
A74: Other assets | B74: $mm | C74: =1.3 | D74: =1.3 | E74: =1.3 | F74: =1.3 | G74: =1.3 | H74: =1.3 | I74: =1.3 | J74: =1.3 | ... V74: =1.3
A75: Total assets | B75: $mm | C75: =SUM(C67,C30,C31,C32,C69,C70,C71,C72,C73,C74) | D75: =SUM(D67,D30,D31,D32,D69,D70,D71,D72,D73,D74) | E75: =SUM(E67,E30,E31,E32,E69,E70,E71,E72,E73,E74) | F75: =SUM(F67,F30,F31,F32,F69,F70,F71,F72,F73,F74) | G75: =SUM(G67,G30,G31,G32,G69,G70,G71,G72,G73,G74) | H75: =SUM(H67,H30,H31,H32,H69,H70,H71,H72,H73,H74) | I75: =SUM(I67,I30,I31,I32,I69,I70,I71,I72,I73,I74) | J75: =SUM(J67,J30,J31,J32,J69,J70,J71,J72,J73,J74) | ... V75: =SUM(V67,V30,V31,V32,V69,V70,V71,V72,V73,V74)
A76: Term loan | B76: $mm | C76: =MAX(0,MAX(0,'S&U_Opening'!$E$18+C61)+C63) | D76: =MAX(0,MAX(0,C76+D61)+D63) | E76: =MAX(0,MAX(0,D76+E61)+E63) | F76: =MAX(0,MAX(0,E76+F61)+F63) | G76: =MAX(0,MAX(0,F76+G61)+G63) | H76: =MAX(0,MAX(0,G76+H61)+H63) | I76: =MAX(0,MAX(0,H76+I61)+I63) | J76: =MAX(0,MAX(0,I76+J61)+J63) | K76: =MAX(0,MAX(0,J76+K61)+K63) | ... V76: =MAX(0,MAX(0,U76+V61)+V63)
A77: DDTL | B77: $mm | C77: =MAX(0,0+C58+C62) | D77: =MAX(0,C77+D58+D62) | E77: =MAX(0,D77+E58+E62) | F77: =MAX(0,E77+F58+F62) | G77: =MAX(0,F77+G58+G62) | H77: =MAX(0,G77+H58+H62) | I77: =MAX(0,H77+I58+I62) | J77: =MAX(0,I77+J58+J62) | K77: =MAX(0,J77+K58+K62) | ... V77: =MAX(0,U77+V58+V62)
A78: Revolver | B78: $mm | C78: =0+C59+C60 | D78: =C78+D59+D60 | E78: =D78+E59+E60 | F78: =E78+F59+F60 | G78: =F78+G59+G60 | H78: =G78+H59+H60 | I78: =H78+I59+I60 | J78: =I78+J59+J60 | K78: =J78+K59+K60 | ... V78: =U78+V59+V60
A79: Accounts payable - BS | B79: $mm | C79: =C33 | D79: =D33 | E79: =E33 | F79: =F33 | G79: =G33 | H79: =H33 | I79: =I33 | J79: =J33 | ... V79: =V33
A80: Accrued liabilities - BS | B80: $mm | C80: =C34 | D80: =D34 | E80: =E34 | F80: =F34 | G80: =G34 | H80: =H34 | I80: =I34 | J80: =J34 | ... V80: =V34
A81: Deferred revenue - BS | B81: $mm | C81: =C35 | D81: =D35 | E81: =E35 | F81: =F35 | G81: =G35 | H81: =H35 | I81: =I35 | J81: =J35 | ... V81: =V35
A82: Deferred tax liability | B82: $mm | C82: =MAX(0,'S&U_Opening'!$E$19+'Scenario_Drivers'!C57-C26+C27) | D82: =MAX(0,C82+'Scenario_Drivers'!D57-D26+D27) | E82: =MAX(0,D82+'Scenario_Drivers'!E57-E26+E27) | F82: =MAX(0,E82+'Scenario_Drivers'!F57-F26+F27) | G82: =MAX(0,F82+'Scenario_Drivers'!G57-G26+G27) | H82: =MAX(0,G82+'Scenario_Drivers'!H57-H26+H27) | I82: =MAX(0,H82+'Scenario_Drivers'!I57-I26+I27) | J82: =MAX(0,I82+'Scenario_Drivers'!J57-J26+J27) | K82: =MAX(0,J82+'Scenario_Drivers'!K57-K26+K27) | ... V82: =MAX(0,U82+'Scenario_Drivers'!V57-V26+V27)
A83: Other liabilities | B83: $mm | C83: ='S&U_Opening'!$E$20+'Scenario_Drivers'!C58 | D83: =C83+'Scenario_Drivers'!D58 | E83: =D83+'Scenario_Drivers'!E58 | F83: =E83+'Scenario_Drivers'!F58 | G83: =F83+'Scenario_Drivers'!G58 | H83: =G83+'Scenario_Drivers'!H58 | I83: =H83+'Scenario_Drivers'!I58 | J83: =I83+'Scenario_Drivers'!J58 | K83: =J83+'Scenario_Drivers'!K58 | ... V83: =U83+'Scenario_Drivers'!V58
A84: Total liabilities | B84: $mm | C84: =SUM(C76:C83) | D84: =SUM(D76:D83) | E84: =SUM(E76:E83) | F84: =SUM(F76:F83) | G84: =SUM(G76:G83) | H84: =SUM(H76:H83) | I84: =SUM(I76:I83) | J84: =SUM(J76:J83) | ... V84: =SUM(V76:V83)
A85: Equity | B85: $mm | C85: ='S&U_Opening'!$E$21+C28+C57 | D85: =C85+D28+D57 | E85: =D85+E28+E57 | F85: =E85+F28+F57 | G85: =F85+G28+G57 | H85: =G85+H28+H57 | I85: =H85+I28+I57 | J85: =I85+J28+J57 | K85: =J85+K28+K57 | ... V85: =U85+V28+V57
A86: Total liabilities & equity | B86: $mm | C86: =C84+C85 | D86: =D84+D85 | E86: =E84+E85 | F86: =F84+F85 | G86: =G84+G85 | H86: =H84+H85 | I86: =I84+I85 | J86: =J84+J85 | ... V86: =V84+V85
A87: Balance sheet check | B87: $mm | C87: =C75-C86 | D87: =D75-D86 | E87: =E75-E86 | F87: =F75-F86 | G87: =G75-G86 | H87: =H75-H86 | I87: =I75-I86 | J87: =J75-J86 | ... V87: =V75-V86
A88: Debt and Covenant Metrics
A89: Gross debt | B89: $mm | C89: =SUM(C76:C78) | D89: =SUM(D76:D78) | E89: =SUM(E76:E78) | F89: =SUM(F76:F78) | G89: =SUM(G76:G78) | H89: =SUM(H76:H78) | I89: =SUM(I76:I78) | J89: =SUM(J76:J78) | ... V89: =SUM(V76:V78)
A90: Eligible cash | B90: $mm | C90: =MIN(C67,Inputs!$B$19) | D90: =MIN(D67,Inputs!$B$19) | E90: =MIN(E67,Inputs!$B$19) | F90: =MIN(F67,Inputs!$B$19) | G90: =MIN(G67,Inputs!$B$19) | H90: =MIN(H67,Inputs!$B$19) | I90: =MIN(I67,Inputs!$B$19) | J90: =MIN(J67,Inputs!$B$19) | ... V90: =MIN(V67,Inputs!$B$19)
A91: Covenant net debt | B91: $mm | C91: =C89-C90 | D91: =D89-D90 | E91: =E89-E90 | F91: =F89-F90 | G91: =G89-G90 | H91: =H89-H90 | I91: =I89-I90 | J91: =J89-J90 | ... V91: =V89-V90
A92: Economic net debt | B92: $mm | C92: =C89-C67 | D92: =D89-D67 | E92: =E89-E67 | F92: =F89-F67 | G92: =G89-G67 | H92: =H89-H67 | I92: =I89-I67 | J92: =J89-J67 | ... V92: =V89-V67
A93: LTM revenue | B93: $mm | C93: =SUM(C5:C5) | D93: =SUM(C5:D5) | E93: =SUM(C5:E5) | F93: =SUM(C5:F5) | G93: =SUM(D5:G5) | H93: =SUM(E5:H5) | I93: =SUM(F5:I5) | J93: =SUM(G5:J5) | K93: =SUM(H5:K5) | L93: =SUM(I5:L5) | M93: =SUM(J5:M5) | ... V93: =SUM(S5:V5)
A94: LTM reported EBITDA | B94: $mm | C94: =SUM(C12:C12) | D94: =SUM(C12:D12) | E94: =SUM(C12:E12) | F94: =SUM(C12:F12) | G94: =SUM(D12:G12) | H94: =SUM(E12:H12) | I94: =SUM(F12:I12) | J94: =SUM(G12:J12) | K94: =SUM(H12:K12) | L94: =SUM(I12:L12) | M94: =SUM(J12:M12) | ... V94: =SUM(S12:V12)
A95: LTM firm EBITDA | B95: $mm | C95: =SUM(C10:C10) | D95: =SUM(C10:D10) | E95: =SUM(C10:E10) | F95: =SUM(C10:F10) | G95: =SUM(D10:G10) | H95: =SUM(E10:H10) | I95: =SUM(F10:I10) | J95: =SUM(G10:J10) | K95: =SUM(H10:K10) | L95: =SUM(I10:L10) | M95: =SUM(J10:M10) | ... V95: =SUM(S10:V10)
A96: LTM add-backs | B96: $mm | C96: =SUM(C13:C13) | D96: =SUM(C13:D13) | E96: =SUM(C13:E13) | F96: =SUM(C13:F13) | G96: =SUM(D13:G13) | H96: =SUM(E13:H13) | I96: =SUM(F13:I13) | J96: =SUM(G13:J13) | K96: =SUM(H13:K13) | L96: =SUM(I13:L13) | M96: =SUM(J13:M13) | ... V96: =SUM(S13:V13)
A97: LTM covenant EBITDA | B97: $mm | C97: =SUM(C14:C14) | D97: =SUM(C14:D14) | E97: =SUM(C14:E14) | F97: =SUM(C14:F14) | G97: =SUM(D14:G14) | H97: =SUM(E14:H14) | I97: =SUM(F14:I14) | J97: =SUM(G14:J14) | K97: =SUM(H14:K14) | L97: =SUM(I14:L14) | M97: =SUM(J14:M14) | ... V97: =SUM(S14:V14)
A98: Total net leverage | B98: x | C98: =C91/MAX(0.001,C97) | D98: =D91/MAX(0.001,D97) | E98: =E91/MAX(0.001,E97) | F98: =F91/MAX(0.001,F97) | G98: =G91/MAX(0.001,G97) | H98: =H91/MAX(0.001,H97) | I98: =I91/MAX(0.001,I97) | J98: =J91/MAX(0.001,J97) | ... V98: =V91/MAX(0.001,V97)
A99: Gross leverage | B99: x | C99: =C89/MAX(0.001,C95) | D99: =D89/MAX(0.001,D95) | E99: =E89/MAX(0.001,E95) | F99: =F89/MAX(0.001,F95) | G99: =G89/MAX(0.001,G95) | H99: =H89/MAX(0.001,H95) | I99: =I89/MAX(0.001,I95) | J99: =J89/MAX(0.001,J95) | ... V99: =V89/MAX(0.001,V95)
A100: Fixed charge coverage | B100: x | C100: =(C94-SUM(C27:C27)-SUM(C41:C41))/MAX(0.001,(-SUM(C22:C22)-SUM(C61:C61)-SUM(C62:C62))) | D100: =(D94-SUM(C27:D27)-SUM(C41:D41))/MAX(0.001,(-SUM(C22:D22)-SUM(C61:D61)-SUM(C62:D62))) | E100: =(E94-SUM(C27:E27)-SUM(C41:E41))/MAX(0.001,(-SUM(C22:E22)-SUM(C61:E61)-SUM(C62:E62))) | F100: =(F94-SUM(C27:F27)-SUM(C41:F41))/MAX(0.001,(-SUM(C22:F22)-SUM(C61:F61)-SUM(C62:F62))) | G100: =(G94-SUM(D27:G27)-SUM(D41:G41))/MAX(0.001,(-SUM(D22:G22)-SUM(D61:G61)-SUM(D62:G62))) | H100: =(H94-SUM(E27:H27)-SUM(E41:H41))/MAX(0.001,(-SUM(E22:H22)-SUM(E61:H61)-SUM(E62:H62))) | I100: =(I94-SUM(F27:I27)-SUM(F41:I41))/MAX(0.001,(-SUM(F22:I22)-SUM(F61:I61)-SUM(F62:I62))) | J100: =(J94-SUM(G27:J27)-SUM(G41:J41))/MAX(0.001,(-SUM(G22:J22)-SUM(G61:J61)-SUM(G62:J62))) | K100: =(K94-SUM(H27:K27)-SUM(H41:K41))/MAX(0.001,(-SUM(H22:K22)-SUM(H61:K61)-SUM(H62:K62))) | L100: =(L94-SUM(I27:L27)-SUM(I41:L41))/MAX(0.001,(-SUM(I22:L22)-SUM(I61:L61)-SUM(I62:L62))) | M100: =(M94-SUM(J27:M27)-SUM(J41:M41))/MAX(0.001,(-SUM(J22:M22)-SUM(J61:M61)-SUM(J62:M62))) | ... V100: =(V94-SUM(S27:V27)-SUM(S41:V41))/MAX(0.001,(-SUM(S22:V22)-SUM(S61:V61)-SUM(S62:V62)))
A101: Revolver availability | B101: $mm | C101: =MAX(0,Inputs!$B$20-C78-'Scenario_Drivers'!C62) | D101: =MAX(0,Inputs!$B$20-D78-'Scenario_Drivers'!D62) | E101: =MAX(0,Inputs!$B$20-E78-'Scenario_Drivers'!E62) | F101: =MAX(0,Inputs!$B$20-F78-'Scenario_Drivers'!F62) | G101: =MAX(0,Inputs!$B$20-G78-'Scenario_Drivers'!G62) | H101: =MAX(0,Inputs!$B$20-H78-'Scenario_Drivers'!H62) | I101: =MAX(0,Inputs!$B$20-I78-'Scenario_Drivers'!I62) | J101: =MAX(0,Inputs!$B$20-J78-'Scenario_Drivers'!J62) | ... V101: =MAX(0,Inputs!$B$20-V78-'Scenario_Drivers'!V62)
...

Sheet SB_Up
A1: Project Keystone - Standalone Upside Quarterly LBO ($mm)
A3: Line Item | B3: Unit | C3: 46203 | D3: 46295 | E3: 46387 | F3: 46477 | G3: 46568 | H3: 46660 | I3: 46752 | J3: 46843 | K3: 46934 | L3: 47026 | M3: 47118 | N3: 47208 | O3: 47299 | P3: 47391 | Q3: 47483 | R3: 47573 | S3: 47664 | T3: 47756 | U3: 47848 | V3: 47938
A4: Operating Model
A5: Revenue | B5: $mm | C5: ='Scenario_Drivers'!C73 | D5: ='Scenario_Drivers'!D73 | E5: ='Scenario_Drivers'!E73 | F5: ='Scenario_Drivers'!F73 | G5: ='Scenario_Drivers'!G73 | H5: ='Scenario_Drivers'!H73 | I5: ='Scenario_Drivers'!I73 | J5: ='Scenario_Drivers'!J73 | ... V5: ='Scenario_Drivers'!V73
A6: Growth | B6: % | C6: =C5/(74.0*'Scenario_Drivers'!C104)-1 | D6: =D5/C5-1 | E6: =E5/D5-1 | F6: =F5/V5-1 | G6: =G5/F5-1 | H6: =H5/G5-1 | I6: =I5/H5-1 | J6: =J5/F5-1 | K6: =K5/J5-1 | L6: =L5/K5-1 | M6: =M5/L5-1 | N6: =N5/J5-1 | O6: =O5/N5-1 | P6: =P5/O5-1 | Q6: =Q5/P5-1 | R6: =R5/N5-1 | S6: =S5/R5-1 | T6: =T5/S5-1 | U6: =U5/T5-1 | V6: =V5/R5-1
A7: Gross margin | B7: % | C7: ='Scenario_Drivers'!C74 | D7: ='Scenario_Drivers'!D74 | E7: ='Scenario_Drivers'!E74 | F7: ='Scenario_Drivers'!F74 | G7: ='Scenario_Drivers'!G74 | H7: ='Scenario_Drivers'!H74 | I7: ='Scenario_Drivers'!I74 | J7: ='Scenario_Drivers'!J74 | ... V7: ='Scenario_Drivers'!V74
A8: Gross profit | B8: $mm | C8: =C5*C7 | D8: =D5*D7 | E8: =E5*E7 | F8: =F5*F7 | G8: =G5*G7 | H8: =H5*H7 | I8: =I5*I7 | J8: =J5*J7 | ... V8: =V5*V7
A9: COGS | B9: $mm | C9: =-(C5-C8) | D9: =-(D5-D8) | E9: =-(E5-E8) | F9: =-(F5-F8) | G9: =-(G5-G8) | H9: =-(H5-H8) | I9: =-(I5-I8) | J9: =-(J5-J8) | ... V9: =-(V5-V8)
A10: Firm EBITDA | B10: $mm | C10: ='Scenario_Drivers'!C75 | D10: ='Scenario_Drivers'!D75 | E10: ='Scenario_Drivers'!E75 | F10: ='Scenario_Drivers'!F75 | G10: ='Scenario_Drivers'!G75 | H10: ='Scenario_Drivers'!H75 | I10: ='Scenario_Drivers'!I75 | J10: ='Scenario_Drivers'!J75 | ... V10: ='Scenario_Drivers'!V75
A11: One-time charges | B11: $mm | C11: =-'Scenario_Drivers'!C76 | D11: =-'Scenario_Drivers'!D76 | E11: =-'Scenario_Drivers'!E76 | F11: =-'Scenario_Drivers'!F76 | G11: =-'Scenario_Drivers'!G76 | H11: =-'Scenario_Drivers'!H76 | I11: =-'Scenario_Drivers'!I76 | J11: =-'Scenario_Drivers'!J76 | ... V11: =-'Scenario_Drivers'!V76
A12: Reported EBITDA | B12: $mm | C12: =C10+C11 | D12: =D10+D11 | E12: =E10+E11 | F12: =F10+F11 | G12: =G10+G11 | H12: =H10+H11 | I12: =I10+I11 | J12: =J10+J11 | ... V12: =V10+V11
A13: Covenant add-backs | B13: $mm | C13: ='Scenario_Drivers'!C77 | D13: ='Scenario_Drivers'!D77 | E13: ='Scenario_Drivers'!E77 | F13: ='Scenario_Drivers'!F77 | G13: ='Scenario_Drivers'!G77 | H13: ='Scenario_Drivers'!H77 | I13: ='Scenario_Drivers'!I77 | J13: ='Scenario_Drivers'!J77 | ... V13: ='Scenario_Drivers'!V77
A14: Covenant EBITDA | B14: $mm | C14: =C12+C13 | D14: =D12+D13 | E14: =E12+E13 | F14: =F12+F13 | G14: =G12+G13 | H14: =H12+H13 | I14: =I12+I13 | J14: =J12+J13 | ... V14: =V12+V13
A15: Firm EBITDA margin | B15: % | C15: =C10/C5 | D15: =D10/D5 | E15: =E10/E5 | F15: =F10/F5 | G15: =G10/G5 | H15: =H10/H5 | I15: =I10/I5 | J15: =J10/J5 | ... V15: =V10/V5
A16: Income Statement
A17: Depreciation | B17: $mm | C17: =C5*Inputs!$B$17 | D17: =D5*Inputs!$B$17 | E17: =E5*Inputs!$B$17 | F17: =F5*Inputs!$B$17 | G17: =G5*Inputs!$B$17 | H17: =H5*Inputs!$B$17 | I17: =I5*Inputs!$B$17 | J17: =J5*Inputs!$B$17 | ... V17: =V5*Inputs!$B$17
A18: Core PPA amortization | B18: $mm | C18: ='Scenario_Drivers'!C103 | D18: ='Scenario_Drivers'!D103 | E18: ='Scenario_Drivers'!E103 | F18: ='Scenario_Drivers'!F103 | G18: ='Scenario_Drivers'!G103 | H18: ='Scenario_Drivers'!H103 | I18: ='Scenario_Drivers'!I103 | J18: ='Scenario_Drivers'!J103 | ... V18: ='Scenario_Drivers'!V103
A19: Integration asset amortization | B19: $mm | C19: =0 | D19: =0 | E19: =0 | F19: =0 | G19: =0 | H19: =0 | I19: =0 | J19: =0 | ... V19: =0
A20: Total D&A | B20: $mm | C20: =SUM(C17:C19) | D20: =SUM(D17:D19) | E20: =SUM(E17:E19) | F20: =SUM(F17:F19) | G20: =SUM(G17:G19) | H20: =SUM(H17:H19) | I20: =SUM(I17:I19) | J20: =SUM(J17:J19) | ... V20: =SUM(V17:V19)
A21: EBIT | B21: $mm | C21: =C12-C20 | D21: =D12-D20 | E21: =E12-E20 | F21: =F12-F20 | G21: =G12-G20 | H21: =H12-H20 | I21: =I12-I20 | J21: =J12-J20 | ... V21: =V12-V20
A22: Cash interest | B22: $mm | C22: =-((('S&U_Opening'!$E$18+MAX(0,'S&U_Opening'!$E$18-(MIN(0.107,'S&U_Opening'!$E$18))))/2)*(MAX('Scenario_Drivers'!C101,Inputs!$B$26)+Inputs!$B$23+'Scenario_Drivers'!C102)/4+((0+0+'Scenario_Drivers'!C93-(IF(0>0,MIN(0.015,0),0)))/2)*(MAX('Scenario_Drivers'!C101,Inputs!$B$26)+Inputs!$B$25+'Scenario_Drivers'!C102)/4+0*(MAX('Scenario_Drivers'!C101,Inputs!$B$26)+Inputs!$B$24+'Scenario_Drivers'!C102)/4+MAX(0,Inputs!$B$20-0-'Scenario_Drivers'!C96)*Inputs!$B$29/4+0) | D22: =-(((C76+MAX(0,C76-(MIN(0.107,C76))))/2)*(MAX('Scenario_Drivers'!D101,Inputs!$B$26)+Inputs!$B$23+'Scenario_Drivers'!D102)/4+((C77+C77+'Scenario_Drivers'!D93-(IF(C77>0,MIN(0.015,C77),0)))/2)*(MAX('Scenario_Drivers'!D101,Inputs!$B$26)+Inputs!$B$25+'Scenario_Drivers'!D102)/4+C78*(MAX('Scenario_Drivers'!D101,Inputs!$B$26)+Inputs!$B$24+'Scenario_Drivers'!D102)/4+MAX(0,Inputs!$B$20-C78-'Scenario_Drivers'!D96)*Inputs!$B$29/4+MAX(0,Inputs!$B$21-C77-'Scenario_Drivers'!D93)*Inputs!$B$30/4) | E22: =-(((D76+MAX(0,D76-(MIN(0.107,D76))))/2)*(MAX('Scenario_Drivers'!E101,Inputs!$B$26)+Inputs!$B$23+'Scenario_Drivers'!E102)/4+((D77+D77+'Scenario_Drivers'!E93-(IF(D77>0,MIN(0.015,D77),0)))/2)*(MAX('Scenario_Drivers'!E101,Inputs!$B$26)+Inputs!$B$25+'Scenario_Drivers'!E102)/4+D78*(MAX('Scenario_Drivers'!E101,Inputs!$B$26)+Inputs!$B$24+'Scenario_Drivers'!E102)/4+MAX(0,Inputs!$B$20-D78-'Scenario_Drivers'!E96)*Inputs!$B$29/4+MAX(0,Inputs!$B$21-D77-'Scenario_Drivers'!E93)*Inputs!$B$30/4) | F22: =-(((E76+MAX(0,E76-(MIN(0.107,E76))))/2)*(MAX('Scenario_Drivers'!F101,Inputs!$B$26)+Inputs!$B$23+'Scenario_Drivers'!F102)/4+((E77+E77+'Scenario_Drivers'!F93-(IF(E77>0,MIN(0.015,E77),0)))/2)*(MAX('Scenario_Drivers'!F101,Inputs!$B$26)+Inputs!$B$25+'Scenario_Drivers'!F102)/4+E78*(MAX('Scenario_Drivers'!F101,Inputs!$B$26)+Inputs!$B$24+'Scenario_Drivers'!F102)/4+MAX(0,Inputs!$B$20-E78-'Scenario_Drivers'!F96)*Inputs!$B$29/4+MAX(0,Inputs!$B$21-E77-'Scenario_Drivers'!F93)*Inputs!$B$30/4) | G22: =-(((F76+MAX(0,F76-(MIN(0.107,F76))))/2)*(MAX('Scenario_Drivers'!G101,Inputs!$B$26)+Inputs!$B$23+'Scenario_Drivers'!G102)/4+((F77+F77+'Scenario_Drivers'!G93-(IF(F77>0,MIN(0.015,F77),0)))/2)*(MAX('Scenario_Drivers'!G101,Inputs!$B$26)+Inputs!$B$25+'Scenario_Drivers'!G102)/4+F78*(MAX('Scenario_Drivers'!G101,Inputs!$B$26)+Inputs!$B$24+'Scenario_Drivers'!G102)/4+MAX(0,Inputs!$B$20-F78-'Scenario_Drivers'!G96)*Inputs!$B$29/4+MAX(0,Inputs!$B$21-F77-'Scenario_Drivers'!G93)*Inputs!$B$30/4) | H22: =-(((G76+MAX(0,G76-(MIN(0.107,G76))))/2)*(MAX('Scenario_Drivers'!H101,Inputs!$B$26)+Inputs!$B$23+'Scenario_Drivers'!H102)/4+((G77+G77+'Scenario_Drivers'!H93-(IF(G77>0,MIN(0.015,G77),0)))/2)*(MAX('Scenario_Drivers'!H101,Inputs!$B$26)+Inputs!$B$25+'Scenario_Drivers'!H102)/4+G78*(MAX('Scenario_Drivers'!H101,Inputs!$B$26)+Inputs!$B$24+'Scenario_Drivers'!H102)/4+MAX(0,Inputs!$B$20-G78-'Scenario_Drivers'!H96)*Inputs!$B$29/4+MAX(0,Inputs!$B$21-G77-'Scenario_Drivers'!H93)*Inputs!$B$30/4) | I22: =-(((H76+MAX(0,H76-(MIN(0.107,H76))))/2)*(MAX('Scenario_Drivers'!I101,Inputs!$B$26)+Inputs!$B$23+'Scenario_Drivers'!I102)/4+((H77+H77+'Scenario_Drivers'!I93-(IF(H77>0,MIN(0.015,H77),0)))/2)*(MAX('Scenario_Drivers'!I101,Inputs!$B$26)+Inputs!$B$25+'Scenario_Drivers'!I102)/4+H78*(MAX('Scenario_Drivers'!I101,Inputs!$B$26)+Inputs!$B$24+'Scenario_Drivers'!I102)/4+MAX(0,Inputs!$B$20-H78-'Scenario_Drivers'!I96)*Inputs!$B$29/4+0) | J22: =-(((I76+MAX(0,I76-(MIN(0.107,I76))))/2)*(MAX('Scenario_Drivers'!J101,Inputs!$B$26)+Inputs!$B$23+'Scenario_Drivers'!J102)/4+((I77+I77+'Scenario_Drivers'!J93-(IF(I77>0,MIN(0.015,I77),0)))/2)*(MAX('Scenario_Drivers'!J101,Inputs!$B$26)+Inputs!$B$25+'Scenario_Drivers'!J102)/4+I78*(MAX('Scenario_Drivers'!J101,Inputs!$B$26)+Inputs!$B$24+'Scenario_Drivers'!J102)/4+MAX(0,Inputs!$B$20-I78-'Scenario_Drivers'!J96)*Inputs!$B$29/4+0) | K22: =-(((J76+MAX(0,J76-(MIN(0.107,J76))))/2)*(MAX('Scenario_Drivers'!K101,Inputs!$B$26)+Inputs!$B$23+'Scenario_Drivers'!K102)/4+((J77+J77+'Scenario_Drivers'!K93-(IF(J77>0,MIN(0.015,J77),0)))/2)*(MAX('Scenario_Drivers'!K101,Inputs!$B$26)+Inputs!$B$25+'Scenario_Drivers'!K102)/4+J78*(MAX('Scenario_Drivers'!K101,Inputs!$B$26)+Inputs!$B$24+'Scenario_Drivers'!K102)/4+MAX(0,Inputs!$B$20-J78-'Scenario_Drivers'!K96)*Inputs!$B$29/4+0) | L22: =-(((K76+MAX(0,K76-(MIN(0.107,K76))))/2)*(MAX('Scenario_Drivers'!L101,Inputs!$B$26)+Inputs!$B$23+'Scenario_Drivers'!L102)/4+((K77+K77+'Scenario_Drivers'!L93-(IF(K77>0,MIN(0.015,K77),0)))/2)*(MAX('Scenario_Drivers'!L101,Inputs!$B$26)+Inputs!$B$25+'Scenario_Drivers'!L102)/4+K78*(MAX('Scenario_Drivers'!L101,Inputs!$B$26)+Inputs!$B$24+'Scenario_Drivers'!L102)/4+MAX(0,Inputs!$B$20-K78-'Scenario_Drivers'!L96)*Inputs!$B$29/4+0) | M22: =-(((L76+MAX(0,L76-(MIN(0.107,L76))))/2)*(MAX('Scenario_Drivers'!M101,Inputs!$B$26)+Inputs!$B$23+'Scenario_Drivers'!M102)/4+((L77+L77+'Scenario_Drivers'!M93-(IF(L77>0,MIN(0.015,L77),0)))/2)*(MAX('Scenario_Drivers'!M101,Inputs!$B$26)+Inputs!$B$25+'Scenario_Drivers'!M102)/4+L78*(MAX('Scenario_Drivers'!M101,Inputs!$B$26)+Inputs!$B$24+'Scenario_Drivers'!M102)/4+MAX(0,Inputs!$B$20-L78-'Scenario_Drivers'!M96)*Inputs!$B$29/4+0) | N22: =-(((M76+MAX(0,M76-(MIN(0.107,M76))))/2)*(MAX('Scenario_Drivers'!N101,Inputs!$B$26)+Inputs!$B$23+'Scenario_Drivers'!N102)/4+((M77+M77+'Scenario_Drivers'!N93-(IF(M77>0,MIN(0.015,M77),0)))/2)*(MAX('Scenario_Drivers'!N101,Inputs!$B$26)+Inputs!$B$25+'Scenario_Drivers'!N102)/4+M78*(MAX('Scenario_Drivers'!N101,Inputs!$B$26)+Inputs!$B$24+'Scenario_Drivers'!N102)/4+MAX(0,Inputs!$B$20-M78-'Scenario_Drivers'!N96)*Inputs!$B$29/4+0) | O22: =-(((N76+MAX(0,N76-(MIN(0.107,N76))))/2)*(MAX('Scenario_Drivers'!O101,Inputs!$B$26)+Inputs!$B$23+'Scenario_Drivers'!O102)/4+((N77+N77+'Scenario_Drivers'!O93-(IF(N77>0,MIN(0.015,N77),0)))/2)*(MAX('Scenario_Drivers'!O101,Inputs!$B$26)+Inputs!$B$25+'Scenario_Drivers'!O102)/4+N78*(MAX('Scenario_Drivers'!O101,Inputs!$B$26)+Inputs!$B$24+'Scenario_Drivers'!O102)/4+MAX(0,Inputs!$B$20-N78-'Scenario_Drivers'!O96)*Inputs!$B$29/4+0) | P22: =-(((O76+MAX(0,O76-(MIN(0.107,O76))))/2)*(MAX('Scenario_Drivers'!P101,Inputs!$B$26)+Inputs!$B$23+'Scenario_Drivers'!P102)/4+((O77+O77+'Scenario_Drivers'!P93-(IF(O77>0,MIN(0.015,O77),0)))/2)*(MAX('Scenario_Drivers'!P101,Inputs!$B$26)+Inputs!$B$25+'Scenario_Drivers'!P102)/4+O78*(MAX('Scenario_Drivers'!P101,Inputs!$B$26)+Inputs!$B$24+'Scenario_Drivers'!P102)/4+MAX(0,Inputs!$B$20-O78-'Scenario_Drivers'!P96)*Inputs!$B$29/4+0) | ... V22: =-(((U76+MAX(0,U76-(MIN(0.107,U76))))/2)*(MAX('Scenario_Drivers'!V101,Inputs!$B$26)+Inputs!$B$23+'Scenario_Drivers'!V102)/4+((U77+U77+'Scenario_Drivers'!V93-(IF(U77>0,MIN(0.015,U77),0)))/2)*(MAX('Scenario_Drivers'!V101,Inputs!$B$26)+Inputs!$B$25+'Scenario_Drivers'!V102)/4+U78*(MAX('Scenario_Drivers'!V101,Inputs!$B$26)+Inputs!$B$24+'Scenario_Drivers'!V102)/4+MAX(0,Inputs!$B$20-U78-'Scenario_Drivers'!V96)*Inputs!$B$29/4+0)
A23: Financing fee amortization | B23: $mm | C23: =MIN('S&U_Opening'!$B$24,1.4/24) | D23: =MIN(C73,1.4/24) | E23: =MIN(D73,1.4/24) | F23: =MIN(E73,1.4/24) | G23: =MIN(F73,1.4/24) | H23: =MIN(G73,1.4/24) | I23: =MIN(H73,1.4/24) | J23: =MIN(I73,1.4/24) | K23: =MIN(J73,1.4/24) | ... V23: =MIN(U73,1.4/24)
A24: Interest income | B24: $mm | C24: ='S&U_Opening'!$B$15*1.0%/4 | D24: =C67*1.0%/4 | E24: =D67*1.0%/4 | F24: =E67*1.0%/4 | G24: =F67*1.0%/4 | H24: =G67*1.0%/4 | I24: =H67*1.0%/4 | J24: =I67*1.0%/4 | K24: =J67*1.0%/4 | ... V24: =U67*1.0%/4
A25: Pre-tax income | B25: $mm | C25: =C21+C22-C23+C24 | D25: =D21+D22-D23+D24 | E25: =E21+E22-E23+E24 | F25: =F21+F22-F23+F24 | G25: =G21+G22-G23+G24 | H25: =H21+H22-H23+H24 | I25: =I21+I22-I23+I24 | J25: =J21+J22-J23+J24 | ... V25: =V21+V22-V23+V24
A26: Book tax expense | B26: $mm | C26: =-MAX(0,C25*Inputs!$B$15) | D26: =-MAX(0,D25*Inputs!$B$15) | E26: =-MAX(0,E25*Inputs!$B$15) | F26: =-MAX(0,F25*Inputs!$B$15) | G26: =-MAX(0,G25*Inputs!$B$15) | H26: =-MAX(0,H25*Inputs!$B$15) | I26: =-MAX(0,I25*Inputs!$B$15) | J26: =-MAX(0,J25*Inputs!$B$15) | ... V26: =-MAX(0,V25*Inputs!$B$15)
A27: Cash taxes | B27: $mm | C27: =-MAX(0,(C116-0)*Inputs!$B$15) | D27: =-MAX(0,(D116-C115)*Inputs!$B$15) | E27: =-MAX(0,(E116-D115)*Inputs!$B$15) | F27: =-MAX(0,(F116-E115)*Inputs!$B$15) | G27: =-MAX(0,(G116-F115)*Inputs!$B$15) | H27: =-MAX(0,(H116-G115)*Inputs!$B$15) | I27: =-MAX(0,(I116-H115)*Inputs!$B$15) | J27: =-MAX(0,(J116-I115)*Inputs!$B$15) | K27: =-MAX(0,(K116-J115)*Inputs!$B$15) | ... V27: =-MAX(0,(V116-U115)*Inputs!$B$15)
A28: Net income | B28: $mm | C28: =C25+C26 | D28: =D25+D26 | E28: =E25+E26 | F28: =F25+F26 | G28: =G25+G26 | H28: =H25+H26 | I28: =I25+I26 | J28: =J25+J26 | ... V28: =V25+V26
A29: Working Capital and Capital Expenditure
A30: Accounts receivable | B30: $mm | C30: =(C5/'Scenario_Drivers'!C104)*'Scenario_Drivers'!C78/365 | D30: =(D5/'Scenario_Drivers'!D104)*'Scenario_Drivers'!D78/365 | E30: =(E5/'Scenario_Drivers'!E104)*'Scenario_Drivers'!E78/365 | F30: =(F5/'Scenario_Drivers'!F104)*'Scenario_Drivers'!F78/365 | G30: =(G5/'Scenario_Drivers'!G104)*'Scenario_Drivers'!G78/365 | H30: =(H5/'Scenario_Drivers'!H104)*'Scenario_Drivers'!H78/365 | I30: =(I5/'Scenario_Drivers'!I104)*'Scenario_Drivers'!I78/365 | J30: =(J5/'Scenario_Drivers'!J104)*'Scenario_Drivers'!J78/365 | ... V30: =(V5/'Scenario_Drivers'!V104)*'Scenario_Drivers'!V78/365
A31: Unbilled WIP | B31: $mm | C31: =(C5/'Scenario_Drivers'!C104)*'Scenario_Drivers'!C79 | D31: =(D5/'Scenario_Drivers'!D104)*'Scenario_Drivers'!D79 | E31: =(E5/'Scenario_Drivers'!E104)*'Scenario_Drivers'!E79 | F31: =(F5/'Scenario_Drivers'!F104)*'Scenario_Drivers'!F79 | G31: =(G5/'Scenario_Drivers'!G104)*'Scenario_Drivers'!G79 | H31: =(H5/'Scenario_Drivers'!H104)*'Scenario_Drivers'!H79 | I31: =(I5/'Scenario_Drivers'!I104)*'Scenario_Drivers'!I79 | J31: =(J5/'Scenario_Drivers'!J104)*'Scenario_Drivers'!J79 | ... V31: =(V5/'Scenario_Drivers'!V104)*'Scenario_Drivers'!V79
A32: Prepaids | B32: $mm | C32: =(C5/'Scenario_Drivers'!C104)*'Scenario_Drivers'!C80 | D32: =(D5/'Scenario_Drivers'!D104)*'Scenario_Drivers'!D80 | E32: =(E5/'Scenario_Drivers'!E104)*'Scenario_Drivers'!E80 | F32: =(F5/'Scenario_Drivers'!F104)*'Scenario_Drivers'!F80 | G32: =(G5/'Scenario_Drivers'!G104)*'Scenario_Drivers'!G80 | H32: =(H5/'Scenario_Drivers'!H104)*'Scenario_Drivers'!H80 | I32: =(I5/'Scenario_Drivers'!I104)*'Scenario_Drivers'!I80 | J32: =(J5/'Scenario_Drivers'!J104)*'Scenario_Drivers'!J80 | ... V32: =(V5/'Scenario_Drivers'!V104)*'Scenario_Drivers'!V80
A33: Accounts payable | B33: $mm | C33: =(C5/'Scenario_Drivers'!C104)*'Scenario_Drivers'!C81 | D33: =(D5/'Scenario_Drivers'!D104)*'Scenario_Drivers'!D81 | E33: =(E5/'Scenario_Drivers'!E104)*'Scenario_Drivers'!E81 | F33: =(F5/'Scenario_Drivers'!F104)*'Scenario_Drivers'!F81 | G33: =(G5/'Scenario_Drivers'!G104)*'Scenario_Drivers'!G81 | H33: =(H5/'Scenario_Drivers'!H104)*'Scenario_Drivers'!H81 | I33: =(I5/'Scenario_Drivers'!I104)*'Scenario_Drivers'!I81 | J33: =(J5/'Scenario_Drivers'!J104)*'Scenario_Drivers'!J81 | ... V33: =(V5/'Scenario_Drivers'!V104)*'Scenario_Drivers'!V81
A34: Accrued liabilities | B34: $mm | C34: =(C5/'Scenario_Drivers'!C104)*'Scenario_Drivers'!C82 | D34: =(D5/'Scenario_Drivers'!D104)*'Scenario_Drivers'!D82 | E34: =(E5/'Scenario_Drivers'!E104)*'Scenario_Drivers'!E82 | F34: =(F5/'Scenario_Drivers'!F104)*'Scenario_Drivers'!F82 | G34: =(G5/'Scenario_Drivers'!G104)*'Scenario_Drivers'!G82 | H34: =(H5/'Scenario_Drivers'!H104)*'Scenario_Drivers'!H82 | I34: =(I5/'Scenario_Drivers'!I104)*'Scenario_Drivers'!I82 | J34: =(J5/'Scenario_Drivers'!J104)*'Scenario_Drivers'!J82 | ... V34: =(V5/'Scenario_Drivers'!V104)*'Scenario_Drivers'!V82
A35: Deferred revenue | B35: $mm | C35: =(C5/'Scenario_Drivers'!C104)*'Scenario_Drivers'!C83 | D35: =(D5/'Scenario_Drivers'!D104)*'Scenario_Drivers'!D83 | E35: =(E5/'Scenario_Drivers'!E104)*'Scenario_Drivers'!E83 | F35: =(F5/'Scenario_Drivers'!F104)*'Scenario_Drivers'!F83 | G35: =(G5/'Scenario_Drivers'!G104)*'Scenario_Drivers'!G83 | H35: =(H5/'Scenario_Drivers'!H104)*'Scenario_Drivers'!H83 | I35: =(I5/'Scenario_Drivers'!I104)*'Scenario_Drivers'!I83 | J35: =(J5/'Scenario_Drivers'!J104)*'Scenario_Drivers'!J83 | ... V35: =(V5/'Scenario_Drivers'!V104)*'Scenario_Drivers'!V83
A36: Operating NWC | B36: $mm | C36: =C30+C31+C32-C33-C34-C35 | D36: =D30+D31+D32-D33-D34-D35 | E36: =E30+E31+E32-E33-E34-E35 | F36: =F30+F31+F32-F33-F34-F35 | G36: =G30+G31+G32-G33-G34-G35 | H36: =H30+H31+H32-H33-H34-H35 | I36: =I30+I31+I32-I33-I34-I35 | J36: =J30+J31+J32-J33-J34-J35 | ... V36: =V30+V31+V32-V33-V34-V35
A37: Acquired NWC | B37: $mm | C37: ='Scenario_Drivers'!C85 | D37: ='Scenario_Drivers'!D85 | E37: ='Scenario_Drivers'!E85 | F37: ='Scenario_Drivers'!F85 | G37: ='Scenario_Drivers'!G85 | H37: ='Scenario_Drivers'!H85 | I37: ='Scenario_Drivers'!I85 | J37: ='Scenario_Drivers'!J85 | ... V37: ='Scenario_Drivers'!V85
A38: Organic change in NWC | B38: $mm | C38: =C36-('S&U_Opening'!$B$16+'S&U_Opening'!$B$17+'S&U_Opening'!$B$18-'S&U_Opening'!$E$15-'S&U_Opening'!$E$16-'S&U_Opening'!$E$17)-C37 | D38: =D36-(C36)-D37 | E38: =E36-(D36)-E37 | F38: =F36-(E36)-F37 | G38: =G36-(F36)-G37 | H38: =H36-(G36)-H37 | I38: =I36-(H36)-I37 | J38: =J36-(I36)-J37 | K38: =K36-(J36)-K37 | ... V38: =V36-(U36)-V37
A39: Maintenance capex | B39: $mm | C39: =C5*'Scenario_Drivers'!C84*Inputs!$B$18 | D39: =D5*'Scenario_Drivers'!D84*Inputs!$B$18 | E39: =E5*'Scenario_Drivers'!E84*Inputs!$B$18 | F39: =F5*'Scenario_Drivers'!F84*Inputs!$B$18 | G39: =G5*'Scenario_Drivers'!G84*Inputs!$B$18 | H39: =H5*'Scenario_Drivers'!H84*Inputs!$B$18 | I39: =I5*'Scenario_Drivers'!I84*Inputs!$B$18 | J39: =J5*'Scenario_Drivers'!J84*Inputs!$B$18 | ... V39: =V5*'Scenario_Drivers'!V84*Inputs!$B$18
A40: Growth capex | B40: $mm | C40: =C5*'Scenario_Drivers'!C84*(1-Inputs!$B$18) | D40: =D5*'Scenario_Drivers'!D84*(1-Inputs!$B$18) | E40: =E5*'Scenario_Drivers'!E84*(1-Inputs!$B$18) | F40: =F5*'Scenario_Drivers'!F84*(1-Inputs!$B$18) | G40: =G5*'Scenario_Drivers'!G84*(1-Inputs!$B$18) | H40: =H5*'Scenario_Drivers'!H84*(1-Inputs!$B$18) | I40: =I5*'Scenario_Drivers'!I84*(1-Inputs!$B$18) | J40: =J5*'Scenario_Drivers'!J84*(1-Inputs!$B$18) | ... V40: =V5*'Scenario_Drivers'!V84*(1-Inputs!$B$18)
A41: Total capex | B41: $mm | C41: =SUM(C39:C40) | D41: =SUM(D39:D40) | E41: =SUM(E39:E40) | F41: =SUM(F39:F40) | G41: =SUM(G39:G40) | H41: =SUM(H39:H40) | I41: =SUM(I39:I40) | J41: =SUM(J39:J40) | ... V41: =SUM(V39:V40)
A42: Acquired PP&E | B42: $mm | C42: ='Scenario_Drivers'!C86 | D42: ='Scenario_Drivers'!D86 | E42: ='Scenario_Drivers'!E86 | F42: ='Scenario_Drivers'!F86 | G42: ='Scenario_Drivers'!G86 | H42: ='Scenario_Drivers'!H86 | I42: ='Scenario_Drivers'!I86 | J42: ='Scenario_Drivers'!J86 | ... V42: ='Scenario_Drivers'!V86
A43: Acquisition EV | B43: $mm | C43: ='Scenario_Drivers'!C87 | D43: ='Scenario_Drivers'!D87 | E43: ='Scenario_Drivers'!E87 | F43: ='Scenario_Drivers'!F87 | G43: ='Scenario_Drivers'!G87 | H43: ='Scenario_Drivers'!H87 | I43: ='Scenario_Drivers'!I87 | J43: ='Scenario_Drivers'!J87 | ... V43: ='Scenario_Drivers'!V87
A44: Acquisition fees | B44: $mm | C44: ='Scenario_Drivers'!C88 | D44: ='Scenario_Drivers'!D88 | E44: ='Scenario_Drivers'!E88 | F44: ='Scenario_Drivers'!F88 | G44: ='Scenario_Drivers'!G88 | H44: ='Scenario_Drivers'!H88 | I44: ='Scenario_Drivers'!I88 | J44: ='Scenario_Drivers'!J88 | ... V44: ='Scenario_Drivers'!V88
A45: Capitalized integration spend | B45: $mm | C45: ='Scenario_Drivers'!C95 | D45: ='Scenario_Drivers'!D95 | E45: ='Scenario_Drivers'!E95 | F45: ='Scenario_Drivers'!F95 | G45: ='Scenario_Drivers'!G95 | H45: ='Scenario_Drivers'!H95 | I45: ='Scenario_Drivers'!I95 | J45: ='Scenario_Drivers'!J95 | ... V45: ='Scenario_Drivers'!V95
A46: Cash Flow Statement
A47: Net income - CF | B47: $mm | C47: =C28 | D47: =D28 | E47: =E28 | F47: =F28 | G47: =G28 | H47: =H28 | I47: =I28 | J47: =J28 | ... V47: =V28
A48: Total D&A - CF | B48: $mm | C48: =C20 | D48: =D20 | E48: =E20 | F48: =F20 | G48: =G20 | H48: =H20 | I48: =I20 | J48: =J20 | ... V48: =V20
A49: Financing fee amortization - CF | B49: $mm | C49: =C23 | D49: =D23 | E49: =E23 | F49: =F23 | G49: =G23 | H49: =H23 | I49: =I23 | J49: =J23 | ... V49: =V23
A50: Deferred tax / non-cash tax | B50: $mm | C50: =-C26+C27 | D50: =-D26+D27 | E50: =-E26+E27 | F50: =-F26+F27 | G50: =-G26+G27 | H50: =-H26+H27 | I50: =-I26+I27 | J50: =-J26+J27 | ... V50: =-V26+V27
A51: Change in NWC - CF | B51: $mm | C51: =-C38 | D51: =-D38 | E51: =-E38 | F51: =-F38 | G51: =-G38 | H51: =-H38 | I51: =-I38 | J51: =-J38 | ... V51: =-V38
A52: Cash from operations | B52: $mm | C52: =SUM(C47:C51) | D52: =SUM(D47:D51) | E52: =SUM(E47:E51) | F52: =SUM(F47:F51) | G52: =SUM(G47:G51) | H52: =SUM(H47:H51) | I52: =SUM(I47:I51) | J52: =SUM(J47:J51) | ... V52: =SUM(V47:V51)
A53: Capital expenditure - CF | B53: $mm | C53: =-C41 | D53: =-D41 | E53: =-E41 | F53: =-F41 | G53: =-G41 | H53: =-H41 | I53: =-I41 | J53: =-J41 | ... V53: =-V41
A54: Acquisition EV - CF | B54: $mm | C54: =-C43 | D54: =-D43 | E54: =-E43 | F54: =-F43 | G54: =-G43 | H54: =-H43 | I54: =-I43 | J54: =-J43 | ... V54: =-V43
A55: Capitalized integration spend - CF | B55: $mm | C55: =-C45 | D55: =-D45 | E55: =-E45 | F55: =-F45 | G55: =-G45 | H55: =-H45 | I55: =-I45 | J55: =-J45 | ... V55: =-V45
A56: Cash from investing | B56: $mm | C56: =SUM(C53:C55) | D56: =SUM(D53:D55) | E56: =SUM(E53:E55) | F56: =SUM(F53:F55) | G56: =SUM(G53:G55) | H56: =SUM(H53:H55) | I56: =SUM(I53:I55) | J56: =SUM(J53:J55) | ... V56: =SUM(V53:V55)
A57: Sponsor equity contribution | B57: $mm | C57: ='Scenario_Drivers'!C94 | D57: ='Scenario_Drivers'!D94 | E57: ='Scenario_Drivers'!E94 | F57: ='Scenario_Drivers'!F94 | G57: ='Scenario_Drivers'!G94 | H57: ='Scenario_Drivers'!H94 | I57: ='Scenario_Drivers'!I94 | J57: ='Scenario_Drivers'!J94 | ... V57: ='Scenario_Drivers'!V94
A58: DDTL draw | B58: $mm | C58: ='Scenario_Drivers'!C93 | D58: ='Scenario_Drivers'!D93 | E58: ='Scenario_Drivers'!E93 | F58: ='Scenario_Drivers'!F93 | G58: ='Scenario_Drivers'!G93 | H58: ='Scenario_Drivers'!H93 | I58: ='Scenario_Drivers'!I93 | J58: ='Scenario_Drivers'!J93 | ... V58: ='Scenario_Drivers'!V93
A59: Revolver draw | B59: $mm | C59: =IF('Scenario_Drivers'!C98>=0,MAX(0,'Scenario_Drivers'!C98-0),IF('S&U_Opening'!$B$15+C52+C56+C57+C58+C61+C62<'Scenario_Drivers'!C97,MIN((MAX(0,Inputs!$B$20-'Scenario_Drivers'!C96))-0,'Scenario_Drivers'!C97-('S&U_Opening'!$B$15+C52+C56+C57+C58+C61+C62)),0)) | D59: =IF('Scenario_Drivers'!D98>=0,MAX(0,'Scenario_Drivers'!D98-C78),IF(C67+D52+D56+D57+D58+D61+D62<'Scenario_Drivers'!D97,MIN((MAX(0,Inputs!$B$20-'Scenario_Drivers'!D96))-C78,'Scenario_Drivers'!D97-(C67+D52+D56+D57+D58+D61+D62)),0)) | E59: =IF('Scenario_Drivers'!E98>=0,MAX(0,'Scenario_Drivers'!E98-D78),IF(D67+E52+E56+E57+E58+E61+E62<'Scenario_Drivers'!E97,MIN((MAX(0,Inputs!$B$20-'Scenario_Drivers'!E96))-D78,'Scenario_Drivers'!E97-(D67+E52+E56+E57+E58+E61+E62)),0)) | F59: =IF('Scenario_Drivers'!F98>=0,MAX(0,'Scenario_Drivers'!F98-E78),IF(E67+F52+F56+F57+F58+F61+F62<'Scenario_Drivers'!F97,MIN((MAX(0,Inputs!$B$20-'Scenario_Drivers'!F96))-E78,'Scenario_Drivers'!F97-(E67+F52+F56+F57+F58+F61+F62)),0)) | G59: =IF('Scenario_Drivers'!G98>=0,MAX(0,'Scenario_Drivers'!G98-F78),IF(F67+G52+G56+G57+G58+G61+G62<'Scenario_Drivers'!G97,MIN((MAX(0,Inputs!$B$20-'Scenario_Drivers'!G96))-F78,'Scenario_Drivers'!G97-(F67+G52+G56+G57+G58+G61+G62)),0)) | H59: =IF('Scenario_Drivers'!H98>=0,MAX(0,'Scenario_Drivers'!H98-G78),IF(G67+H52+H56+H57+H58+H61+H62<'Scenario_Drivers'!H97,MIN((MAX(0,Inputs!$B$20-'Scenario_Drivers'!H96))-G78,'Scenario_Drivers'!H97-(G67+H52+H56+H57+H58+H61+H62)),0)) | I59: =IF('Scenario_Drivers'!I98>=0,MAX(0,'Scenario_Drivers'!I98-H78),IF(H67+I52+I56+I57+I58+I61+I62<'Scenario_Drivers'!I97,MIN((MAX(0,Inputs!$B$20-'Scenario_Drivers'!I96))-H78,'Scenario_Drivers'!I97-(H67+I52+I56+I57+I58+I61+I62)),0)) | J59: =IF('Scenario_Drivers'!J98>=0,MAX(0,'Scenario_Drivers'!J98-I78),IF(I67+J52+J56+J57+J58+J61+J62<'Scenario_Drivers'!J97,MIN((MAX(0,Inputs!$B$20-'Scenario_Drivers'!J96))-I78,'Scenario_Drivers'!J97-(I67+J52+J56+J57+J58+J61+J62)),0)) | K59: =IF('Scenario_Drivers'!K98>=0,MAX(0,'Scenario_Drivers'!K98-J78),IF(J67+K52+K56+K57+K58+K61+K62<'Scenario_Drivers'!K97,MIN((MAX(0,Inputs!$B$20-'Scenario_Drivers'!K96))-J78,'Scenario_Drivers'!K97-(J67+K52+K56+K57+K58+K61+K62)),0)) | ... V59: =IF('Scenario_Drivers'!V98>=0,MAX(0,'Scenario_Drivers'!V98-U78),IF(U67+V52+V56+V57+V58+V61+V62<'Scenario_Drivers'!V97,MIN((MAX(0,Inputs!$B$20-'Scenario_Drivers'!V96))-U78,'Scenario_Drivers'!V97-(U67+V52+V56+V57+V58+V61+V62)),0))
A60: Revolver repayment | B60: $mm | C60: =-(IF('Scenario_Drivers'!C99=1,0,IF('Scenario_Drivers'!C98>=0,MAX(0,0-'Scenario_Drivers'!C98),IF('S&U_Opening'!$B$15+C52+C56+C57+C58+C61+C62>'Scenario_Drivers'!C97,MIN(0,('S&U_Opening'!$B$15+C52+C56+C57+C58+C61+C62)-'Scenario_Drivers'!C97),0)))) | D60: =-(IF('Scenario_Drivers'!D99=1,C78,IF('Scenario_Drivers'!D98>=0,MAX(0,C78-'Scenario_Drivers'!D98),IF(C67+D52+D56+D57+D58+D61+D62>'Scenario_Drivers'!D97,MIN(C78,(C67+D52+D56+D57+D58+D61+D62)-'Scenario_Drivers'!D97),0)))) | E60: =-(IF('Scenario_Drivers'!E99=1,D78,IF('Scenario_Drivers'!E98>=0,MAX(0,D78-'Scenario_Drivers'!E98),IF(D67+E52+E56+E57+E58+E61+E62>'Scenario_Drivers'!E97,MIN(D78,(D67+E52+E56+E57+E58+E61+E62)-'Scenario_Drivers'!E97),0)))) | F60: =-(IF('Scenario_Drivers'!F99=1,E78,IF('Scenario_Drivers'!F98>=0,MAX(0,E78-'Scenario_Drivers'!F98),IF(E67+F52+F56+F57+F58+F61+F62>'Scenario_Drivers'!F97,MIN(E78,(E67+F52+F56+F57+F58+F61+F62)-'Scenario_Drivers'!F97),0)))) | G60: =-(IF('Scenario_Drivers'!G99=1,F78,IF('Scenario_Drivers'!G98>=0,MAX(0,F78-'Scenario_Drivers'!G98),IF(F67+G52+G56+G57+G58+G61+G62>'Scenario_Drivers'!G97,MIN(F78,(F67+G52+G56+G57+G58+G61+G62)-'Scenario_Drivers'!G97),0)))) | H60: =-(IF('Scenario_Drivers'!H99=1,G78,IF('Scenario_Drivers'!H98>=0,MAX(0,G78-'Scenario_Drivers'!H98),IF(G67+H52+H56+H57+H58+H61+H62>'Scenario_Drivers'!H97,MIN(G78,(G67+H52+H56+H57+H58+H61+H62)-'Scenario_Drivers'!H97),0)))) | I60: =-(IF('Scenario_Drivers'!I99=1,H78,IF('Scenario_Drivers'!I98>=0,MAX(0,H78-'Scenario_Drivers'!I98),IF(H67+I52+I56+I57+I58+I61+I62>'Scenario_Drivers'!I97,MIN(H78,(H67+I52+I56+I57+I58+I61+I62)-'Scenario_Drivers'!I97),0)))) | J60: =-(IF('Scenario_Drivers'!J99=1,I78,IF('Scenario_Drivers'!J98>=0,MAX(0,I78-'Scenario_Drivers'!J98),IF(I67+J52+J56+J57+J58+J61+J62>'Scenario_Drivers'!J97,MIN(I78,(I67+J52+J56+J57+J58+J61+J62)-'Scenario_Drivers'!J97),0)))) | K60: =-(IF('Scenario_Drivers'!K99=1,J78,IF('Scenario_Drivers'!K98>=0,MAX(0,J78-'Scenario_Drivers'!K98),IF(J67+K52+K56+K57+K58+K61+K62>'Scenario_Drivers'!K97,MIN(J78,(J67+K52+K56+K57+K58+K61+K62)-'Scenario_Drivers'!K97),0)))) | ... V60: =-(IF('Scenario_Drivers'!V99=1,U78,IF('Scenario_Drivers'!V98>=0,MAX(0,U78-'Scenario_Drivers'!V98),IF(U67+V52+V56+V57+V58+V61+V62>'Scenario_Drivers'!V97,MIN(U78,(U67+V52+V56+V57+V58+V61+V62)-'Scenario_Drivers'!V97),0))))
A61: Scheduled term amortization | B61: $mm | C61: =-(MIN(0.107,'S&U_Opening'!$E$18)) | D61: =-(MIN(0.107,C76)) | E61: =-(MIN(0.107,D76)) | F61: =-(MIN(0.107,E76)) | G61: =-(MIN(0.107,F76)) | H61: =-(MIN(0.107,G76)) | I61: =-(MIN(0.107,H76)) | J61: =-(MIN(0.107,I76)) | K61: =-(MIN(0.107,J76)) | ... V61: =-(MIN(0.107,U76))
A62: Scheduled DDTL amortization | B62: $mm | C62: =-(IF(0>0,MIN(0.015,0),0)) | D62: =-(IF(C77>0,MIN(0.015,C77),0)) | E62: =-(IF(D77>0,MIN(0.015,D77),0)) | F62: =-(IF(E77>0,MIN(0.015,E77),0)) | G62: =-(IF(F77>0,MIN(0.015,F77),0)) | H62: =-(IF(G77>0,MIN(0.015,G77),0)) | I62: =-(IF(H77>0,MIN(0.015,H77),0)) | J62: =-(IF(I77>0,MIN(0.015,I77),0)) | K62: =-(IF(J77>0,MIN(0.015,J77),0)) | ... V62: =-(IF(U77>0,MIN(0.015,U77),0))
A63: ECF sweep | B63: $mm | C63: =-(0) | D63: =-(0) | E63: =-(MIN((MAX(0,D76+E61)),MAX(0,((D67+E52+E56+E57+E58+E61+E62)+E59+E60)-'Scenario_Drivers'!E97))*(IF((((MAX(0,D76+E61))+(MAX(0,D77+E58+E62))+(D78+E59+E60)-MIN(((D67+E52+E56+E57+E58+E61+E62)+E59+E60),Inputs!$B$19))/MAX(0.001,(SUM(C14:E14))))>3.0,50%,IF((((MAX(0,D76+E61))+(MAX(0,D77+E58+E62))+(D78+E59+E60)-MIN(((D67+E52+E56+E57+E58+E61+E62)+E59+E60),Inputs!$B$19))/MAX(0.001,(SUM(C14:E14))))>2.5,25%,0%)))) | F63: =-(0) | G63: =-(0) | H63: =-(0) | I63: =-(MIN((MAX(0,H76+I61)),MAX(0,((H67+I52+I56+I57+I58+I61+I62)+I59+I60)-'Scenario_Drivers'!I97))*(IF((((MAX(0,H76+I61))+(MAX(0,H77+I58+I62))+(H78+I59+I60)-MIN(((H67+I52+I56+I57+I58+I61+I62)+I59+I60),Inputs!$B$19))/MAX(0.001,(SUM(F14:I14))))>3.0,50%,IF((((MAX(0,H76+I61))+(MAX(0,H77+I58+I62))+(H78+I59+I60)-MIN(((H67+I52+I56+I57+I58+I61+I62)+I59+I60),Inputs!$B$19))/MAX(0.001,(SUM(F14:I14))))>2.5,25%,0%)))) | J63: =-(0) | K63: =-(0) | L63: =-(0) | M63: =-(MIN((MAX(0,L76+M61)),MAX(0,((L67+M52+M56+M57+M58+M61+M62)+M59+M60)-'Scenario_Drivers'!M97))*(IF((((MAX(0,L76+M61))+(MAX(0,L77+M58+M62))+(L78+M59+M60)-MIN(((L67+M52+M56+M57+M58+M61+M62)+M59+M60),Inputs!$B$19))/MAX(0.001,(SUM(J14:M14))))>3.0,50%,IF((((MAX(0,L76+M61))+(MAX(0,L77+M58+M62))+(L78+M59+M60)-MIN(((L67+M52+M56+M57+M58+M61+M62)+M59+M60),Inputs!$B$19))/MAX(0.001,(SUM(J14:M14))))>2.5,25%,0%)))) | N63: =-(0) | O63: =-(0) | P63: =-(0) | Q63: =-(MIN((MAX(0,P76+Q61)),MAX(0,((P67+Q52+Q56+Q57+Q58+Q61+Q62)+Q59+Q60)-'Scenario_Drivers'!Q97))*(IF((((MAX(0,P76+Q61))+(MAX(0,P77+Q58+Q62))+(P78+Q59+Q60)-MIN(((P67+Q52+Q56+Q57+Q58+Q61+Q62)+Q59+Q60),Inputs!$B$19))/MAX(0.001,(SUM(N14:Q14))))>3.0,50%,IF((((MAX(0,P76+Q61))+(MAX(0,P77+Q58+Q62))+(P78+Q59+Q60)-MIN(((P67+Q52+Q56+Q57+Q58+Q61+Q62)+Q59+Q60),Inputs!$B$19))/MAX(0.001,(SUM(N14:Q14))))>2.5,25%,0%)))) | R63: =-(0) | S63: =-(0) | T63: =-(0) | U63: =-(MIN((MAX(0,T76+U61)),MAX(0,((T67+U52+U56+U57+U58+U61+U62)+U59+U60)-'Scenario_Drivers'!U97))*(IF((((MAX(0,T76+U61))+(MAX(0,T77+U58+U62))+(T78+U59+U60)-MIN(((T67+U52+U56+U57+U58+U61+U62)+U59+U60),Inputs!$B$19))/MAX(0.001,(SUM(R14:U14))))>3.0,50%,IF((((MAX(0,T76+U61))+(MAX(0,T77+U58+U62))+(T78+U59+U60)-MIN(((T67+U52+U56+U57+U58+U61+U62)+U59+U60),Inputs!$B$19))/MAX(0.001,(SUM(R14:U14))))>2.5,25%,0%)))) | V63: =-(0)
A64: Cash from financing | B64: $mm | C64: =SUM(C57:C63) | D64: =SUM(D57:D63) | E64: =SUM(E57:E63) | F64: =SUM(F57:F63) | G64: =SUM(G57:G63) | H64: =SUM(H57:H63) | I64: =SUM(I57:I63) | J64: =SUM(J57:J63) | ... V64: =SUM(V57:V63)
A65: Net change in cash | B65: $mm | C65: =C52+C56+C64 | D65: =D52+D56+D64 | E65: =E52+E56+E64 | F65: =F52+F56+F64 | G65: =G52+G56+G64 | H65: =H52+H56+H64 | I65: =I52+I56+I64 | J65: =J52+J56+J64 | ... V65: =V52+V56+V64
A66: Beginning cash | B66: $mm | C66: ='S&U_Opening'!$B$15 | D66: =C67 | E66: =D67 | F66: =E67 | G66: =F67 | H66: =G67 | I66: =H67 | J66: =I67 | K66: =J67 | ... V66: =U67
A67: Ending cash | B67: $mm | C67: =C66+C65 | D67: =D66+D65 | E67: =E66+E65 | F67: =F66+F65 | G67: =G66+G65 | H67: =H66+H65 | I67: =I66+I65 | J67: =J66+J65 | ... V67: =V66+V65
A68: Balance Sheet
A69: PP&E, net | B69: $mm | C69: ='S&U_Opening'!$B$19+C41+C42-C17 | D69: =C69+D41+D42-D17 | E69: =D69+E41+E42-E17 | F69: =E69+F41+F42-F17 | G69: =F69+G41+G42-G17 | H69: =G69+H41+H42-H17 | I69: =H69+I41+I42-I17 | J69: =I69+J41+J42-J17 | K69: =J69+K41+K42-K17 | ... V69: =U69+V41+V42-V17
A70: Goodwill | B70: $mm | C70: ='S&U_Opening'!$B$20+'Scenario_Drivers'!C90 | D70: =C70+'Scenario_Drivers'!D90 | E70: =D70+'Scenario_Drivers'!E90 | F70: =E70+'Scenario_Drivers'!F90 | G70: =F70+'Scenario_Drivers'!G90 | H70: =G70+'Scenario_Drivers'!H90 | I70: =H70+'Scenario_Drivers'!I90 | J70: =I70+'Scenario_Drivers'!J90 | K70: =J70+'Scenario_Drivers'!K90 | ... V70: =U70+'Scenario_Drivers'!V90
A71: Intangibles, net | B71: $mm | C71: =MAX(0,SUM('S&U_Opening'!$B$21:$B$23)+'Scenario_Drivers'!C89-C18) | D71: =MAX(0,C71+'Scenario_Drivers'!D89-D18) | E71: =MAX(0,D71+'Scenario_Drivers'!E89-E18) | F71: =MAX(0,E71+'Scenario_Drivers'!F89-F18) | G71: =MAX(0,F71+'Scenario_Drivers'!G89-G18) | H71: =MAX(0,G71+'Scenario_Drivers'!H89-H18) | I71: =MAX(0,H71+'Scenario_Drivers'!I89-I18) | J71: =MAX(0,I71+'Scenario_Drivers'!J89-J18) | K71: =MAX(0,J71+'Scenario_Drivers'!K89-K18) | ... V71: =MAX(0,U71+'Scenario_Drivers'!V89-V18)
A72: Integration asset | B72: $mm | C72: =MAX(0,0+C45-C19) | D72: =MAX(0,C72+D45-D19) | E72: =MAX(0,D72+E45-E19) | F72: =MAX(0,E72+F45-F19) | G72: =MAX(0,F72+G45-G19) | H72: =MAX(0,G72+H45-H19) | I72: =MAX(0,H72+I45-I19) | J72: =MAX(0,I72+J45-J19) | K72: =MAX(0,J72+K45-K19) | ... V72: =MAX(0,U72+V45-V19)
A73: Deferred financing fees | B73: $mm | C73: =MAX(0,'S&U_Opening'!$B$24-C23) | D73: =MAX(0,C73-D23) | E73: =MAX(0,D73-E23) | F73: =MAX(0,E73-F23) | G73: =MAX(0,F73-G23) | H73: =MAX(0,G73-H23) | I73: =MAX(0,H73-I23) | J73: =MAX(0,I73-J23) | K73: =MAX(0,J73-K23) | ... V73: =MAX(0,U73-V23)
A74: Other assets | B74: $mm | C74: =1.3 | D74: =1.3 | E74: =1.3 | F74: =1.3 | G74: =1.3 | H74: =1.3 | I74: =1.3 | J74: =1.3 | ... V74: =1.3
A75: Total assets | B75: $mm | C75: =SUM(C67,C30,C31,C32,C69,C70,C71,C72,C73,C74) | D75: =SUM(D67,D30,D31,D32,D69,D70,D71,D72,D73,D74) | E75: =SUM(E67,E30,E31,E32,E69,E70,E71,E72,E73,E74) | F75: =SUM(F67,F30,F31,F32,F69,F70,F71,F72,F73,F74) | G75: =SUM(G67,G30,G31,G32,G69,G70,G71,G72,G73,G74) | H75: =SUM(H67,H30,H31,H32,H69,H70,H71,H72,H73,H74) | I75: =SUM(I67,I30,I31,I32,I69,I70,I71,I72,I73,I74) | J75: =SUM(J67,J30,J31,J32,J69,J70,J71,J72,J73,J74) | ... V75: =SUM(V67,V30,V31,V32,V69,V70,V71,V72,V73,V74)
A76: Term loan | B76: $mm | C76: =MAX(0,MAX(0,'S&U_Opening'!$E$18+C61)+C63) | D76: =MAX(0,MAX(0,C76+D61)+D63) | E76: =MAX(0,MAX(0,D76+E61)+E63) | F76: =MAX(0,MAX(0,E76+F61)+F63) | G76: =MAX(0,MAX(0,F76+G61)+G63) | H76: =MAX(0,MAX(0,G76+H61)+H63) | I76: =MAX(0,MAX(0,H76+I61)+I63) | J76: =MAX(0,MAX(0,I76+J61)+J63) | K76: =MAX(0,MAX(0,J76+K61)+K63) | ... V76: =MAX(0,MAX(0,U76+V61)+V63)
A77: DDTL | B77: $mm | C77: =MAX(0,0+C58+C62) | D77: =MAX(0,C77+D58+D62) | E77: =MAX(0,D77+E58+E62) | F77: =MAX(0,E77+F58+F62) | G77: =MAX(0,F77+G58+G62) | H77: =MAX(0,G77+H58+H62) | I77: =MAX(0,H77+I58+I62) | J77: =MAX(0,I77+J58+J62) | K77: =MAX(0,J77+K58+K62) | ... V77: =MAX(0,U77+V58+V62)
A78: Revolver | B78: $mm | C78: =0+C59+C60 | D78: =C78+D59+D60 | E78: =D78+E59+E60 | F78: =E78+F59+F60 | G78: =F78+G59+G60 | H78: =G78+H59+H60 | I78: =H78+I59+I60 | J78: =I78+J59+J60 | K78: =J78+K59+K60 | ... V78: =U78+V59+V60
A79: Accounts payable - BS | B79: $mm | C79: =C33 | D79: =D33 | E79: =E33 | F79: =F33 | G79: =G33 | H79: =H33 | I79: =I33 | J79: =J33 | ... V79: =V33
A80: Accrued liabilities - BS | B80: $mm | C80: =C34 | D80: =D34 | E80: =E34 | F80: =F34 | G80: =G34 | H80: =H34 | I80: =I34 | J80: =J34 | ... V80: =V34
A81: Deferred revenue - BS | B81: $mm | C81: =C35 | D81: =D35 | E81: =E35 | F81: =F35 | G81: =G35 | H81: =H35 | I81: =I35 | J81: =J35 | ... V81: =V35
A82: Deferred tax liability | B82: $mm | C82: =MAX(0,'S&U_Opening'!$E$19+'Scenario_Drivers'!C91-C26+C27) | D82: =MAX(0,C82+'Scenario_Drivers'!D91-D26+D27) | E82: =MAX(0,D82+'Scenario_Drivers'!E91-E26+E27) | F82: =MAX(0,E82+'Scenario_Drivers'!F91-F26+F27) | G82: =MAX(0,F82+'Scenario_Drivers'!G91-G26+G27) | H82: =MAX(0,G82+'Scenario_Drivers'!H91-H26+H27) | I82: =MAX(0,H82+'Scenario_Drivers'!I91-I26+I27) | J82: =MAX(0,I82+'Scenario_Drivers'!J91-J26+J27) | K82: =MAX(0,J82+'Scenario_Drivers'!K91-K26+K27) | ... V82: =MAX(0,U82+'Scenario_Drivers'!V91-V26+V27)
A83: Other liabilities | B83: $mm | C83: ='S&U_Opening'!$E$20+'Scenario_Drivers'!C92 | D83: =C83+'Scenario_Drivers'!D92 | E83: =D83+'Scenario_Drivers'!E92 | F83: =E83+'Scenario_Drivers'!F92 | G83: =F83+'Scenario_Drivers'!G92 | H83: =G83+'Scenario_Drivers'!H92 | I83: =H83+'Scenario_Drivers'!I92 | J83: =I83+'Scenario_Drivers'!J92 | K83: =J83+'Scenario_Drivers'!K92 | ... V83: =U83+'Scenario_Drivers'!V92
A84: Total liabilities | B84: $mm | C84: =SUM(C76:C83) | D84: =SUM(D76:D83) | E84: =SUM(E76:E83) | F84: =SUM(F76:F83) | G84: =SUM(G76:G83) | H84: =SUM(H76:H83) | I84: =SUM(I76:I83) | J84: =SUM(J76:J83) | ... V84: =SUM(V76:V83)
A85: Equity | B85: $mm | C85: ='S&U_Opening'!$E$21+C28+C57 | D85: =C85+D28+D57 | E85: =D85+E28+E57 | F85: =E85+F28+F57 | G85: =F85+G28+G57 | H85: =G85+H28+H57 | I85: =H85+I28+I57 | J85: =I85+J28+J57 | K85: =J85+K28+K57 | ... V85: =U85+V28+V57
A86: Total liabilities & equity | B86: $mm | C86: =C84+C85 | D86: =D84+D85 | E86: =E84+E85 | F86: =F84+F85 | G86: =G84+G85 | H86: =H84+H85 | I86: =I84+I85 | J86: =J84+J85 | ... V86: =V84+V85
A87: Balance sheet check | B87: $mm | C87: =C75-C86 | D87: =D75-D86 | E87: =E75-E86 | F87: =F75-F86 | G87: =G75-G86 | H87: =H75-H86 | I87: =I75-I86 | J87: =J75-J86 | ... V87: =V75-V86
A88: Debt and Covenant Metrics
A89: Gross debt | B89: $mm | C89: =SUM(C76:C78) | D89: =SUM(D76:D78) | E89: =SUM(E76:E78) | F89: =SUM(F76:F78) | G89: =SUM(G76:G78) | H89: =SUM(H76:H78) | I89: =SUM(I76:I78) | J89: =SUM(J76:J78) | ... V89: =SUM(V76:V78)
A90: Eligible cash | B90: $mm | C90: =MIN(C67,Inputs!$B$19) | D90: =MIN(D67,Inputs!$B$19) | E90: =MIN(E67,Inputs!$B$19) | F90: =MIN(F67,Inputs!$B$19) | G90: =MIN(G67,Inputs!$B$19) | H90: =MIN(H67,Inputs!$B$19) | I90: =MIN(I67,Inputs!$B$19) | J90: =MIN(J67,Inputs!$B$19) | ... V90: =MIN(V67,Inputs!$B$19)
A91: Covenant net debt | B91: $mm | C91: =C89-C90 | D91: =D89-D90 | E91: =E89-E90 | F91: =F89-F90 | G91: =G89-G90 | H91: =H89-H90 | I91: =I89-I90 | J91: =J89-J90 | ... V91: =V89-V90
A92: Economic net debt | B92: $mm | C92: =C89-C67 | D92: =D89-D67 | E92: =E89-E67 | F92: =F89-F67 | G92: =G89-G67 | H92: =H89-H67 | I92: =I89-I67 | J92: =J89-J67 | ... V92: =V89-V67
A93: LTM revenue | B93: $mm | C93: =SUM(C5:C5) | D93: =SUM(C5:D5) | E93: =SUM(C5:E5) | F93: =SUM(C5:F5) | G93: =SUM(D5:G5) | H93: =SUM(E5:H5) | I93: =SUM(F5:I5) | J93: =SUM(G5:J5) | K93: =SUM(H5:K5) | L93: =SUM(I5:L5) | M93: =SUM(J5:M5) | ... V93: =SUM(S5:V5)
A94: LTM reported EBITDA | B94: $mm | C94: =SUM(C12:C12) | D94: =SUM(C12:D12) | E94: =SUM(C12:E12) | F94: =SUM(C12:F12) | G94: =SUM(D12:G12) | H94: =SUM(E12:H12) | I94: =SUM(F12:I12) | J94: =SUM(G12:J12) | K94: =SUM(H12:K12) | L94: =SUM(I12:L12) | M94: =SUM(J12:M12) | ... V94: =SUM(S12:V12)
A95: LTM firm EBITDA | B95: $mm | C95: =SUM(C10:C10) | D95: =SUM(C10:D10) | E95: =SUM(C10:E10) | F95: =SUM(C10:F10) | G95: =SUM(D10:G10) | H95: =SUM(E10:H10) | I95: =SUM(F10:I10) | J95: =SUM(G10:J10) | K95: =SUM(H10:K10) | L95: =SUM(I10:L10) | M95: =SUM(J10:M10) | ... V95: =SUM(S10:V10)
A96: LTM add-backs | B96: $mm | C96: =SUM(C13:C13) | D96: =SUM(C13:D13) | E96: =SUM(C13:E13) | F96: =SUM(C13:F13) | G96: =SUM(D13:G13) | H96: =SUM(E13:H13) | I96: =SUM(F13:I13) | J96: =SUM(G13:J13) | K96: =SUM(H13:K13) | L96: =SUM(I13:L13) | M96: =SUM(J13:M13) | ... V96: =SUM(S13:V13)
A97: LTM covenant EBITDA | B97: $mm | C97: =SUM(C14:C14) | D97: =SUM(C14:D14) | E97: =SUM(C14:E14) | F97: =SUM(C14:F14) | G97: =SUM(D14:G14) | H97: =SUM(E14:H14) | I97: =SUM(F14:I14) | J97: =SUM(G14:J14) | K97: =SUM(H14:K14) | L97: =SUM(I14:L14) | M97: =SUM(J14:M14) | ... V97: =SUM(S14:V14)
A98: Total net leverage | B98: x | C98: =C91/MAX(0.001,C97) | D98: =D91/MAX(0.001,D97) | E98: =E91/MAX(0.001,E97) | F98: =F91/MAX(0.001,F97) | G98: =G91/MAX(0.001,G97) | H98: =H91/MAX(0.001,H97) | I98: =I91/MAX(0.001,I97) | J98: =J91/MAX(0.001,J97) | ... V98: =V91/MAX(0.001,V97)
A99: Gross leverage | B99: x | C99: =C89/MAX(0.001,C95) | D99: =D89/MAX(0.001,D95) | E99: =E89/MAX(0.001,E95) | F99: =F89/MAX(0.001,F95) | G99: =G89/MAX(0.001,G95) | H99: =H89/MAX(0.001,H95) | I99: =I89/MAX(0.001,I95) | J99: =J89/MAX(0.001,J95) | ... V99: =V89/MAX(0.001,V95)
A100: Fixed charge coverage | B100: x | C100: =(C94-SUM(C27:C27)-SUM(C41:C41))/MAX(0.001,(-SUM(C22:C22)-SUM(C61:C61)-SUM(C62:C62))) | D100: =(D94-SUM(C27:D27)-SUM(C41:D41))/MAX(0.001,(-SUM(C22:D22)-SUM(C61:D61)-SUM(C62:D62))) | E100: =(E94-SUM(C27:E27)-SUM(C41:E41))/MAX(0.001,(-SUM(C22:E22)-SUM(C61:E61)-SUM(C62:E62))) | F100: =(F94-SUM(C27:F27)-SUM(C41:F41))/MAX(0.001,(-SUM(C22:F22)-SUM(C61:F61)-SUM(C62:F62))) | G100: =(G94-SUM(D27:G27)-SUM(D41:G41))/MAX(0.001,(-SUM(D22:G22)-SUM(D61:G61)-SUM(D62:G62))) | H100: =(H94-SUM(E27:H27)-SUM(E41:H41))/MAX(0.001,(-SUM(E22:H22)-SUM(E61:H61)-SUM(E62:H62))) | I100: =(I94-SUM(F27:I27)-SUM(F41:I41))/MAX(0.001,(-SUM(F22:I22)-SUM(F61:I61)-SUM(F62:I62))) | J100: =(J94-SUM(G27:J27)-SUM(G41:J41))/MAX(0.001,(-SUM(G22:J22)-SUM(G61:J61)-SUM(G62:J62))) | K100: =(K94-SUM(H27:K27)-SUM(H41:K41))/MAX(0.001,(-SUM(H22:K22)-SUM(H61:K61)-SUM(H62:K62))) | L100: =(L94-SUM(I27:L27)-SUM(I41:L41))/MAX(0.001,(-SUM(I22:L22)-SUM(I61:L61)-SUM(I62:L62))) | M100: =(M94-SUM(J27:M27)-SUM(J41:M41))/MAX(0.001,(-SUM(J22:M22)-SUM(J61:M61)-SUM(J62:M62))) | ... V100: =(V94-SUM(S27:V27)-SUM(S41:V41))/MAX(0.001,(-SUM(S22:V22)-SUM(S61:V61)-SUM(S62:V62)))
A101: Revolver availability | B101: $mm | C101: =MAX(0,Inputs!$B$20-C78-'Scenario_Drivers'!C96) | D101: =MAX(0,Inputs!$B$20-D78-'Scenario_Drivers'!D96) | E101: =MAX(0,Inputs!$B$20-E78-'Scenario_Drivers'!E96) | F101: =MAX(0,Inputs!$B$20-F78-'Scenario_Drivers'!F96) | G101: =MAX(0,Inputs!$B$20-G78-'Scenario_Drivers'!G96) | H101: =MAX(0,Inputs!$B$20-H78-'Scenario_Drivers'!H96) | I101: =MAX(0,Inputs!$B$20-I78-'Scenario_Drivers'!I96) | J101: =MAX(0,Inputs!$B$20-J78-'Scenario_Drivers'!J96) | ... V101: =MAX(0,Inputs!$B$20-V78-'Scenario_Drivers'!V96)
...

Sheet Acq_Base
A1: Project Keystone - Acquisition Base Quarterly LBO ($mm)
A3: Line Item | B3: Unit | C3: 46203 | D3: 46295 | E3: 46387 | F3: 46477 | G3: 46568 | H3: 46660 | I3: 46752 | J3: 46843 | K3: 46934 | L3: 47026 | M3: 47118 | N3: 47208 | O3: 47299 | P3: 47391 | Q3: 47483 | R3: 47573 | S3: 47664 | T3: 47756 | U3: 47848 | V3: 47938
A4: Operating Model
A5: Revenue | B5: $mm | C5: ='Scenario_Drivers'!C107 | D5: ='Scenario_Drivers'!D107 | E5: ='Scenario_Drivers'!E107 | F5: ='Scenario_Drivers'!F107 | G5: ='Scenario_Drivers'!G107 | H5: ='Scenario_Drivers'!H107 | I5: ='Scenario_Drivers'!I107 | J5: ='Scenario_Drivers'!J107 | ... V5: ='Scenario_Drivers'!V107
A6: Growth | B6: % | C6: =C5/(74.0*'Scenario_Drivers'!C138)-1 | D6: =D5/C5-1 | E6: =E5/D5-1 | F6: =F5/V5-1 | G6: =G5/F5-1 | H6: =H5/G5-1 | I6: =I5/H5-1 | J6: =J5/F5-1 | K6: =K5/J5-1 | L6: =L5/K5-1 | M6: =M5/L5-1 | N6: =N5/J5-1 | O6: =O5/N5-1 | P6: =P5/O5-1 | Q6: =Q5/P5-1 | R6: =R5/N5-1 | S6: =S5/R5-1 | T6: =T5/S5-1 | U6: =U5/T5-1 | V6: =V5/R5-1
A7: Gross margin | B7: % | C7: ='Scenario_Drivers'!C108 | D7: ='Scenario_Drivers'!D108 | E7: ='Scenario_Drivers'!E108 | F7: ='Scenario_Drivers'!F108 | G7: ='Scenario_Drivers'!G108 | H7: ='Scenario_Drivers'!H108 | I7: ='Scenario_Drivers'!I108 | J7: ='Scenario_Drivers'!J108 | ... V7: ='Scenario_Drivers'!V108
A8: Gross profit | B8: $mm | C8: =C5*C7 | D8: =D5*D7 | E8: =E5*E7 | F8: =F5*F7 | G8: =G5*G7 | H8: =H5*H7 | I8: =I5*I7 | J8: =J5*J7 | ... V8: =V5*V7
A9: COGS | B9: $mm | C9: =-(C5-C8) | D9: =-(D5-D8) | E9: =-(E5-E8) | F9: =-(F5-F8) | G9: =-(G5-G8) | H9: =-(H5-H8) | I9: =-(I5-I8) | J9: =-(J5-J8) | ... V9: =-(V5-V8)
A10: Firm EBITDA | B10: $mm | C10: ='Scenario_Drivers'!C109 | D10: ='Scenario_Drivers'!D109 | E10: ='Scenario_Drivers'!E109 | F10: ='Scenario_Drivers'!F109 | G10: ='Scenario_Drivers'!G109 | H10: ='Scenario_Drivers'!H109 | I10: ='Scenario_Drivers'!I109 | J10: ='Scenario_Drivers'!J109 | ... V10: ='Scenario_Drivers'!V109
A11: One-time charges | B11: $mm | C11: =-'Scenario_Drivers'!C110 | D11: =-'Scenario_Drivers'!D110 | E11: =-'Scenario_Drivers'!E110 | F11: =-'Scenario_Drivers'!F110 | G11: =-'Scenario_Drivers'!G110 | H11: =-'Scenario_Drivers'!H110 | I11: =-'Scenario_Drivers'!I110 | J11: =-'Scenario_Drivers'!J110 | ... V11: =-'Scenario_Drivers'!V110
A12: Reported EBITDA | B12: $mm | C12: =C10+C11 | D12: =D10+D11 | E12: =E10+E11 | F12: =F10+F11 | G12: =G10+G11 | H12: =H10+H11 | I12: =I10+I11 | J12: =J10+J11 | ... V12: =V10+V11
A13: Covenant add-backs | B13: $mm | C13: ='Scenario_Drivers'!C111 | D13: ='Scenario_Drivers'!D111 | E13: ='Scenario_Drivers'!E111 | F13: ='Scenario_Drivers'!F111 | G13: ='Scenario_Drivers'!G111 | H13: ='Scenario_Drivers'!H111 | I13: ='Scenario_Drivers'!I111 | J13: ='Scenario_Drivers'!J111 | ... V13: ='Scenario_Drivers'!V111
A14: Covenant EBITDA | B14: $mm | C14: =C12+C13 | D14: =D12+D13 | E14: =E12+E13 | F14: =F12+F13 | G14: =G12+G13 | H14: =H12+H13 | I14: =I12+I13 | J14: =J12+J13 | ... V14: =V12+V13
A15: Firm EBITDA margin | B15: % | C15: =C10/C5 | D15: =D10/D5 | E15: =E10/E5 | F15: =F10/F5 | G15: =G10/G5 | H15: =H10/H5 | I15: =I10/I5 | J15: =J10/J5 | ... V15: =V10/V5
A16: Income Statement
A17: Depreciation | B17: $mm | C17: =C5*Inputs!$B$17 | D17: =D5*Inputs!$B$17 | E17: =E5*Inputs!$B$17 | F17: =F5*Inputs!$B$17 | G17: =G5*Inputs!$B$17 | H17: =H5*Inputs!$B$17 | I17: =I5*Inputs!$B$17 | J17: =J5*Inputs!$B$17 | ... V17: =V5*Inputs!$B$17
A18: Core PPA amortization | B18: $mm | C18: ='Scenario_Drivers'!C137 | D18: ='Scenario_Drivers'!D137 | E18: ='Scenario_Drivers'!E137 | F18: ='Scenario_Drivers'!F137 | G18: ='Scenario_Drivers'!G137 | H18: ='Scenario_Drivers'!H137 | I18: ='Scenario_Drivers'!I137 | J18: ='Scenario_Drivers'!J137 | ... V18: ='Scenario_Drivers'!V137
A19: Integration asset amortization | B19: $mm | C19: =0 | D19: =0 | E19: =0 | F19: =0 | G19: =0 | H19: =0 | I19: =0 | J19: =0 | ... V19: =0
A20: Total D&A | B20: $mm | C20: =SUM(C17:C19) | D20: =SUM(D17:D19) | E20: =SUM(E17:E19) | F20: =SUM(F17:F19) | G20: =SUM(G17:G19) | H20: =SUM(H17:H19) | I20: =SUM(I17:I19) | J20: =SUM(J17:J19) | ... V20: =SUM(V17:V19)
A21: EBIT | B21: $mm | C21: =C12-C20 | D21: =D12-D20 | E21: =E12-E20 | F21: =F12-F20 | G21: =G12-G20 | H21: =H12-H20 | I21: =I12-I20 | J21: =J12-J20 | ... V21: =V12-V20
A22: Cash interest | B22: $mm | C22: =-((('S&U_Opening'!$E$18+MAX(0,'S&U_Opening'!$E$18-(MIN(0.107,'S&U_Opening'!$E$18))))/2)*(MAX('Scenario_Drivers'!C135,Inputs!$B$26)+Inputs!$B$23+'Scenario_Drivers'!C136)/4+((0+0+'Scenario_Drivers'!C127-(IF(0>0,MIN(0.015,0),0)))/2)*(MAX('Scenario_Drivers'!C135,Inputs!$B$26)+Inputs!$B$25+'Scenario_Drivers'!C136)/4+0*(MAX('Scenario_Drivers'!C135,Inputs!$B$26)+Inputs!$B$24+'Scenario_Drivers'!C136)/4+MAX(0,Inputs!$B$20-0-'Scenario_Drivers'!C130)*Inputs!$B$29/4+0) | D22: =-(((C76+MAX(0,C76-(MIN(0.107,C76))))/2)*(MAX('Scenario_Drivers'!D135,Inputs!$B$26)+Inputs!$B$23+'Scenario_Drivers'!D136)/4+((C77+C77+'Scenario_Drivers'!D127-(IF(C77>0,MIN(0.015,C77),0)))/2)*(MAX('Scenario_Drivers'!D135,Inputs!$B$26)+Inputs!$B$25+'Scenario_Drivers'!D136)/4+C78*(MAX('Scenario_Drivers'!D135,Inputs!$B$26)+Inputs!$B$24+'Scenario_Drivers'!D136)/4+MAX(0,Inputs!$B$20-C78-'Scenario_Drivers'!D130)*Inputs!$B$29/4+MAX(0,Inputs!$B$21-C77-'Scenario_Drivers'!D127)*Inputs!$B$30/4) | E22: =-(((D76+MAX(0,D76-(MIN(0.107,D76))))/2)*(MAX('Scenario_Drivers'!E135,Inputs!$B$26)+Inputs!$B$23+'Scenario_Drivers'!E136)/4+((D77+D77+'Scenario_Drivers'!E127-(IF(D77>0,MIN(0.015,D77),0)))/2)*(MAX('Scenario_Drivers'!E135,Inputs!$B$26)+Inputs!$B$25+'Scenario_Drivers'!E136)/4+D78*(MAX('Scenario_Drivers'!E135,Inputs!$B$26)+Inputs!$B$24+'Scenario_Drivers'!E136)/4+MAX(0,Inputs!$B$20-D78-'Scenario_Drivers'!E130)*Inputs!$B$29/4+MAX(0,Inputs!$B$21-D77-'Scenario_Drivers'!E127)*Inputs!$B$30/4) | F22: =-(((E76+MAX(0,E76-(MIN(0.107,E76))))/2)*(MAX('Scenario_Drivers'!F135,Inputs!$B$26)+Inputs!$B$23+'Scenario_Drivers'!F136)/4+((E77+E77+'Scenario_Drivers'!F127-(IF(E77>0,MIN(0.015,E77),0)))/2)*(MAX('Scenario_Drivers'!F135,Inputs!$B$26)+Inputs!$B$25+'Scenario_Drivers'!F136)/4+E78*(MAX('Scenario_Drivers'!F135,Inputs!$B$26)+Inputs!$B$24+'Scenario_Drivers'!F136)/4+MAX(0,Inputs!$B$20-E78-'Scenario_Drivers'!F130)*Inputs!$B$29/4+MAX(0,Inputs!$B$21-E77-'Scenario_Drivers'!F127)*Inputs!$B$30/4) | G22: =-(((F76+MAX(0,F76-(MIN(0.107,F76))))/2)*(MAX('Scenario_Drivers'!G135,Inputs!$B$26)+Inputs!$B$23+'Scenario_Drivers'!G136)/4+((F77+F77+'Scenario_Drivers'!G127-(IF(F77>0,MIN(0.015,F77),0)))/2)*(MAX('Scenario_Drivers'!G135,Inputs!$B$26)+Inputs!$B$25+'Scenario_Drivers'!G136)/4+F78*(MAX('Scenario_Drivers'!G135,Inputs!$B$26)+Inputs!$B$24+'Scenario_Drivers'!G136)/4+MAX(0,Inputs!$B$20-F78-'Scenario_Drivers'!G130)*Inputs!$B$29/4+MAX(0,Inputs!$B$21-F77-'Scenario_Drivers'!G127)*Inputs!$B$30/4) | H22: =-(((G76+MAX(0,G76-(MIN(0.107,G76))))/2)*(MAX('Scenario_Drivers'!H135,Inputs!$B$26)+Inputs!$B$23+'Scenario_Drivers'!H136)/4+((G77+G77+'Scenario_Drivers'!H127-(IF(G77>0,MIN(0.015,G77),0)))/2)*(MAX('Scenario_Drivers'!H135,Inputs!$B$26)+Inputs!$B$25+'Scenario_Drivers'!H136)/4+G78*(MAX('Scenario_Drivers'!H135,Inputs!$B$26)+Inputs!$B$24+'Scenario_Drivers'!H136)/4+MAX(0,Inputs!$B$20-G78-'Scenario_Drivers'!H130)*Inputs!$B$29/4+MAX(0,Inputs!$B$21-G77-'Scenario_Drivers'!H127)*Inputs!$B$30/4) | I22: =-(((H76+MAX(0,H76-(MIN(0.107,H76))))/2)*(MAX('Scenario_Drivers'!I135,Inputs!$B$26)+Inputs!$B$23+'Scenario_Drivers'!I136)/4+((H77+H77+'Scenario_Drivers'!I127-(IF(H77>0,MIN(0.015,H77),0)))/2)*(MAX('Scenario_Drivers'!I135,Inputs!$B$26)+Inputs!$B$25+'Scenario_Drivers'!I136)/4+H78*(MAX('Scenario_Drivers'!I135,Inputs!$B$26)+Inputs!$B$24+'Scenario_Drivers'!I136)/4+MAX(0,Inputs!$B$20-H78-'Scenario_Drivers'!I130)*Inputs!$B$29/4+0) | J22: =-(((I76+MAX(0,I76-(MIN(0.107,I76))))/2)*(MAX('Scenario_Drivers'!J135,Inputs!$B$26)+Inputs!$B$23+'Scenario_Drivers'!J136)/4+((I77+I77+'Scenario_Drivers'!J127-(IF(I77>0,MIN(0.015,I77),0)))/2)*(MAX('Scenario_Drivers'!J135,Inputs!$B$26)+Inputs!$B$25+'Scenario_Drivers'!J136)/4+I78*(MAX('Scenario_Drivers'!J135,Inputs!$B$26)+Inputs!$B$24+'Scenario_Drivers'!J136)/4+MAX(0,Inputs!$B$20-I78-'Scenario_Drivers'!J130)*Inputs!$B$29/4+0) | K22: =-(((J76+MAX(0,J76-(MIN(0.107,J76))))/2)*(MAX('Scenario_Drivers'!K135,Inputs!$B$26)+Inputs!$B$23+'Scenario_Drivers'!K136)/4+((J77+J77+'Scenario_Drivers'!K127-(IF(J77>0,MIN(0.015,J77),0)))/2)*(MAX('Scenario_Drivers'!K135,Inputs!$B$26)+Inputs!$B$25+'Scenario_Drivers'!K136)/4+J78*(MAX('Scenario_Drivers'!K135,Inputs!$B$26)+Inputs!$B$24+'Scenario_Drivers'!K136)/4+MAX(0,Inputs!$B$20-J78-'Scenario_Drivers'!K130)*Inputs!$B$29/4+0) | L22: =-(((K76+MAX(0,K76-(MIN(0.107,K76))))/2)*(MAX('Scenario_Drivers'!L135,Inputs!$B$26)+Inputs!$B$23+'Scenario_Drivers'!L136)/4+((K77+K77+'Scenario_Drivers'!L127-(IF(K77>0,MIN(0.015,K77),0)))/2)*(MAX('Scenario_Drivers'!L135,Inputs!$B$26)+Inputs!$B$25+'Scenario_Drivers'!L136)/4+K78*(MAX('Scenario_Drivers'!L135,Inputs!$B$26)+Inputs!$B$24+'Scenario_Drivers'!L136)/4+MAX(0,Inputs!$B$20-K78-'Scenario_Drivers'!L130)*Inputs!$B$29/4+0) | M22: =-(((L76+MAX(0,L76-(MIN(0.107,L76))))/2)*(MAX('Scenario_Drivers'!M135,Inputs!$B$26)+Inputs!$B$23+'Scenario_Drivers'!M136)/4+((L77+L77+'Scenario_Drivers'!M127-(IF(L77>0,MIN(0.015,L77),0)))/2)*(MAX('Scenario_Drivers'!M135,Inputs!$B$26)+Inputs!$B$25+'Scenario_Drivers'!M136)/4+L78*(MAX('Scenario_Drivers'!M135,Inputs!$B$26)+Inputs!$B$24+'Scenario_Drivers'!M136)/4+MAX(0,Inputs!$B$20-L78-'Scenario_Drivers'!M130)*Inputs!$B$29/4+0) | N22: =-(((M76+MAX(0,M76-(MIN(0.107,M76))))/2)*(MAX('Scenario_Drivers'!N135,Inputs!$B$26)+Inputs!$B$23+'Scenario_Drivers'!N136)/4+((M77+M77+'Scenario_Drivers'!N127-(IF(M77>0,MIN(0.015,M77),0)))/2)*(MAX('Scenario_Drivers'!N135,Inputs!$B$26)+Inputs!$B$25+'Scenario_Drivers'!N136)/4+M78*(MAX('Scenario_Drivers'!N135,Inputs!$B$26)+Inputs!$B$24+'Scenario_Drivers'!N136)/4+MAX(0,Inputs!$B$20-M78-'Scenario_Drivers'!N130)*Inputs!$B$29/4+0) | O22: =-(((N76+MAX(0,N76-(MIN(0.107,N76))))/2)*(MAX('Scenario_Drivers'!O135,Inputs!$B$26)+Inputs!$B$23+'Scenario_Drivers'!O136)/4+((N77+N77+'Scenario_Drivers'!O127-(IF(N77>0,MIN(0.015,N77),0)))/2)*(MAX('Scenario_Drivers'!O135,Inputs!$B$26)+Inputs!$B$25+'Scenario_Drivers'!O136)/4+N78*(MAX('Scenario_Drivers'!O135,Inputs!$B$26)+Inputs!$B$24+'Scenario_Drivers'!O136)/4+MAX(0,Inputs!$B$20-N78-'Scenario_Drivers'!O130)*Inputs!$B$29/4+0) | P22: =-(((O76+MAX(0,O76-(MIN(0.107,O76))))/2)*(MAX('Scenario_Drivers'!P135,Inputs!$B$26)+Inputs!$B$23+'Scenario_Drivers'!P136)/4+((O77+O77+'Scenario_Drivers'!P127-(IF(O77>0,MIN(0.015,O77),0)))/2)*(MAX('Scenario_Drivers'!P135,Inputs!$B$26)+Inputs!$B$25+'Scenario_Drivers'!P136)/4+O78*(MAX('Scenario_Drivers'!P135,Inputs!$B$26)+Inputs!$B$24+'Scenario_Drivers'!P136)/4+MAX(0,Inputs!$B$20-O78-'Scenario_Drivers'!P130)*Inputs!$B$29/4+0) | ... V22: =-(((U76+MAX(0,U76-(MIN(0.107,U76))))/2)*(MAX('Scenario_Drivers'!V135,Inputs!$B$26)+Inputs!$B$23+'Scenario_Drivers'!V136)/4+((U77+U77+'Scenario_Drivers'!V127-(IF(U77>0,MIN(0.015,U77),0)))/2)*(MAX('Scenario_Drivers'!V135,Inputs!$B$26)+Inputs!$B$25+'Scenario_Drivers'!V136)/4+U78*(MAX('Scenario_Drivers'!V135,Inputs!$B$26)+Inputs!$B$24+'Scenario_Drivers'!V136)/4+MAX(0,Inputs!$B$20-U78-'Scenario_Drivers'!V130)*Inputs!$B$29/4+0)
A23: Financing fee amortization | B23: $mm | C23: =MIN('S&U_Opening'!$B$24,1.4/24) | D23: =MIN(C73,1.4/24) | E23: =MIN(D73,1.4/24) | F23: =MIN(E73,1.4/24) | G23: =MIN(F73,1.4/24) | H23: =MIN(G73,1.4/24) | I23: =MIN(H73,1.4/24) | J23: =MIN(I73,1.4/24) | K23: =MIN(J73,1.4/24) | ... V23: =MIN(U73,1.4/24)
A24: Interest income | B24: $mm | C24: ='S&U_Opening'!$B$15*1.0%/4 | D24: =C67*1.0%/4 | E24: =D67*1.0%/4 | F24: =E67*1.0%/4 | G24: =F67*1.0%/4 | H24: =G67*1.0%/4 | I24: =H67*1.0%/4 | J24: =I67*1.0%/4 | K24: =J67*1.0%/4 | ... V24: =U67*1.0%/4
A25: Pre-tax income | B25: $mm | C25: =C21+C22-C23+C24 | D25: =D21+D22-D23+D24 | E25: =E21+E22-E23+E24 | F25: =F21+F22-F23+F24 | G25: =G21+G22-G23+G24 | H25: =H21+H22-H23+H24 | I25: =I21+I22-I23+I24 | J25: =J21+J22-J23+J24 | ... V25: =V21+V22-V23+V24
A26: Book tax expense | B26: $mm | C26: =-MAX(0,C25*Inputs!$B$15) | D26: =-MAX(0,D25*Inputs!$B$15) | E26: =-MAX(0,E25*Inputs!$B$15) | F26: =-MAX(0,F25*Inputs!$B$15) | G26: =-MAX(0,G25*Inputs!$B$15) | H26: =-MAX(0,H25*Inputs!$B$15) | I26: =-MAX(0,I25*Inputs!$B$15) | J26: =-MAX(0,J25*Inputs!$B$15) | ... V26: =-MAX(0,V25*Inputs!$B$15)
A27: Cash taxes | B27: $mm | C27: =-MAX(0,(C116-0)*Inputs!$B$15) | D27: =-MAX(0,(D116-C115)*Inputs!$B$15) | E27: =-MAX(0,(E116-D115)*Inputs!$B$15) | F27: =-MAX(0,(F116-E115)*Inputs!$B$15) | G27: =-MAX(0,(G116-F115)*Inputs!$B$15) | H27: =-MAX(0,(H116-G115)*Inputs!$B$15) | I27: =-MAX(0,(I116-H115)*Inputs!$B$15) | J27: =-MAX(0,(J116-I115)*Inputs!$B$15) | K27: =-MAX(0,(K116-J115)*Inputs!$B$15) | ... V27: =-MAX(0,(V116-U115)*Inputs!$B$15)
A28: Net income | B28: $mm | C28: =C25+C26 | D28: =D25+D26 | E28: =E25+E26 | F28: =F25+F26 | G28: =G25+G26 | H28: =H25+H26 | I28: =I25+I26 | J28: =J25+J26 | ... V28: =V25+V26
A29: Working Capital and Capital Expenditure
A30: Accounts receivable | B30: $mm | C30: =(C5/'Scenario_Drivers'!C138)*'Scenario_Drivers'!C112/365 | D30: =(D5/'Scenario_Drivers'!D138)*'Scenario_Drivers'!D112/365 | E30: =(E5/'Scenario_Drivers'!E138)*'Scenario_Drivers'!E112/365 | F30: =(F5/'Scenario_Drivers'!F138)*'Scenario_Drivers'!F112/365 | G30: =(G5/'Scenario_Drivers'!G138)*'Scenario_Drivers'!G112/365 | H30: =(H5/'Scenario_Drivers'!H138)*'Scenario_Drivers'!H112/365 | I30: =(I5/'Scenario_Drivers'!I138)*'Scenario_Drivers'!I112/365 | J30: =(J5/'Scenario_Drivers'!J138)*'Scenario_Drivers'!J112/365 | ... V30: =(V5/'Scenario_Drivers'!V138)*'Scenario_Drivers'!V112/365
A31: Unbilled WIP | B31: $mm | C31: =(C5/'Scenario_Drivers'!C138)*'Scenario_Drivers'!C113 | D31: =(D5/'Scenario_Drivers'!D138)*'Scenario_Drivers'!D113 | E31: =(E5/'Scenario_Drivers'!E138)*'Scenario_Drivers'!E113 | F31: =(F5/'Scenario_Drivers'!F138)*'Scenario_Drivers'!F113 | G31: =(G5/'Scenario_Drivers'!G138)*'Scenario_Drivers'!G113 | H31: =(H5/'Scenario_Drivers'!H138)*'Scenario_Drivers'!H113 | I31: =(I5/'Scenario_Drivers'!I138)*'Scenario_Drivers'!I113 | J31: =(J5/'Scenario_Drivers'!J138)*'Scenario_Drivers'!J113 | ... V31: =(V5/'Scenario_Drivers'!V138)*'Scenario_Drivers'!V113
A32: Prepaids | B32: $mm | C32: =(C5/'Scenario_Drivers'!C138)*'Scenario_Drivers'!C114 | D32: =(D5/'Scenario_Drivers'!D138)*'Scenario_Drivers'!D114 | E32: =(E5/'Scenario_Drivers'!E138)*'Scenario_Drivers'!E114 | F32: =(F5/'Scenario_Drivers'!F138)*'Scenario_Drivers'!F114 | G32: =(G5/'Scenario_Drivers'!G138)*'Scenario_Drivers'!G114 | H32: =(H5/'Scenario_Drivers'!H138)*'Scenario_Drivers'!H114 | I32: =(I5/'Scenario_Drivers'!I138)*'Scenario_Drivers'!I114 | J32: =(J5/'Scenario_Drivers'!J138)*'Scenario_Drivers'!J114 | ... V32: =(V5/'Scenario_Drivers'!V138)*'Scenario_Drivers'!V114
A33: Accounts payable | B33: $mm | C33: =(C5/'Scenario_Drivers'!C138)*'Scenario_Drivers'!C115 | D33: =(D5/'Scenario_Drivers'!D138)*'Scenario_Drivers'!D115 | E33: =(E5/'Scenario_Drivers'!E138)*'Scenario_Drivers'!E115 | F33: =(F5/'Scenario_Drivers'!F138)*'Scenario_Drivers'!F115 | G33: =(G5/'Scenario_Drivers'!G138)*'Scenario_Drivers'!G115 | H33: =(H5/'Scenario_Drivers'!H138)*'Scenario_Drivers'!H115 | I33: =(I5/'Scenario_Drivers'!I138)*'Scenario_Drivers'!I115 | J33: =(J5/'Scenario_Drivers'!J138)*'Scenario_Drivers'!J115 | ... V33: =(V5/'Scenario_Drivers'!V138)*'Scenario_Drivers'!V115
A34: Accrued liabilities | B34: $mm | C34: =(C5/'Scenario_Drivers'!C138)*'Scenario_Drivers'!C116 | D34: =(D5/'Scenario_Drivers'!D138)*'Scenario_Drivers'!D116 | E34: =(E5/'Scenario_Drivers'!E138)*'Scenario_Drivers'!E116 | F34: =(F5/'Scenario_Drivers'!F138)*'Scenario_Drivers'!F116 | G34: =(G5/'Scenario_Drivers'!G138)*'Scenario_Drivers'!G116 | H34: =(H5/'Scenario_Drivers'!H138)*'Scenario_Drivers'!H116 | I34: =(I5/'Scenario_Drivers'!I138)*'Scenario_Drivers'!I116 | J34: =(J5/'Scenario_Drivers'!J138)*'Scenario_Drivers'!J116 | ... V34: =(V5/'Scenario_Drivers'!V138)*'Scenario_Drivers'!V116
A35: Deferred revenue | B35: $mm | C35: =(C5/'Scenario_Drivers'!C138)*'Scenario_Drivers'!C117 | D35: =(D5/'Scenario_Drivers'!D138)*'Scenario_Drivers'!D117 | E35: =(E5/'Scenario_Drivers'!E138)*'Scenario_Drivers'!E117 | F35: =(F5/'Scenario_Drivers'!F138)*'Scenario_Drivers'!F117 | G35: =(G5/'Scenario_Drivers'!G138)*'Scenario_Drivers'!G117 | H35: =(H5/'Scenario_Drivers'!H138)*'Scenario_Drivers'!H117 | I35: =(I5/'Scenario_Drivers'!I138)*'Scenario_Drivers'!I117 | J35: =(J5/'Scenario_Drivers'!J138)*'Scenario_Drivers'!J117 | ... V35: =(V5/'Scenario_Drivers'!V138)*'Scenario_Drivers'!V117
A36: Operating NWC | B36: $mm | C36: =C30+C31+C32-C33-C34-C35 | D36: =D30+D31+D32-D33-D34-D35 | E36: =E30+E31+E32-E33-E34-E35 | F36: =F30+F31+F32-F33-F34-F35 | G36: =G30+G31+G32-G33-G34-G35 | H36: =H30+H31+H32-H33-H34-H35 | I36: =I30+I31+I32-I33-I34-I35 | J36: =J30+J31+J32-J33-J34-J35 | ... V36: =V30+V31+V32-V33-V34-V35
A37: Acquired NWC | B37: $mm | C37: ='Scenario_Drivers'!C119 | D37: ='Scenario_Drivers'!D119 | E37: ='Scenario_Drivers'!E119 | F37: ='Scenario_Drivers'!F119 | G37: ='Scenario_Drivers'!G119 | H37: ='Scenario_Drivers'!H119 | I37: ='Scenario_Drivers'!I119 | J37: ='Scenario_Drivers'!J119 | ... V37: ='Scenario_Drivers'!V119
A38: Organic change in NWC | B38: $mm | C38: =C36-('S&U_Opening'!$B$16+'S&U_Opening'!$B$17+'S&U_Opening'!$B$18-'S&U_Opening'!$E$15-'S&U_Opening'!$E$16-'S&U_Opening'!$E$17)-C37 | D38: =D36-(C36)-D37 | E38: =E36-(D36)-E37 | F38: =F36-(E36)-F37 | G38: =G36-(F36)-G37 | H38: =H36-(G36)-H37 | I38: =I36-(H36)-I37 | J38: =J36-(I36)-J37 | K38: =K36-(J36)-K37 | ... V38: =V36-(U36)-V37
A39: Maintenance capex | B39: $mm | C39: =C5*'Scenario_Drivers'!C118*Inputs!$B$18 | D39: =D5*'Scenario_Drivers'!D118*Inputs!$B$18 | E39: =E5*'Scenario_Drivers'!E118*Inputs!$B$18 | F39: =F5*'Scenario_Drivers'!F118*Inputs!$B$18 | G39: =G5*'Scenario_Drivers'!G118*Inputs!$B$18 | H39: =H5*'Scenario_Drivers'!H118*Inputs!$B$18 | I39: =I5*'Scenario_Drivers'!I118*Inputs!$B$18 | J39: =J5*'Scenario_Drivers'!J118*Inputs!$B$18 | ... V39: =V5*'Scenario_Drivers'!V118*Inputs!$B$18
A40: Growth capex | B40: $mm | C40: =C5*'Scenario_Drivers'!C118*(1-Inputs!$B$18) | D40: =D5*'Scenario_Drivers'!D118*(1-Inputs!$B$18) | E40: =E5*'Scenario_Drivers'!E118*(1-Inputs!$B$18) | F40: =F5*'Scenario_Drivers'!F118*(1-Inputs!$B$18) | G40: =G5*'Scenario_Drivers'!G118*(1-Inputs!$B$18) | H40: =H5*'Scenario_Drivers'!H118*(1-Inputs!$B$18) | I40: =I5*'Scenario_Drivers'!I118*(1-Inputs!$B$18) | J40: =J5*'Scenario_Drivers'!J118*(1-Inputs!$B$18) | ... V40: =V5*'Scenario_Drivers'!V118*(1-Inputs!$B$18)
A41: Total capex | B41: $mm | C41: =SUM(C39:C40) | D41: =SUM(D39:D40) | E41: =SUM(E39:E40) | F41: =SUM(F39:F40) | G41: =SUM(G39:G40) | H41: =SUM(H39:H40) | I41: =SUM(I39:I40) | J41: =SUM(J39:J40) | ... V41: =SUM(V39:V40)
A42: Acquired PP&E | B42: $mm | C42: ='Scenario_Drivers'!C120 | D42: ='Scenario_Drivers'!D120 | E42: ='Scenario_Drivers'!E120 | F42: ='Scenario_Drivers'!F120 | G42: ='Scenario_Drivers'!G120 | H42: ='Scenario_Drivers'!H120 | I42: ='Scenario_Drivers'!I120 | J42: ='Scenario_Drivers'!J120 | ... V42: ='Scenario_Drivers'!V120
A43: Acquisition EV | B43: $mm | C43: ='Scenario_Drivers'!C121 | D43: ='Scenario_Drivers'!D121 | E43: ='Scenario_Drivers'!E121 | F43: ='Scenario_Drivers'!F121 | G43: ='Scenario_Drivers'!G121 | H43: ='Scenario_Drivers'!H121 | I43: ='Scenario_Drivers'!I121 | J43: ='Scenario_Drivers'!J121 | ... V43: ='Scenario_Drivers'!V121
A44: Acquisition fees | B44: $mm | C44: ='Scenario_Drivers'!C122 | D44: ='Scenario_Drivers'!D122 | E44: ='Scenario_Drivers'!E122 | F44: ='Scenario_Drivers'!F122 | G44: ='Scenario_Drivers'!G122 | H44: ='Scenario_Drivers'!H122 | I44: ='Scenario_Drivers'!I122 | J44: ='Scenario_Drivers'!J122 | ... V44: ='Scenario_Drivers'!V122
A45: Capitalized integration spend | B45: $mm | C45: ='Scenario_Drivers'!C129 | D45: ='Scenario_Drivers'!D129 | E45: ='Scenario_Drivers'!E129 | F45: ='Scenario_Drivers'!F129 | G45: ='Scenario_Drivers'!G129 | H45: ='Scenario_Drivers'!H129 | I45: ='Scenario_Drivers'!I129 | J45: ='Scenario_Drivers'!J129 | ... V45: ='Scenario_Drivers'!V129
A46: Cash Flow Statement
A47: Net income - CF | B47: $mm | C47: =C28 | D47: =D28 | E47: =E28 | F47: =F28 | G47: =G28 | H47: =H28 | I47: =I28 | J47: =J28 | ... V47: =V28
A48: Total D&A - CF | B48: $mm | C48: =C20 | D48: =D20 | E48: =E20 | F48: =F20 | G48: =G20 | H48: =H20 | I48: =I20 | J48: =J20 | ... V48: =V20
A49: Financing fee amortization - CF | B49: $mm | C49: =C23 | D49: =D23 | E49: =E23 | F49: =F23 | G49: =G23 | H49: =H23 | I49: =I23 | J49: =J23 | ... V49: =V23
A50: Deferred tax / non-cash tax | B50: $mm | C50: =-C26+C27 | D50: =-D26+D27 | E50: =-E26+E27 | F50: =-F26+F27 | G50: =-G26+G27 | H50: =-H26+H27 | I50: =-I26+I27 | J50: =-J26+J27 | ... V50: =-V26+V27
A51: Change in NWC - CF | B51: $mm | C51: =-C38 | D51: =-D38 | E51: =-E38 | F51: =-F38 | G51: =-G38 | H51: =-H38 | I51: =-I38 | J51: =-J38 | ... V51: =-V38
A52: Cash from operations | B52: $mm | C52: =SUM(C47:C51) | D52: =SUM(D47:D51) | E52: =SUM(E47:E51) | F52: =SUM(F47:F51) | G52: =SUM(G47:G51) | H52: =SUM(H47:H51) | I52: =SUM(I47:I51) | J52: =SUM(J47:J51) | ... V52: =SUM(V47:V51)
A53: Capital expenditure - CF | B53: $mm | C53: =-C41 | D53: =-D41 | E53: =-E41 | F53: =-F41 | G53: =-G41 | H53: =-H41 | I53: =-I41 | J53: =-J41 | ... V53: =-V41
A54: Acquisition EV - CF | B54: $mm | C54: =-C43 | D54: =-D43 | E54: =-E43 | F54: =-F43 | G54: =-G43 | H54: =-H43 | I54: =-I43 | J54: =-J43 | ... V54: =-V43
A55: Capitalized integration spend - CF | B55: $mm | C55: =-C45 | D55: =-D45 | E55: =-E45 | F55: =-F45 | G55: =-G45 | H55: =-H45 | I55: =-I45 | J55: =-J45 | ... V55: =-V45
